Workbook

Sheet REGISTRO  1- lote 9
B1: AVICOLA SAN LORENZO
B2: GRANJA : | E2: SAN LORENZO
B3: RESPONSABLE : | O3: MACHO
B5: GALPON | D5: LOTE | G5: INCUBADORA | K5: CANTIDAD INICIAL | O5: PESO PROMEDIO INIC.
B6: T1 | D6: 49 | G6: FINAVES | K6: 6578 | O6: 44
B8: FECHA INICIO | G8: 45780 | L8: DIAS DE ENGORDE: | P8: =(G9-G8)+1 -> 49
B9: FECHA TERMINACION | G9: =+PESAS!B11 -> 45828 | L9: DIAS PROMEDIO
B11: POLLOS VENDIDOS | Z11: conversion: kilos concentrado/ kilos en pie
B12: PESO TOTAL FINAL | L12: CONSUMO TOTAL DEL LOTE | Z12: se necesita xxx kilos concentrado para producir 1 kilo de pollo en pie
Z13: Entre mas bajo mejor
I14: TOTAL CONSUMO | Q14: CONSUMO POR AVE | U14: PESO
A15: KILOS CONSUMIDOS | I15: SEMANAL | M15: ACUMULADO | Q15: (Gramos) | T15: CONSUMO | U15: GRAMOS | V15: gramos | Z15: BULTOS CONSUMIDOS
A16: S/D | B16: S | C16: D | D16: L | E16: M | F16: M | G16: J | H16: V | I16: Bultos | K16: Kilos | M16: Bultos | O16: Kilos | Q16: Diario | R16: Sem. | S16: Acumul. | T16: KL. | U16: PROMEDIO | V16: Ganancia dia | W16: Conversion | X16: VPI | Z16: S/D | AA16: S | AB16: D | AC16: L | AD16: M | AE16: M | AF16: J | AG16: V | AH16: TOTAL | AL16: BULTOS CONSUMIDOS
A17: 1 | B17: =+AA17*40 -> 80 | C17: =+AB17*40 -> 80 | D17: =+AC17*40 -> 120 | E17: =+AD17*40 -> 160 | F17: =+AE17*40 -> 160 | G17: =+AF17*40 -> 200 | H17: =+AG17*40 -> 240 | I17: =+K17/40 -> 26 | K17: =SUM(B17:H17) -> 1040 | M17: =+I17 -> 26 | O17: =+K17 -> 1040 | Q17: =+R17/7 -> 23.020054 | R17: =+K17*1000/S30 -> 161.14038 | S17: =+R17 -> 161.14038 | T17: =+O17/S30 -> 0.16114038 | U17: 195 | V17: =(U17-O6)/7 -> 21.571429 | W17: =+O17/(S30*(U17/1000)) -> 0.82636091 | X17: =+U17/O6 -> 4.4318182 | Z17: 1 | AA17: 2 | AB17: 2 | AC17: 3 | AD17: 4 | AE17: 4 | AF17: 5 | AG17: 6 | AH17: =+SUM(AA17:AG17) -> 26 | AL17: S/D | AM17: S | AN17: D | AO17: L | AP17: M | AQ17: M | AR17: J | AS17: V | AT17: TOTAL
A18: 2 | B18: =+AA18*40 -> 240 | C18: =+AB18*40 -> 240 | D18: =+AC18*40 -> 280 | E18: =+AD18*40 -> 320 | F18: =+AE18*40 -> 360 | G18: =+AF18*40 -> 380 | H18: =+AG18*40 -> 400 | I18: =+K18/40 -> 55.5 | K18: =SUM(B18:H18) -> 2220 | M18: =+M17+I18 -> 81.5 | O18: =+O17+K18 -> 3260 | Q18: =+R18/7 -> 49.576811 | R18: =+K18*1000/S31 -> 347.03767 | S18: =+O18*1000/S31 -> 509.61388 | T18: =+O18/S31 -> 0.50961388 | U18: 455 | V18: =+(U18-U17)/7 -> 37.142857 | W18: =+O18/(S31*(U18/1000)) -> 1.1200305 | X18: =+U18/U17 -> 2.3333333 | Z18: 2 | AA18: 6 | AB18: 6 | AC18: 7 | AD18: 8 | AE18: 9 | AF18: 9.5 | AG18: 10 | AH18: =+SUM(AA18:AG18) -> 55.5 | AL18: 1 | AM18: 3 | AN18: 1 | AO18: 2 | AP18: 2 | AQ18: 2 | AR18: 2.5 | AS18: 2 | AT18: =+SUM(AM18:AS18) -> 14.5 | AU18: 3742
A19: 3 | B19: =+AA19*40 -> 400 | C19: =+AB19*40 -> 440 | D19: =+AC19*40 -> 480 | E19: =+AD19*40 -> 520 | F19: =+AE19*40 -> 560 | G19: =+AF19*40 -> 600 | H19: =+AG19*40 -> 600 | I19: =+K19/40 -> 90 | K19: =SUM(B19:H19) -> 3600 | M19: =+M18+I19 -> 171.5 | O19: =+O18+K19 -> 6860 | Q19: =+R19/7 -> 80.938891 | R19: =+K19*1000/S32 -> 566.57224 | S19: =+O19*1000/S32 -> 1079.6349 | T19: =+O19/S32 -> 1.0796349 | U19: 880 | V19: =+(U19-U18)/7 -> 60.714286 | W19: =+O19/(S32*(U19/1000)) -> 1.2268578 | X19: =+U19/U18 -> 1.9340659 | Z19: 3 | AA19: 10 | AB19: 11 | AC19: 12 | AD19: 13 | AE19: 14 | AF19: 15 | AG19: 15 | AH19: =+SUM(AA19:AG19) -> 90 | AL19: 2 | AM19: 3 | AN19: 3.5 | AO19: 4 | AP19: 5 | AQ19: 5 | AR19: 6 | AS19: 6 | AT19: =+SUM(AM19:AS19) -> 32.5
A20: 4 | B20: =+AA20*40 -> 680 | C20: =+AB20*40 -> 720 | D20: =+AC20*40 -> 760 | E20: =+AD20*40 -> 800 | F20: =+AE20*40 -> 840 | G20: =+AF20*40 -> 880 | H20: =+AG20*40 -> 880 | I20: =+K20/40 -> 139 | K20: =SUM(B20:H20) -> 5560 | M20: =+M19+I20 -> 310.5 | O20: =+O19+K20 -> 12420 | Q20: =+R20/7 -> 125.55892 | R20: =+K20*1000/S33 -> 878.91242 | S20: =+O20*1000/S33 -> 1963.326 | T20: =+O20/S33 -> 1.963326 | U20: 1450 | V20: =+(U20-U19)/7 -> 81.428571 | W20: =+O20/(S33*(U20/1000)) -> 1.3540179 | X20: =+U20/U19 -> 1.6477273 | Z20: 4 | AA20: 17 | AB20: 18 | AC20: 19 | AD20: 20 | AE20: 21 | AF20: 22 | AG20: 22 | AH20: =+SUM(AA20:AG20) -> 139 | AL20: 3 | AM20: 6 | AN20: 6 | AO20: 7 | AP20: 8 | AQ20: 8 | AR20: 9 | AS20: 9 | AT20: =+SUM(AM20:AS20) -> 53
A21: 5 | B21: =+AA21*40 -> 920 | C21: =+AB21*40 -> 920 | D21: =+AC21*40 -> 960 | E21: =+AD21*40 -> 1000 | F21: =+AE21*40 -> 1000 | G21: =+AF21*40 -> 1040 | H21: =+AG21*40 -> 1040 | I21: =+K21/40 -> 172 | K21: =SUM(B21:H21) -> 6880 | M21: =+M20+I21 -> 482.5 | O21: =+O20+K21 -> 19300 | Q21: =+R21/7 -> 156.90567 | R21: =+K21*1000/S34 -> 1098.3397 | S21: =+O21*1000/S34 -> 3081.0983 | T21: =+O21/S34 -> 3.0810983 | U21: 2050 | V21: =+(U21-U20)/7 -> 85.714286 | W21: =+O21/(S34*(U21/1000)) -> 1.5029748 | X21: =+U21/U20 -> 1.4137931 | Z21: 5 | AA21: 23 | AB21: 23 | AC21: 24 | AD21: 25 | AE21: 25 | AF21: 26 | AG21: 26 | AH21: =+SUM(AA21:AG21) -> 172 | AL21: 4 | AM21: 10 | AN21: 10 | AO21: 11 | AP21: 11 | AQ21: 12 | AR21: 12 | AS21: 13 | AT21: =+SUM(AM21:AS21) -> 79
A22: 6 | B22: =+AA22*40 -> 1040 | C22: =+AB22*40 -> 1040 | D22: =+AC22*40 -> 1040 | E22: =+AD22*40 -> 1040 | F22: =+AE22*40 -> 1080 | G22: =+AF22*40 -> 1080 | H22: =+AG22*40 -> 1040 | I22: =+K22/40 -> 184 | K22: =SUM(B22:H22) -> 7360 | M22: =+M21+I22 -> 666.5 | O22: =+O21+K22 -> 26660 | Q22: =+R22/7 -> 169.394 | R22: =+K22*1000/S35 -> 1185.758 | S22: =+O22*1000/S35 -> 4295.1506 | T22: =+O22/S35 -> 4.2951506 | U22: 2680 | V22: =+(U22-U21)/7 -> 90 | W22: =+O22/(S35*(U22/1000)) -> 1.6026681 | X22: =+U22/U21 -> 1.3073171 | Z22: 6 | AA22: 26 | AB22: 26 | AC22: 26 | AD22: 26 | AE22: 27 | AF22: 27 | AG22: 26 | AH22: =+SUM(AA22:AG22) -> 184 | AL22: 5 | AM22: 13 | AN22: 13 | AO22: 13 | AP22: 13 | AQ22: 13 | AR22: 13 | AS22: 13 | AT22: =+SUM(AM22:AS22) -> 91
A23: 7 | B23: =+AA23*40 -> 1040 | C23: =+AB23*40 -> 1040 | D23: =+AC23*40 -> 1000 | E23: =+AD23*40 -> 1000 | F23: =+AE23*40 -> 800 | G23: =+AF23*40 -> 720 | H23: =+AG23*40 -> 0 | I23: =+K23/40 -> 140 | K23: =SUM(B23:H23) -> 5600 | M23: =+M22+I23 -> 806.5 | O23: =+O22+K23 -> 32260 | Q23: =+R23/7 -> 129.87013 | R23: =+K23*1000/S36 -> 909.09091 | S23: =+O23*1000/S36 -> 5237.013 | T23: =+O23/S36 -> 5.237013 | V23: =+(U23-U22)/7 -> -382.85714 | W23: =+O23/(S36*(U23/1000)) -> #DIV/0! | X23: =+U23/U22 -> 0 | Z23: 7 | AA23: 26 | AB23: 26 | AC23: 25 | AD23: 25 | AE23: 20 | AF23: 18 | AH23: =+SUM(AA23:AG23) -> 140 | AL23: 6 | AM23: 15 | AN23: 15 | AO23: 15 | AP23: 15 | AQ23: 15 | AR23: 15 | AS23: 15 | AT23: =+SUM(AM23:AS23) -> 105
A24: 8 | B24: =+AA24*40 -> 0 | C24: =+AB24*40 -> 0 | D24: =+AC24*40 -> 0 | E24: =+AD24*40 -> 0 | F24: =+AE24*40 -> 0 | G24: =+AF24*40 -> 0 | H24: =+AG24*40 -> 0 | I24: =+K24/40 -> 0 | K24: =SUM(B24:H24) -> 0 | M24: =+M23+I24 -> 806.5 | O24: =+O23+K24 -> 32260 | Q24: =+R24/7 -> 0 | R24: =+K24*1000/S37 -> 0 | S24: =+O24*1000/S37 -> 5237.013 | T24: =+O24/S37 -> 5.237013 | V24: =+(U24-U23)/7 -> 0 | W24: =+O24/(S37*(U24/1000)) -> #DIV/0! | X24: =+U24/U23 -> #DIV/0! | Z24: 8 | AH24: =+SUM(AA24:AG24) -> 0 | AL24: 7 | AM24: 15 | AN24: 15 | AO24: 15 | AP24: 15 | AQ24: 15 | AT24: =+SUM(AM24:AS24) -> 75
A25: 9 | B25: =+AA25*40 -> 0 | C25: =+AB25*40 -> 0 | D25: =+AC25*40 -> 0 | E25: =+AD25*40 -> 0 | F25: =+AE25*40 -> 0 | G25: =+AF25*40 -> 0 | H25: =+AG25*40 -> 0 | I25: =+K25/40 -> 0 | K25: =SUM(B25:H25) -> 0 | M25: =+M24+I25 -> 806.5 | O25: =+O24+K25 -> 32260 | Q25: =+R25/7 -> 0 | R25: =+K25*1000/S38 -> 0 | S25: =+O25*1000/S38 -> 5237.013 | T25: =+O25/S38 -> 5.237013 | V25: =+(U25-U24)/7 -> 0 | W25: =+O25/(S38*(U25/1000)) -> #DIV/0! | X25: =+U25/U24 -> #DIV/0! | Z25: 9 | AH25: =+SUM(AA25:AG25) -> 0 | AL25: 8 | AT25: =+SUM(AM25:AS25) -> 0
AL26: 9 | AT26: =+SUM(AM26:AS26) -> 0 | AV26: =3+1+2+2.5+2+2.5+2.5 -> 15.5
I27: TOTAL MORTALIDAD Y SELECCIÓN | S27: SALDO | AT27: =+SUM(AT18:AT26) -> 450 | AU27: =454+0.5+2.5+1-8 -> 450 | AV27: =481+2.5+1+-8 -> 476.5
B28: AVES MUERTAS POR DIA | I28: Mort./sem. | K28: Selec/Sem | M28: Mort.Acum. | O28: Selec.Acum. | Q28: Mort/Selec.Ac. | S28: AVES | AV28: =481+2.5+1-8 -> 476.5
A29: S/D | B29: =+B16 -> S | C29: =+C16 -> D | D29: =+D16 -> L | E29: =+E16 -> M | F29: =+F16 -> M | G29: =+G16 -> J | H29: =+H16 -> V | I29: No.A. | J29: % | K29: No.A. | L29: % | M29: No.A. | N29: % | O29: No.A. | P29: % | Q29: No.A. | R29: % | S29: (superv.) | AL29: BULTOS CONSUMIDOS | AV29: =3+1+2+2+2+2.5+2 -> 14.5
A30: 1 | B30: =3+6 -> 9 | C30: =2+4 -> 6 | D30: =4+6 -> 10 | E30: =10+14 -> 24 | F30: =16+15 -> 31 | G30: =8+12 -> 20 | H30: =10+14 -> 24 | I30: =SUM(B30:H30) -> 124 | J30: =+I30/K6 -> 0.018850715 | M30: =+I30 -> 124 | N30: =+M30/K$6 -> 0.018850715 | Q30: =+M30+O30 -> 124 | R30: =+Q30/$K$6 -> 0.018850715 | S30: =+K6-I30-K30 -> 6454 | AL30: S/D | AM30: =+'[1]REGISTRO 1 LOTE 9'!M29 -> No.A. | AN30: =+'[1]REGISTRO 1 LOTE 9'!N29 -> % | AO30: =+'[1]REGISTRO 1 LOTE 9'!O29 -> No.A. | AP30: =+'[1]REGISTRO 1 LOTE 9'!P29 -> % | AQ30: =+'[1]REGISTRO 1 LOTE 9'!Q29 -> No.A. | AR30: =+'[1]REGISTRO 1 LOTE 9'!R29 -> % | AS30: =+'[1]REGISTRO 1 LOTE 9'!S29 -> (superv.) | AT30: TOTAL | AV30: =439+0.5+2.5+1+-8 -> 435
A31: 2 | B31: 4 | C31: 6 | D31: 7 | E31: 7 | F31: 9 | G31: 10 | H31: 14 | I31: =SUM(B31:H31) -> 57 | J31: =+I31/S30 -> 0.0088317323 | M31: =+M30+I31 -> 181 | N31: =+M31/K$6 -> 0.027515962 | Q31: =+M31+O31 -> 181 | R31: =+Q31/$K$6 -> 0.027515962 | S31: =+S30-I31-K31 -> 6397 | AL31: 1 | AM31: 3 | AN31: 1 | AO31: 2 | AP31: 2.5 | AQ31: 2 | AR31: 2.5 | AS31: 2.5 | AT31: =+SUM(AM31:AS31) -> 15.5 | AU31: 3742
A32: 3 | B32: 5 | C32: 7 | D32: 6 | E32: 8 | F32: 4 | G32: 6 | H32: 7 | I32: =SUM(B32:H32) -> 43 | J32: =+I32/S31 -> 0.0067219009 | M32: =+M31+I32 -> 224 | N32: =+M32/K$6 -> 0.034052904 | Q32: =+M32+O32 -> 224 | R32: =+Q32/$K$6 -> 0.034052904 | S32: =+S31-I32-K32 -> 6354 | AL32: 2 | AM32: 3 | AN32: 3.5 | AO32: 4 | AP32: 5 | AQ32: 5 | AR32: 6 | AS32: 6 | AT32: =+SUM(AM32:AS32) -> 32.5
A33: 4 | B33: 3 | C33: 4 | D33: 6 | E33: 3 | F33: 5 | G33: 4 | H33: 3 | I33: =SUM(B33:H33) -> 28 | J33: =+I33/S32 -> 0.004406673 | M33: =+M32+I33 -> 252 | N33: =+M33/K$6 -> 0.038309517 | Q33: =+M33+O33 -> 252 | R33: =+Q33/$K$6 -> 0.038309517 | S33: =+S32-I33-K33 -> 6326 | AL33: 3 | AM33: 6 | AN33: 6 | AO33: 7 | AP33: 8 | AQ33: 8 | AR33: 9 | AS33: 9 | AT33: =+SUM(AM33:AS33) -> 53
A34: 5 | B34: 9 | C34: 7 | D34: 8 | E34: 10 | F34: 9 | G34: 10 | H34: 9 | I34: =SUM(B34:H34) -> 62 | J34: =+I34/S33 -> 0.009800822 | M34: =+M33+I34 -> 314 | N34: =+M34/K$6 -> 0.047734874 | Q34: =+M34+O34 -> 314 | R34: =+Q34/$K$6 -> 0.047734874 | S34: =+S33-I34-K34 -> 6264 | AL34: 4 | AM34: 10 | AN34: 10 | AO34: 11 | AP34: 11 | AQ34: 12 | AR34: 12 | AS34: 13 | AT34: =+SUM(AM34:AS34) -> 79
A35: 6 | B35: 9 | C35: 6 | D35: 10 | E35: 8 | F35: 7 | G35: 8 | H35: 9 | I35: =SUM(B35:H35) -> 57 | J35: =+I35/S34 -> 0.0090996169 | M35: =+M34+I35 -> 371 | N35: =+M35/K$6 -> 0.056400122 | Q35: =+M35+O35 -> 371 | R35: =+Q35/$K$6 -> 0.056400122 | S35: =+S34-I35-K35 -> 6207 | AL35: 5 | AM35: 13 | AN35: 13 | AO35: 13 | AP35: 13 | AQ35: 13 | AR35: 13 | AS35: 13 | AT35: =+SUM(AM35:AS35) -> 91
A36: 7 | B36: 7 | C36: 8 | D36: 7 | E36: 9 | F36: 6 | G36: 4 | H36: 6 | I36: =SUM(B36:H36) -> 47 | J36: =+I36/S35 -> 0.007572096 | M36: =+M35+I36 -> 418 | N36: =+M36/K$6 -> 0.063545151 | Q36: =+M36+O36 -> 418 | R36: =+Q36/$K$6 -> 0.063545151 | S36: =+S35-I36-K36 -> 6160 | AL36: 6 | AM36: 15 | AN36: 15 | AO36: 15 | AP36: 15 | AQ36: 15 | AR36: 15 | AS36: 15 | AT36: =+SUM(AM36:AS36) -> 105
A37: 8 | I37: =SUM(B37:H37) -> 0 | J37: =+I37/S36 -> 0 | M37: =+M36+I37 -> 418 | N37: =+M37/K$6 -> 0.063545151 | Q37: =+M37+O37 -> 418 | R37: =+Q37/$K$6 -> 0.063545151 | S37: =+S36-I37-K37 -> 6160 | AL37: 7 | AM37: 15 | AN37: 15 | AO37: 15 | AP37: 15 | AQ37: 17 | AR37: 25 | AT37: =+SUM(AM37:AS37) -> 102 | AW37: =14+30+52+79+99+105+102 -> 481
A38: 9 | I38: =SUM(B38:H38) -> 0 | J38: =+I38/S37 -> 0 | M38: =+M37+I38 -> 418 | N38: =+M38/K$6 -> 0.063545151 | Q38: =+M38+O38 -> 418 | R38: =+Q38/$K$6 -> 0.063545151 | S38: =+S37-I38-K38 -> 6160 | AL38: 8 | AT38: =+SUM(AM38:AS38) -> 0
AL39: 9 | AT39: =+SUM(AM39:AS39) -> 0
B40: PESO POR AVE | E40: Aumento | G40: Conversion | I40: PROGRAMA DE VACUNACION | O40: TRATAMIENTO | AT40: =+SUM(AT31:AT39) -> 478 | AU40: =481+1.5+2.5+1-8 -> 478
A41: S/D | B41: Mach | C41: Hemb. | D41: Prom. | E41: por ave/dia | G41: alimento | I41: DIA | J41: MES | K41: VACUNA | O41: DIA | P41: MES | Q41: DROGA / DOSIS
A42: 1 | D42: =+(B42+C42)/2 -> 0 | E42: =+D42/7 -> 0 | G42: =+S17/D42 -> #DIV/0! | AL42: BULTOS CONSUMIDOS
A43: 2 | D43: =+(B43+C43)/2 -> 0 | E43: =(D43-D42)/7 -> 0 | G43: =+S18/D43 -> #DIV/0! | AL43: S/D | AM43: =+'[1]REGISTRO 1 LOTE 9'!M42 -> 0 | AN43: =+'[1]REGISTRO 1 LOTE 9'!N42 -> 0 | AO43: =+'[1]REGISTRO 1 LOTE 9'!O42 -> 0 | AP43: =+'[1]REGISTRO 1 LOTE 9'!P42 -> 0 | AQ43: =+'[1]REGISTRO 1 LOTE 9'!Q42 -> 0 | AR43: =+'[1]REGISTRO 1 LOTE 9'!R42 -> 0 | AS43: =+'[1]REGISTRO 1 LOTE 9'!S42 -> 0 | AT43: TOTAL
A44: 3 | D44: =+(B44+C44)/2 -> 0 | E44: =(D44-D43)/7 -> 0 | G44: =+S19/D44 -> #DIV/0! | AL44: 1 | AM44: 3 | AN44: 1 | AO44: 2 | AP44: 2 | AQ44: 2 | AR44: 2.5 | AS44: 2 | AT44: =+SUM(AM44:AS44) -> 14.5
A45: 4 | D45: =+(B45+C45)/2 -> 0 | E45: =(D45-D44)/7 -> 0 | G45: =+S20/D45 -> #DIV/0! | AL45: 2 | AM45: 3 | AN45: 3.5 | AO45: 4 | AP45: 5 | AQ45: 5 | AR45: 5 | AS45: 6 | AT45: =+SUM(AM45:AS45) -> 31.5 | AV45: =1.5+1.5+1.5+2+2+2.5+3 -> 14 | AW45: =1.5+1.5+1.5+2+2+2.5+3 -> 14 | AX45: =1.5+1.5+1.5+2+2+2.5+3 -> 14
A46: 5 | D46: =+(B46+C46)/2 -> 0 | E46: =(D46-D45)/7 -> 0 | G46: =+S21/D46 -> #DIV/0! | AL46: 3 | AM46: 6 | AN46: 6 | AO46: 7 | AP46: 8 | AQ46: 8 | AR46: 9 | AS46: 9 | AT46: =+SUM(AM46:AS46) -> 53 | AV46: =1.5+1.5+1.5+2+2+2.5+3 -> 14 | AW46: =3+3.5+4+4+5+5+5.5 -> 30 | AX46: =3+3.5+4+4+5+5+5.5 -> 30
A47: 6 | D47: =+(B47+C47)/2 -> 0 | E47: =(D47-D46)/7 -> 0 | G47: =+S22/D47 -> #DIV/0! | AL47: 4 | AM47: 10 | AN47: 10 | AO47: 11 | AP47: 11 | AQ47: 12 | AR47: 12 | AS47: 13 | AT47: =+SUM(AM47:AS47) -> 79 | AV47: =3+3.5+4+4+5+5+5.5 -> 30 | AW47: =6+6+7+7+8+9+9 -> 52 | AX47: =6+6+7+7+8+9+9 -> 52
A48: 7 | D48: =+(B48+C48)/2 -> 0 | E48: =(D48-D47)/7 -> 0 | G48: =+S23/D48 -> #DIV/0! | AL48: 5 | AM48: 13 | AN48: 13 | AO48: 13 | AP48: 13 | AQ48: 13 | AR48: 13 | AS48: 13 | AT48: =+SUM(AM48:AS48) -> 91 | AV48: =6+6+7+7+8+9+9 -> 52 | AW48: =10+10+11+11+12+12+13 -> 79 | AX48: =10+10+11+11+12+12+13 -> 79
A49: 8 | D49: =+(B49+C49)/2 -> 0 | E49: =(D49-D48)/7 -> 0 | G49: =+S24/D49 -> #DIV/0! | AL49: 6 | AM49: 15 | AN49: 15 | AO49: 15 | AP49: 15 | AQ49: 15 | AR49: 15 | AS49: 15 | AT49: =+SUM(AM49:AS49) -> 105 | AV49: =10+10+11+11+12+12+13 -> 79 | AW49: =13+13+14+14+15+15+15 -> 99 | AX49: =13+13+14+14+15+15+15 -> 99
A50: 9 | D50: =+(B50+C50)/2 -> 0 | E50: =(D50-D49)/7 -> 0 | G50: =+S25/D50 -> #DIV/0! | AL50: 7 | AM50: 15 | AN50: 15 | AO50: 14 | AP50: 15 | AT50: =+SUM(AM50:AS50) -> 59 | AV50: =13+13+14+14+15+15+15 -> 99 | AW50: =15*7 -> 105 | AX50: =15*7 -> 105
AL51: 8 | AT51: =+SUM(AM51:AS51) -> 0 | AV51: =15*7 -> 105 | AW51: =15*4+17+25 -> 102 | AX51: =15*5 -> 75
AL52: 9 | AT52: =+SUM(AM52:AS52) -> 0 | AV52: =15+15+15+15 -> 60
B53: GRANJA AVICOLA SAN LORENZO | AT53: =+SUM(AT44:AT52) -> 433 | AU53: =439+0.5+2.5+1-8 -> 435
B54: RESPONSABLE : | E54: =+E3 -> 0 | O54: HEMBRA | AL54: BULTOS CONSUMIDOS SEGÚN REGISTROS GALPONEROS
AL55: S/D | AM55: =+'[1]REGISTRO 1 LOTE 9'!M54 -> 0 | AN55: =+'[1]REGISTRO 1 LOTE 9'!N54 -> 0 | AO55: =+'[1]REGISTRO 1 LOTE 9'!O54 -> HEMBRA | AP55: =+'[1]REGISTRO 1 LOTE 9'!P54 -> 0 | AQ55: =+'[1]REGISTRO 1 LOTE 9'!Q54 -> 0 | AR55: =+'[1]REGISTRO 1 LOTE 9'!R54 -> 0 | AS55: =+'[1]REGISTRO 1 LOTE 9'!S54 -> 0 | AT55: TOTAL | AU55: ALDEMAR | AV55: DIF
B56: GALPON | D56: LOTE | G56: INCUBADORA | K56: CANTIDAD INICIAL | O56: PESO PROMEDIO INIC. | AL56: 1 | AM56: =+AM18+AM31+AM44 -> 9 | AN56: =+AN18+AN31+AN44 -> 3 | AO56: =+AO18+AO31+AO44 -> 6 | AP56: =+AP18+AP31+AP44 -> 6.5 | AQ56: =+AQ18+AQ31+AQ44 -> 6 | AR56: =+AR18+AR31+AR44 -> 7.5 | AS56: =+AS18+AS31+AS44 -> 6.5 | AT56: =+SUM(AM56:AS56) -> 44.5 | AU56: =+SUM(I17)+SUM('REGISTRO 2- lote 10'!I17:J17) -> 44.5 | AV56: =+AT56-AU56 -> 0
B57: =+B6 -> T1 | D57: =+D6 -> 49 | G57: =+G6 -> FINAVES | K57: 6018 | O57: 44 | AL57: 2 | AM57: =+AM19+AM32+AM45 -> 9 | AN57: =+AN19+AN32+AN45 -> 10.5 | AO57: =+AO19+AO32+AO45 -> 12 | AP57: =+AP19+AP32+AP45 -> 15 | AQ57: =+AQ19+AQ32+AQ45 -> 15 | AR57: =+AR19+AR32+AR45 -> 17 | AS57: =+AS19+AS32+AS45 -> 18 | AT57: =+SUM(AM57:AS57) -> 96.5 | AU57: =+SUM(I18)+SUM('REGISTRO 2- lote 10'!I18:J18) -> 95.5 | AV57: =+AT57-AU57 -> 1
AL58: 3 | AM58: =+AM20+AM33+AM46 -> 18 | AN58: =+AN20+AN33+AN46 -> 18 | AO58: =+AO20+AO33+AO46 -> 21 | AP58: =+AP20+AP33+AP46 -> 24 | AQ58: =+AQ20+AQ33+AQ46 -> 24 | AR58: =+AR20+AR33+AR46 -> 27 | AS58: =+AS20+AS33+AS46 -> 27 | AT58: =+SUM(AM58:AS58) -> 159 | AU58: =+SUM(I19)+SUM('REGISTRO 2- lote 10'!I19:J19) -> 157 | AV58: =+AT58-AU58 -> 2
B59: FECHA INICIO | G59: =+G8 -> 45780 | L59: DIAS DE ENGORDE: | P59: =+P8 -> 49 | AL59: 4 | AM59: =+AM21+AM34+AM47 -> 30 | AN59: =+AN21+AN34+AN47 -> 30 | AO59: =+AO21+AO34+AO47 -> 33 | AP59: =+AP21+AP34+AP47 -> 33 | AQ59: =+AQ21+AQ34+AQ47 -> 36 | AR59: =+AR21+AR34+AR47 -> 36 | AS59: =+AS21+AS34+AS47 -> 39 | AT59: =+SUM(AM59:AS59) -> 237 | AU59: =+SUM(I20)+SUM('REGISTRO 2- lote 10'!I20:J20) -> 237 | AV59: =+AT59-AU59 -> 0
B60: FECHA TERMINACION | G60: =+G9 -> 45828 | L60: DIAS PROMEDIO | P60: =+P9 -> 0 | AL60: 5 | AM60: =+AM22+AM35+AM48 -> 39 | AN60: =+AN22+AN35+AN48 -> 39 | AO60: =+AO22+AO35+AO48 -> 39 | AP60: =+AP22+AP35+AP48 -> 39 | AQ60: =+AQ22+AQ35+AQ48 -> 39 | AR60: =+AR22+AR35+AR48 -> 39 | AS60: =+AS22+AS35+AS48 -> 39 | AT60: =+SUM(AM60:AS60) -> 273 | AU60: =+SUM(I21)+SUM('REGISTRO 2- lote 10'!I21:J21) -> 292 | AV60: =+AT60-AU60 -> -19
AL61: 6 | AM61: =+AM23+AM36+AM49 -> 45 | AN61: =+AN23+AN36+AN49 -> 45 | AO61: =+AO23+AO36+AO49 -> 45 | AP61: =+AP23+AP36+AP49 -> 45 | AQ61: =+AQ23+AQ36+AQ49 -> 45 | AR61: =+AR23+AR36+AR49 -> 45 | AS61: =+AS23+AS36+AS49 -> 45 | AT61: =+SUM(AM61:AS61) -> 315 | AU61: =+SUM(I22)+SUM('REGISTRO 2- lote 10'!I22:J22) -> 315 | AV61: =+AT61-AU61 -> 0
B62: POLLOS VENDIDOS | G62: =+G11 -> 0 | Z62: conversion: kilos concentrado/ kilos en pie | AL62: 7 | AM62: =+AM24+AM37+AM50 -> 45 | AN62: =+AN24+AN37+AN50 -> 45 | AO62: =+AO24+AO37+AO50 -> 44 | AP62: =+AP24+AP37+AP50 -> 45 | AQ62: =+AQ24+AQ37+AQ50 -> 32 | AR62: =+AR24+AR37+AR50 -> 25 | AS62: =+AS24+AS37+AS50 -> 0 | AT62: =+SUM(AM62:AS62) -> 236 | AU62: =+SUM(I23)+SUM('REGISTRO 2- lote 10'!I23:J23) -> 237 | AV62: =+AT62-AU62 -> -1
B63: PESO TOTAL FINAL | G63: =+G12 -> 0 | L63: CONSUMO TOTAL DEL LOTE | Z63: se necesita xxx kilos concentrado para producir 1 kilo de pollo en pie | AL63: 8 | AT63: =+SUM(AM63:AS63) -> 0 | AU63: =+SUM(I24)+SUM('REGISTRO 2- lote 10'!I24:J24) -> 0 | AV63: =+AT63-AU63 -> 0
Z64: Entre mas bajo mejor | AL64: 9 | AT64: =+SUM(AM64:AS64) -> 0 | AU64: =+SUM(I25)+SUM('REGISTRO 2- lote 10'!I25:J25) -> 0
I65: TOTAL CONSUMO | Q65: CONSUMO POR AVE | U65: PESO | AT65: =+SUM(AT56:AT64) -> 1361 | AU65: =+SUM(AU56:AU64) -> 1378 | AV65: =+SUM(AV56:AV64) -> -17
A66: KILOS CONSUMIDOS | I66: SEMANAL | M66: ACUMULADO | Q66: (Gramos) | T66: CONSUMO | U66: GRAMOS | V66: gramos | Z66: BULTOS CONSUMIDOS
A67: S/D | B67: =+B16 -> S | C67: =+C16 -> D | D67: =+D16 -> L | E67: =+E16 -> M | F67: =+F16 -> M | G67: =+G16 -> J | H67: =+H16 -> V | I67: Bultos | K67: Kilos | M67: Bultos | O67: Kilos | Q67: Diario | R67: Sem. | S67: Acumul. | T67: KL. | U67: PROMEDIO | V67: Ganancia dia | W67: Conversion | X67: VPI | Z67: S/D | AA67: =+B67 -> S | AB67: =+C67 -> D | AC67: =+D67 -> L | AD67: =+E67 -> M | AE67: =+F67 -> M | AF67: =+G67 -> J | AG67: =+H67 -> V | AH67: TOTAL | AT67: =806.5+571.5 -> 1378 | AU67: =+AT67-AU65 -> 0
A68: 1 | B68: =+AA68*40 -> 100 | C68: =+AB68*40 -> 120 | D68: =+AC68*40 -> 120 | E68: =+AD68*40 -> 140 | F68: =+AE68*40 -> 160 | G68: =+AF68*40 -> 160 | H68: =+AG68*40 -> 160 | I68: =+K68/40 -> 24 | K68: =SUM(B68:H68) -> 960 | M68: =+I68 -> 24 | O68: =+K68 -> 960 | Q68: =+R68/7 -> 23.142568 | R68: =+K68*1000/S81 -> 161.99798 | S68: =+R68 -> 161.99798 | T68: =+O68/S81 -> 0.16199798 | V68: =(U68-O57)/7 -> -6.2857143 | W68: =+O68/(S81*(U68/1000)) -> #DIV/0! | X68: =+U68/O57 -> 0 | Z68: 1 | AA68: 2.5 | AB68: 3 | AC68: 3 | AD68: 3.5 | AE68: 4 | AF68: 4 | AG68: 4 | AH68: =+SUM(AA68:AG68) -> 24 | AT68: =+AT65-AT67 -> -17
A69: 2 | B69: =+AA69*40 -> 200 | C69: =+AB69*40 -> 220 | D69: =+AC69*40 -> 240 | E69: =+AD69*40 -> 280 | F69: =+AE69*40 -> 360 | G69: =+AF69*40 -> 360 | H69: =+AG69*40 -> 400 | I69: =+K69/40 -> 51.5 | K69: =SUM(B69:H69) -> 2060 | M69: =+M68+I69 -> 75.5 | O69: =+O68+K69 -> 3020 | Q69: =+R69/7 -> 50.031573 | R69: =+K69*1000/S82 -> 350.22101 | S69: =+O69*1000/S82 -> 513.43081 | T69: =+O69/S82 -> 0.51343081 | U69: 195 | V69: =+(U69-U68)/7 -> 27.857143 | W69: =+O69/(S82*(U69/1000)) -> 2.6329785 | X69: =+U69/U68 -> #DIV/0! | Z69: 2 | AA69: 5 | AB69: 5.5 | AC69: 6 | AD69: 7 | AE69: 9 | AF69: 9 | AG69: 10 | AH69: =+SUM(AA69:AG69) -> 51.5
A70: 3 | B70: =+AA70*40 -> 440 | C70: =+AB70*40 -> 440 | D70: =+AC70*40 -> 480 | E70: =+AD70*40 -> 480 | F70: =+AE70*40 -> 520 | G70: =+AF70*40 -> 560 | H70: =+AG70*40 -> 560 | I70: =+K70/40 -> 87 | K70: =SUM(B70:H70) -> 3480 | M70: =+M69+I70 -> 162.5 | O70: =+O69+K70 -> 6500 | Q70: =+R70/7 -> 84.82219 | R70: =+K70*1000/S83 -> 593.75533 | S70: =+O70*1000/S83 -> 1109.0258 | T70: =+O70/S83 -> 1.1090258 | U70: 455 | V70: =+(U70-U69)/7 -> 37.142857 | W70: =+O70/(S83*(U70/1000)) -> 2.4374193 | X70: =+U70/U69 -> 2.3333333 | Z70: 3 | AA70: 11 | AB70: 11 | AC70: 12 | AD70: 12 | AE70: 13 | AF70: 14 | AG70: 14 | AH70: =+SUM(AA70:AG70) -> 87 | AT70: =3+1+2+2+2+2.5+2 -> 14.5
A71: 4 | B71: =+AA71*40 -> 560 | C71: =+AB71*40 -> 600 | D71: =+AC71*40 -> 640 | E71: =+AD71*40 -> 720 | F71: =+AE71*40 -> 760 | G71: =+AF71*40 -> 760 | H71: =+AG71*40 -> 800 | I71: =+K71/40 -> 121 | K71: =SUM(B71:H71) -> 4840 | M71: =+M70+I71 -> 283.5 | O71: =+O70+K71 -> 11340 | Q71: =+R71/7 -> 118.59838 | R71: =+K71*1000/S84 -> 830.18868 | S71: =+O71*1000/S84 -> 1945.1115 | T71: =+O71/S84 -> 1.9451115 | U71: 865 | V71: =+(U71-U70)/7 -> 58.571429 | W71: =+O71/(S84*(U71/1000)) -> 2.2486838 | X71: =+U71/U70 -> 1.9010989 | Z71: 4 | AA71: 14 | AB71: 15 | AC71: 16 | AD71: 18 | AE71: 19 | AF71: 19 | AG71: 20 | AH71: =+SUM(AA71:AG71) -> 121 | AT71: =3+1+2+2.5+2+2.5+2.5 -> 15.5
A72: 5 | B72: =+AA72*40 -> 800 | C72: =+AB72*40 -> 800 | D72: =+AC72*40 -> 840 | E72: =+AD72*40 -> 840 | F72: =+AE72*40 -> 880 | G72: =+AF72*40 -> 880 | H72: =+AG72*40 -> 880 | I72: =+K72/40 -> 148 | K72: =SUM(B72:H72) -> 5920 | M72: =+M71+I72 -> 431.5 | O72: =+O71+K72 -> 17260 | Q72: =+R72/7 -> 145.71232 | R72: =+K72*1000/S85 -> 1019.9862 | S72: =+O72*1000/S85 -> 2973.8112 | T72: =+O72/S85 -> 2.9738112 | U72: 1420 | V72: =+(U72-U71)/7 -> 79.285714 | W72: =+O72/(S85*(U72/1000)) -> 2.0942332 | X72: =+U72/U71 -> 1.6416185 | Z72: 5 | AA72: 20 | AB72: 20 | AC72: 21 | AD72: 21 | AE72: 22 | AF72: 22 | AG72: 22 | AH72: =+SUM(AA72:AG72) -> 148 | AT72: =476.5+1.5 -> 478
A73: 6 | B73: =+AA73*40 -> 880 | C73: =+AB73*40 -> 880 | D73: =+AC73*40 -> 880 | E73: =+AD73*40 -> 920 | F73: =+AE73*40 -> 920 | G73: =+AF73*40 -> 920 | H73: =+AG73*40 -> 920 | I73: =+K73/40 -> 158 | K73: =SUM(B73:H73) -> 6320 | M73: =+M72+I73 -> 589.5 | O73: =+O72+K73 -> 23580 | Q73: =+R73/7 -> 156.25773 | R73: =+K73*1000/S86 -> 1093.8041 | S73: =+O73*1000/S86 -> 4080.9969 | T73: =+O73/S86 -> 4.0809969 | U73: 1890 | V73: =+(U73-U72)/7 -> 67.142857 | W73: =+O73/(S86*(U73/1000)) -> 2.1592576 | X73: =+U73/U72 -> 1.3309859 | Z73: 6 | AA73: 22 | AB73: 22 | AC73: 22 | AD73: 23 | AE73: 23 | AF73: 23 | AG73: 23 | AH73: =+SUM(AA73:AG73) -> 158 | AT73: =450+478+439 -> 1367
A74: 7 | B74: =+AA74*40 -> 920 | C74: =+AB74*40 -> 920 | D74: =+AC74*40 -> 920 | E74: =+AD74*40 -> 920 | F74: =+AE74*40 -> 920 | G74: =+AF74*40 -> 800 | H74: =+AG74*40 -> 600 | I74: =+K74/40 -> 150 | K74: =SUM(B74:H74) -> 6000 | M74: =+M73+I74 -> 739.5 | O74: =+O73+K74 -> 29580 | Q74: =+R74/7 -> 149.12019 | R74: =+K74*1000/S87 -> 1043.8413 | S74: =+O74*1000/S87 -> 5146.1378 | T74: =+O74/S87 -> 5.1461378 | U74: 2360 | V74: =+(U74-U73)/7 -> 67.142857 | W74: =+O74/(S87*(U74/1000)) -> 2.1805669 | X74: =+U74/U73 -> 1.2486772 | Z74: 7 | AA74: 23 | AB74: 23 | AC74: 23 | AD74: 23 | AE74: 23 | AF74: 20 | AG74: 15 | AH74: =+SUM(AA74:AG74) -> 150
A75: 8 | B75: =+AA75*40 -> 0 | C75: =+AB75*40 -> 0 | D75: =+AC75*40 -> 0 | E75: =+AD75*40 -> 0 | F75: =+AE75*40 -> 0 | G75: =+AF75*40 -> 0 | H75: =+AG75*40 -> 0 | I75: =+K75/40 -> 0 | K75: =SUM(B75:H75) -> 0 | M75: =+M74+I75 -> 739.5 | O75: =+O74+K75 -> 29580 | Q75: =+R75/7 -> 0 | R75: =+K75*1000/S88 -> 0 | S75: =+O75*1000/S88 -> 5146.1378 | T75: =+O75/S88 -> 5.1461378 | V75: =+(U75-U74)/7 -> -337.14286 | W75: =+O75/(S88*(U75/1000)) -> #DIV/0! | X75: =+U75/U74 -> 0 | Z75: 8 | AH75: =+SUM(AA75:AG75) -> 0
A76: 9 | B76: =+AA76*40 -> 0 | C76: =+AB76*40 -> 0 | D76: =+AC76*40 -> 0 | E76: =+AD76*40 -> 0 | F76: =+AE76*40 -> 0 | G76: =+AF76*40 -> 0 | H76: =+AG76*40 -> 0 | I76: =+K76/40 -> 0 | K76: =SUM(B76:H76) -> 0 | M76: =+M75+I76 -> 739.5 | O76: =+O75+K76 -> 29580 | Q76: =+R76/7 -> 0 | R76: =+K76*1000/S89 -> 0 | S76: =+O76*1000/S89 -> 5146.1378 | T76: =+O76/S89 -> 5.1461378 | V76: =+(U76-U75)/7 -> 0 | W76: =+O76/(S89*(U76/1000)) -> #DIV/0! | X76: =+U76/U75 -> #DIV/0! | Z76: 9 | AH76: =+SUM(AA76:AG76) -> 0
I78: TOTAL MORTALIDAD Y SELECCIÓN | S78: SALDO
B79: AVES MUERTAS POR DIA | I79: Mort./sem. | K79: Selec/Sem | M79: Mort.Acum. | O79: Selec.Acum. | Q79: Mort/Selec.Ac. | S79: AVES
A80: S/D | B80: =+B67 -> S | C80: =+C67 -> D | D80: =+D67 -> L | E80: =+E67 -> M | F80: =+F67 -> M | G80: =+G67 -> J | H80: =+H67 -> V | I80: No.A. | J80: % | K80: No.A. | L80: % | M80: No.A. | N80: % | O80: No.A. | P80: % | Q80: No.A. | R80: % | S80: (superv.)
A81: 1 | B81: =3+5 -> 8 | C81: =4+5 -> 9 | D81: =3+5 -> 8 | E81: =9+16 -> 25 | F81: =6+10 -> 16 | G81: =3+9 -> 12 | H81: =3+11 -> 14 | I81: =SUM(B81:H81) -> 92 | J81: =+I81/K57 -> 0.015287471 | M81: =+I81 -> 92 | N81: =+M81/K$57 -> 0.015287471 | Q81: =+M81+O81 -> 92 | R81: =+Q81/$K$57 -> 0.015287471 | S81: =+K57-I81-K81 -> 5926
A82: 2 | B82: 5 | C82: 6 | D82: 5 | E82: 7 | F82: 7 | G82: 5 | H82: 9 | I82: =SUM(B82:H82) -> 44 | J82: =+I82/S81 -> 0.0074249072 | M82: =+M81+I82 -> 136 | N82: =+M82/K$57 -> 0.02259887 | Q82: =+M82+O82 -> 136 | R82: =+Q82/$K$57 -> 0.02259887 | S82: =+S81-I82-K82 -> 5882
A83: 3 | B83: 2 | C83: 3 | D83: 5 | E83: 2 | F83: 2 | G83: 4 | H83: 3 | I83: =SUM(B83:H83) -> 21 | J83: =+I83/S82 -> 0.0035702142 | M83: =+M82+I83 -> 157 | N83: =+M83/K$57 -> 0.026088401 | Q83: =+M83+O83 -> 157 | R83: =+Q83/$K$57 -> 0.026088401 | S83: =+S82-I83-K83 -> 5861
A84: 4 | B84: 3 | C84: 5 | D84: 2 | E84: 6 | F84: 4 | G84: 5 | H84: 6 | I84: =SUM(B84:H84) -> 31 | J84: =+I84/S83 -> 0.0052891998 | M84: =+M83+I84 -> 188 | N84: =+M84/K$57 -> 0.031239614 | Q84: =+M84+O84 -> 188 | R84: =+Q84/$K$57 -> 0.031239614 | S84: =+S83-I84-K84 -> 5830
A85: 5 | B85: 3 | C85: 4 | D85: 2 | E85: 3 | F85: 4 | G85: 6 | H85: 4 | I85: =SUM(B85:H85) -> 26 | J85: =+I85/S84 -> 0.0044596913 | M85: =+M84+I85 -> 214 | N85: =+M85/K$57 -> 0.035559987 | Q85: =+M85+O85 -> 214 | R85: =+Q85/$K$57 -> 0.035559987 | S85: =+S84-I85-K85 -> 5804
A86: 6 | B86: 4 | C86: 5 | D86: 3 | E86: 4 | F86: 3 | G86: 4 | H86: 3 | I86: =SUM(B86:H86) -> 26 | J86: =+I86/S85 -> 0.0044796692 | M86: =+M85+I86 -> 240 | N86: =+M86/K$57 -> 0.039880359 | Q86: =+M86+O86 -> 240 | R86: =+Q86/$K$57 -> 0.039880359 | S86: =+S85-I86-K86 -> 5778
A87: 7 | B87: 4 | C87: 3 | D87: 4 | E87: 5 | F87: 6 | G87: 3 | H87: 5 | I87: =SUM(B87:H87) -> 30 | J87: =+I87/S86 -> 0.005192108 | M87: =+M86+I87 -> 270 | N87: =+M87/K$57 -> 0.044865404 | Q87: =+M87+O87 -> 270 | R87: =+Q87/$K$57 -> 0.044865404 | S87: =+S86-I87-K87 -> 5748
A88: 8 | I88: =SUM(B88:H88) -> 0 | J88: =+I88/S87 -> 0 | M88: =+M87+I88 -> 270 | N88: =+M88/K$57 -> 0.044865404 | Q88: =+M88+O88 -> 270 | R88: =+Q88/$K$57 -> 0.044865404 | S88: =+S87-I88-K88 -> 5748
A89: 9 | I89: =SUM(B89:H89) -> 0 | J89: =+I89/S88 -> 0 | M89: =+M88+I89 -> 270 | N89: =+M89/K$57 -> 0.044865404 | Q89: =+M89+O89 -> 270 | R89: =+Q89/$K$57 -> 0.044865404 | S89: =+S88-I89-K89 -> 5748
B91: PESO POR AVE | E91: Aumento | G91: Conversion | I91: PROGRAMA DE VACUNACION | O91: TRATAMIENTO
A92: S/D | B92: Mach | C92: Hemb. | D92: Prom. | E92: por ave/dia | G92: alimento | I92: DIA | J92: MES | K92: VACUNA | O92: DIA | P92: MES | Q92: DROGA / DOSIS
A93: 1 | D93: =+(B93+C93)/2 -> 0 | E93: =+D93/7 -> 0 | G93: =+S68/D93 -> #DIV/0!
A94: 2 | D94: =+(B94+C94)/2 -> 0 | E94: =(D94-D93)/7 -> 0 | G94: =+S69/D94 -> #DIV/0!
A95: 3 | D95: =+(B95+C95)/2 -> 0 | E95: =(D95-D94)/7 -> 0 | G95: =+S70/D95 -> #DIV/0!
A96: 4 | D96: =+(B96+C96)/2 -> 0 | E96: =(D96-D95)/7 -> 0 | G96: =+S71/D96 -> #DIV/0!
A97: 5 | D97: =+(B97+C97)/2 -> 0 | E97: =(D97-D96)/7 -> 0 | G97: =+S72/D97 -> #DIV/0!
A98: 6 | D98: =+(B98+C98)/2 -> 0 | E98: =(D98-D97)/7 -> 0 | G98: =+S73/D98 -> #DIV/0!
A99: 7 | D99: =+(B99+C99)/2 -> 0 | E99: =(D99-D98)/7 -> 0 | G99: =+S74/D99 -> #DIV/0!
A100: 8 | D100: =+(B100+C100)/2 -> 0 | E100: =(D100-D99)/7 -> 0 | G100: =+S75/D100 -> #DIV/0!
A101: 9 | D101: =+(B101+C101)/2 -> 0 | E101: =(D101-D100)/7 -> 0 | G101: =+S76/D101 -> #DIV/0!
B104: GRANJA AVICOLA SAN LORENZO
B105: RESPONSABLE : | E105: =+E54 -> 0 | O105: TOTAL
B107: GALPON | D107: LOTE | G107: INCUBADORA | K107: CANTIDAD INICIAL | O107: PESO PROMEDIO INIC.
B108: =+B57 -> T1 | D108: =+D57 -> 49 | G108: =+G57 -> FINAVES | K108: =+K6+K57 -> 12596
...

Sheet CONSUMO DIARIO 1
A1: GRANJA | B1: =+'REGISTRO 1- lote 9'!E2 -> SAN LORENZO
A2: GALPON: | B2: =+'REGISTRO 1- lote 9'!B6 -> T1 | C2: MACHOS | O2: HEMBRAS
A3: LOTE | B3: =+'REGISTRO 1- lote 9'!D6 -> 49
G4: CONSUMO DIARIO | S4: CONSUMO DIARIO
A5: FECHA | B5: SEMANA | C5: DIA | D5: MORTALIDAD | E5: SALIDA A PROCESO | F5: SALDO POLLITOS | G5: TOTAL KL | H5: X POLLO GR | I5: Acumul X P (gr) | J5: Peso pollito gr | K5: ganancia peso gr semanal | L5: Promedio ganancia peso gr dia | M5: CONVERSION | O5: DIA | P5: MORTALIDAD | Q5: SALIDA A PROCESO | R5: SALDO POLLITOS | S5: TOTAL KL | T5: X POLLO GR | U5: Acumul X P (gr) | V5: Peso pollito gr | W5: ganancia peso gr semanal | X5: Promedio ganancia peso gr dia | Y5: CONVERSION
A6: =+'REGISTRO 1- lote 9'!G8 -> 45780 | B6: Semana 1 | C6: 0 | F6: =+'REGISTRO 1- lote 9'!K6 -> 6578 | J6: =+'REGISTRO 1- lote 9'!O6 -> 44 | O6: 0 | R6: =+'REGISTRO 1- lote 9'!K57 -> 6018 | V6: =+'REGISTRO 1- lote 9'!O57 -> 44
A7: =+A6+1 -> 45781 | C7: 1 | D7: =+'REGISTRO 1- lote 9'!$B$30 -> 9 | F7: =+F6-D7-E7 -> 6569 | G7: =+'REGISTRO 1- lote 9'!$B$17 -> 80 | H7: =+G7*1000/F7 -> 12.178414 | I7: =+H7 -> 12.178414 | O7: 1 | P7: =+'REGISTRO 1- lote 9'!$B$81 -> 8 | R7: =+R6-P7-Q7 -> 6010 | S7: =+'REGISTRO 1- lote 9'!$B$68 -> 100 | T7: =+S7*1000/R7 -> 16.638935 | U7: =+T7 -> 16.638935
A8: =+A7+1 -> 45782 | C8: =+C7+1 -> 2 | D8: =+'REGISTRO 1- lote 9'!$C$30 -> 6 | F8: =+F7-D8-E8 -> 6563 | G8: =+'REGISTRO 1- lote 9'!$C$17 -> 80 | H8: =+G8*1000/F8 -> 12.189547 | I8: =+I7+H8 -> 24.367961 | O8: =+O7+1 -> 2 | P8: =+'REGISTRO 1- lote 9'!$C$81 -> 9 | R8: =+R7-P8-Q8 -> 6001 | S8: =+'REGISTRO 1- lote 9'!$C$68 -> 120 | T8: =+S8*1000/R8 -> 19.996667 | U8: =+U7+T8 -> 36.635602
A9: =+A8+1 -> 45783 | C9: =+C8+1 -> 3 | D9: =+'REGISTRO 1- lote 9'!$D$30 -> 10 | F9: =+F8-D9-E9 -> 6553 | G9: =+'REGISTRO 1- lote 9'!$D$17 -> 120 | H9: =+G9*1000/F9 -> 18.312223 | I9: =+I8+H9 -> 42.680185 | O9: =+O8+1 -> 3 | P9: =+'REGISTRO 1- lote 9'!$D$81 -> 8 | R9: =+R8-P9-Q9 -> 5993 | S9: =+'REGISTRO 1- lote 9'!$D$68 -> 120 | T9: =+S9*1000/R9 -> 20.023361 | U9: =+U8+T9 -> 56.658963
A10: =+A9+1 -> 45784 | C10: =+C9+1 -> 4 | D10: =+'REGISTRO 1- lote 9'!$E$30 -> 24 | F10: =+F9-D10-E10 -> 6529 | G10: =+'REGISTRO 1- lote 9'!$E$17 -> 160 | H10: =+G10*1000/F10 -> 24.50605 | I10: =+I9+H10 -> 67.186235 | O10: =+O9+1 -> 4 | P10: =+'REGISTRO 1- lote 9'!$E$81 -> 25 | R10: =+R9-P10-Q10 -> 5968 | S10: =+'REGISTRO 1- lote 9'!$E$68 -> 140 | T10: =+S10*1000/R10 -> 23.458445 | U10: =+U9+T10 -> 80.117408
A11: =+A10+1 -> 45785 | C11: =+C10+1 -> 5 | D11: =+'REGISTRO 1- lote 9'!$F$30 -> 31 | F11: =+F10-D11-E11 -> 6498 | G11: =+'REGISTRO 1- lote 9'!$F$17 -> 160 | H11: =+G11*1000/F11 -> 24.622961 | I11: =+I10+H11 -> 91.809195 | O11: =+O10+1 -> 5 | P11: =+'REGISTRO 1- lote 9'!$F$81 -> 16 | R11: =+R10-P11-Q11 -> 5952 | S11: =+'REGISTRO 1- lote 9'!$F$68 -> 160 | T11: =+S11*1000/R11 -> 26.88172 | U11: =+U10+T11 -> 106.99913
A12: =+A11+1 -> 45786 | C12: =+C11+1 -> 6 | D12: =+'REGISTRO 1- lote 9'!$G$30 -> 20 | F12: =+F11-D12-E12 -> 6478 | G12: =+'REGISTRO 1- lote 9'!$G$17 -> 200 | H12: =+G12*1000/F12 -> 30.873726 | I12: =+I11+H12 -> 122.68292 | O12: =+O11+1 -> 6 | P12: =+'REGISTRO 1- lote 9'!$G$81 -> 12 | R12: =+R11-P12-Q12 -> 5940 | S12: =+'REGISTRO 1- lote 9'!$G$68 -> 160 | T12: =+S12*1000/R12 -> 26.936027 | U12: =+U11+T12 -> 133.93516
A13: =+A12+1 -> 45787 | C13: =+C12+1 -> 7 | D13: =+'REGISTRO 1- lote 9'!$H$30 -> 24 | F13: =+F12-D13-E13 -> 6454 | G13: =+'REGISTRO 1- lote 9'!$H$17 -> 240 | H13: =+G13*1000/F13 -> 37.186241 | I13: =+I12+H13 -> 159.86916 | J13: =+'REGISTRO 1- lote 9'!U17 -> 195 | K13: =+J13-J6 -> 151 | L13: =+(J13-$J$6)/C13 -> 21.571429 | M13: =+I13/J13 -> 0.81984186 | N13: 160-190 | O13: =+O12+1 -> 7 | P13: =+'REGISTRO 1- lote 9'!$H$81 -> 14 | R13: =+R12-P13-Q13 -> 5926 | S13: =+'REGISTRO 1- lote 9'!$H$68 -> 160 | T13: =+S13*1000/R13 -> 26.999663 | U13: =+U12+T13 -> 160.93482 | V13: =+'REGISTRO 1- lote 9'!U68 -> 0 | W13: =+V13-V6 -> -44 | X13: =+(V13-$J$6)/O13 -> -6.2857143 | Y13: =+U13/V13 -> #DIV/0! | Z13: 160-185
A14: =+A13+1 -> 45788 | B14: Semana 2 | C14: =+C13+1 -> 8 | D14: =+'REGISTRO 1- lote 9'!$B$31 -> 4 | F14: =+F13-D14-E14 -> 6450 | G14: =+'REGISTRO 1- lote 9'!$B$18 -> 240 | H14: =+G14*1000/F14 -> 37.209302 | I14: =+I13+H14 -> 197.07847 | O14: =+O13+1 -> 8 | P14: =+'REGISTRO 1- lote 9'!$B$82 -> 5 | R14: =+R13-P14-Q14 -> 5921 | S14: =+'REGISTRO 1- lote 9'!$B$69 -> 200 | T14: =+S14*1000/R14 -> 33.778078 | U14: =+U13+T14 -> 194.7129
A15: =+A14+1 -> 45789 | C15: =+C14+1 -> 9 | D15: =+'REGISTRO 1- lote 9'!$C$31 -> 6 | F15: =+F14-D15-E15 -> 6444 | G15: =+'REGISTRO 1- lote 9'!$C$18 -> 240 | H15: =+G15*1000/F15 -> 37.243948 | I15: =+I14+H15 -> 234.32241 | O15: =+O14+1 -> 9 | P15: =+'REGISTRO 1- lote 9'!$C$82 -> 6 | R15: =+R14-P15-Q15 -> 5915 | S15: =+'REGISTRO 1- lote 9'!$C$69 -> 220 | T15: =+S15*1000/R15 -> 37.193576 | U15: =+U14+T15 -> 231.90647
A16: =+A15+1 -> 45790 | C16: =+C15+1 -> 10 | D16: =+'REGISTRO 1- lote 9'!$D$31 -> 7 | F16: =+F15-D16-E16 -> 6437 | G16: =+'REGISTRO 1- lote 9'!$D$18 -> 280 | H16: =+G16*1000/F16 -> 43.498524 | I16: =+I15+H16 -> 277.82094 | O16: =+O15+1 -> 10 | P16: =+'REGISTRO 1- lote 9'!$D$82 -> 5 | R16: =+R15-P16-Q16 -> 5910 | S16: =+'REGISTRO 1- lote 9'!$D$69 -> 240 | T16: =+S16*1000/R16 -> 40.609137 | U16: =+U15+T16 -> 272.51561
A17: =+A16+1 -> 45791 | C17: =+C16+1 -> 11 | D17: =+'REGISTRO 1- lote 9'!$E$31 -> 7 | F17: =+F16-D17-E17 -> 6430 | G17: =+'REGISTRO 1- lote 9'!$E$18 -> 320 | H17: =+G17*1000/F17 -> 49.766719 | I17: =+I16+H17 -> 327.58766 | O17: =+O16+1 -> 11 | P17: =+'REGISTRO 1- lote 9'!$E$82 -> 7 | R17: =+R16-P17-Q17 -> 5903 | S17: =+'REGISTRO 1- lote 9'!$E$69 -> 280 | T17: =+S17*1000/R17 -> 47.433508 | U17: =+U16+T17 -> 319.94912
A18: =+A17+1 -> 45792 | C18: =+C17+1 -> 12 | D18: =+'REGISTRO 1- lote 9'!$F$31 -> 9 | F18: =+F17-D18-E18 -> 6421 | G18: =+'REGISTRO 1- lote 9'!$F$18 -> 360 | H18: =+G18*1000/F18 -> 56.066033 | I18: =+I17+H18 -> 383.65369 | O18: =+O17+1 -> 12 | P18: =+'REGISTRO 1- lote 9'!$F$82 -> 7 | R18: =+R17-P18-Q18 -> 5896 | S18: =+'REGISTRO 1- lote 9'!$F$69 -> 360 | T18: =+S18*1000/R18 -> 61.058345 | U18: =+U17+T18 -> 381.00746
A19: =+A18+1 -> 45793 | C19: =+C18+1 -> 13 | D19: =+'REGISTRO 1- lote 9'!$G$31 -> 10 | F19: =+F18-D19-E19 -> 6411 | G19: =+'REGISTRO 1- lote 9'!$G$18 -> 380 | H19: =+G19*1000/F19 -> 59.273124 | I19: =+I18+H19 -> 442.92681 | O19: =+O18+1 -> 13 | P19: =+'REGISTRO 1- lote 9'!$G$82 -> 5 | R19: =+R18-P19-Q19 -> 5891 | S19: =+'REGISTRO 1- lote 9'!$G$69 -> 360 | T19: =+S19*1000/R19 -> 61.110168 | U19: =+U18+T19 -> 442.11763
A20: =+A19+1 -> 45794 | C20: =+C19+1 -> 14 | D20: =+'REGISTRO 1- lote 9'!$H$31 -> 14 | F20: =+F19-D20-E20 -> 6397 | G20: =+'REGISTRO 1- lote 9'!$H$18 -> 400 | H20: =+G20*1000/F20 -> 62.529311 | I20: =+I19+H20 -> 505.45612 | J20: =+'REGISTRO 1- lote 9'!U18 -> 455 | K20: =+J20-J13 -> 260 | L20: =+(J20-$J$6)/C20 -> 29.357143 | M20: =+I20/J20 -> 1.1108926 | N20: 380-390 | O20: =+O19+1 -> 14 | P20: =+'REGISTRO 1- lote 9'!$H$82 -> 9 | R20: =+R19-P20-Q20 -> 5882 | S20: =+'REGISTRO 1- lote 9'!$H$69 -> 400 | T20: =+S20*1000/R20 -> 68.00408 | U20: =+U19+T20 -> 510.12171 | V20: =+'REGISTRO 1- lote 9'!U69 -> 195 | W20: =+V20-V13 -> 195 | X20: =+(V20-$J$6)/O20 -> 10.785714 | Y20: =+U20/V20 -> 2.6160088 | Z20: 375-380
A21: =+A20+1 -> 45795 | B21: Semana 3 | C21: =+C20+1 -> 15 | D21: =+'REGISTRO 1- lote 9'!$B$32 -> 5 | F21: =+F20-D21-E21 -> 6392 | G21: =+'REGISTRO 1- lote 9'!$B$19 -> 400 | H21: =+G21*1000/F21 -> 62.578223 | I21: =+I20+H21 -> 568.03435 | O21: =+O20+1 -> 15 | P21: =+'REGISTRO 1- lote 9'!$B$83 -> 2 | R21: =+R20-P21-Q21 -> 5880 | S21: =+'REGISTRO 1- lote 9'!$B$70 -> 440 | T21: =+S21*1000/R21 -> 74.829932 | U21: =+U20+T21 -> 584.95164
A22: =+A21+1 -> 45796 | C22: =+C21+1 -> 16 | D22: =+'REGISTRO 1- lote 9'!$C$32 -> 7 | F22: =+F21-D22-E22 -> 6385 | G22: =+'REGISTRO 1- lote 9'!$C$19 -> 440 | H22: =+G22*1000/F22 -> 68.911511 | I22: =+I21+H22 -> 636.94586 | O22: =+O21+1 -> 16 | P22: =+'REGISTRO 1- lote 9'!$C$83 -> 3 | R22: =+R21-P22-Q22 -> 5877 | S22: =+'REGISTRO 1- lote 9'!$C$70 -> 440 | T22: =+S22*1000/R22 -> 74.86813 | U22: =+U21+T22 -> 659.81977
A23: =+A22+1 -> 45797 | C23: =+C22+1 -> 17 | D23: =+'REGISTRO 1- lote 9'!$D$32 -> 6 | F23: =+F22-D23-E23 -> 6379 | G23: =+'REGISTRO 1- lote 9'!$D$19 -> 480 | H23: =+G23*1000/F23 -> 75.246904 | I23: =+I22+H23 -> 712.19276 | O23: =+O22+1 -> 17 | P23: =+'REGISTRO 1- lote 9'!$D$83 -> 5 | R23: =+R22-P23-Q23 -> 5872 | S23: =+'REGISTRO 1- lote 9'!$D$70 -> 480 | T23: =+S23*1000/R23 -> 81.743869 | U23: =+U22+T23 -> 741.56364
A24: =+A23+1 -> 45798 | C24: =+C23+1 -> 18 | D24: =+'REGISTRO 1- lote 9'!$E$32 -> 8 | F24: =+F23-D24-E24 -> 6371 | G24: =+'REGISTRO 1- lote 9'!$E$19 -> 520 | H24: =+G24*1000/F24 -> 81.61984 | I24: =+I23+H24 -> 793.8126 | O24: =+O23+1 -> 18 | P24: =+'REGISTRO 1- lote 9'!$E$83 -> 2 | R24: =+R23-P24-Q24 -> 5870 | S24: =+'REGISTRO 1- lote 9'!$E$70 -> 480 | T24: =+S24*1000/R24 -> 81.771721 | U24: =+U23+T24 -> 823.33536
A25: =+A24+1 -> 45799 | C25: =+C24+1 -> 19 | D25: =+'REGISTRO 1- lote 9'!$F$32 -> 4 | F25: =+F24-D25-E25 -> 6367 | G25: =+'REGISTRO 1- lote 9'!$F$19 -> 560 | H25: =+G25*1000/F25 -> 87.95351 | I25: =+I24+H25 -> 881.76611 | O25: =+O24+1 -> 19 | P25: =+'REGISTRO 1- lote 9'!$F$83 -> 2 | R25: =+R24-P25-Q25 -> 5868 | S25: =+'REGISTRO 1- lote 9'!$F$70 -> 520 | T25: =+S25*1000/R25 -> 88.616224 | U25: =+U24+T25 -> 911.95159
A26: =+A25+1 -> 45800 | C26: =+C25+1 -> 20 | D26: =+'REGISTRO 1- lote 9'!$G$32 -> 6 | F26: =+F25-D26-E26 -> 6361 | G26: =+'REGISTRO 1- lote 9'!$G$19 -> 600 | H26: =+G26*1000/F26 -> 94.324792 | I26: =+I25+H26 -> 976.0909 | O26: =+O25+1 -> 20 | P26: =+'REGISTRO 1- lote 9'!$G$83 -> 4 | R26: =+R25-P26-Q26 -> 5864 | S26: =+'REGISTRO 1- lote 9'!$G$70 -> 560 | T26: =+S26*1000/R26 -> 95.497954 | U26: =+U25+T26 -> 1007.4495
A27: =+A26+1 -> 45801 | C27: =+C26+1 -> 21 | D27: =+'REGISTRO 1- lote 9'!$H$32 -> 7 | F27: =+F26-D27-E27 -> 6354 | G27: =+'REGISTRO 1- lote 9'!$H$19 -> 600 | H27: =+G27*1000/F27 -> 94.428706 | I27: =+I26+H27 -> 1070.5196 | J27: =+'REGISTRO 1- lote 9'!U19 -> 880 | K27: =+J27-J20 -> 425 | L27: =+(J27-$J$6)/C27 -> 39.809524 | M27: =+I27/J27 -> 1.2164996 | N27: 730-780 | O27: =+O26+1 -> 21 | P27: =+'REGISTRO 1- lote 9'!$H$83 -> 3 | R27: =+R26-P27-Q27 -> 5861 | S27: =+'REGISTRO 1- lote 9'!$H$70 -> 560 | T27: =+S27*1000/R27 -> 95.546835 | U27: =+U26+T27 -> 1102.9964 | V27: =+'REGISTRO 1- lote 9'!U70 -> 455 | W27: =+V27-V20 -> 260 | X27: =+(V27-$J$6)/O27 -> 19.571429 | Y27: =+U27/V27 -> 2.4241679 | Z27: 680-760
A28: =+A27+1 -> 45802 | B28: Semana 4 | C28: =+C27+1 -> 22 | D28: =+'REGISTRO 1- lote 9'!$B$33 -> 3 | F28: =+F27-D28-E28 -> 6351 | G28: =+'REGISTRO 1- lote 9'!$B$20 -> 680 | H28: =+G28*1000/F28 -> 107.06975 | I28: =+I27+H28 -> 1177.5894 | O28: =+O27+1 -> 22 | P28: =+'REGISTRO 1- lote 9'!$B$84 -> 3 | R28: =+R27-P28-Q28 -> 5858 | S28: =+'REGISTRO 1- lote 9'!$B$71 -> 560 | T28: =+S28*1000/R28 -> 95.595766 | U28: =+U27+T28 -> 1198.5921
A29: =+A28+1 -> 45803 | C29: =+C28+1 -> 23 | D29: =+'REGISTRO 1- lote 9'!$C$33 -> 4 | F29: =+F28-D29-E29 -> 6347 | G29: =+'REGISTRO 1- lote 9'!$C$20 -> 720 | H29: =+G29*1000/F29 -> 113.43942 | I29: =+I28+H29 -> 1291.0288 | O29: =+O28+1 -> 23 | P29: =+'REGISTRO 1- lote 9'!$C$84 -> 5 | R29: =+R28-P29-Q29 -> 5853 | S29: =+'REGISTRO 1- lote 9'!$C$71 -> 600 | T29: =+S29*1000/R29 -> 102.51153 | U29: =+U28+T29 -> 1301.1037
A30: =+A29+1 -> 45804 | C30: =+C29+1 -> 24 | D30: =+'REGISTRO 1- lote 9'!$D$33 -> 6 | F30: =+F29-D30-E30 -> 6341 | G30: =+'REGISTRO 1- lote 9'!$D$20 -> 760 | H30: =+G30*1000/F30 -> 119.85491 | I30: =+I29+H30 -> 1410.8837 | O30: =+O29+1 -> 24 | P30: =+'REGISTRO 1- lote 9'!$D$84 -> 2 | R30: =+R29-P30-Q30 -> 5851 | S30: =+'REGISTRO 1- lote 9'!$D$71 -> 640 | T30: =+S30*1000/R30 -> 109.38301 | U30: =+U29+T30 -> 1410.4867
A31: =+A30+1 -> 45805 | C31: =+C30+1 -> 25 | D31: =+'REGISTRO 1- lote 9'!$E$33 -> 3 | F31: =+F30-D31-E31 -> 6338 | G31: =+'REGISTRO 1- lote 9'!$E$20 -> 800 | H31: =+G31*1000/F31 -> 126.22278 | I31: =+I30+H31 -> 1537.1065 | O31: =+O30+1 -> 25 | P31: =+'REGISTRO 1- lote 9'!$E$84 -> 6 | R31: =+R30-P31-Q31 -> 5845 | S31: =+'REGISTRO 1- lote 9'!$E$71 -> 720 | T31: =+S31*1000/R31 -> 123.18221 | U31: =+U30+T31 -> 1533.6689
A32: =+A31+1 -> 45806 | C32: =+C31+1 -> 26 | D32: =+'REGISTRO 1- lote 9'!$F$33 -> 5 | F32: =+F31-D32-E32 -> 6333 | G32: =+'REGISTRO 1- lote 9'!$F$20 -> 840 | H32: =+G32*1000/F32 -> 132.63856 | I32: =+I31+H32 -> 1669.745 | O32: =+O31+1 -> 26 | P32: =+'REGISTRO 1- lote 9'!$F$84 -> 4 | R32: =+R31-P32-Q32 -> 5841 | S32: =+'REGISTRO 1- lote 9'!$F$71 -> 760 | T32: =+S32*1000/R32 -> 130.11471 | U32: =+U31+T32 -> 1663.7836
A33: =+A32+1 -> 45807 | C33: =+C32+1 -> 27 | D33: =+'REGISTRO 1- lote 9'!$G$33 -> 4 | F33: =+F32-D33-E33 -> 6329 | G33: =+'REGISTRO 1- lote 9'!$G$20 -> 880 | H33: =+G33*1000/F33 -> 139.0425 | I33: =+I32+H33 -> 1808.7875 | O33: =+O32+1 -> 27 | P33: =+'REGISTRO 1- lote 9'!$G$84 -> 5 | R33: =+R32-P33-Q33 -> 5836 | S33: =+'REGISTRO 1- lote 9'!$G$71 -> 760 | T33: =+S33*1000/R33 -> 130.22618 | U33: =+U32+T33 -> 1794.0098
A34: =+A33+1 -> 45808 | C34: =+C33+1 -> 28 | D34: =+'REGISTRO 1- lote 9'!$H$33 -> 3 | F34: =+F33-D34-E34 -> 6326 | G34: =+'REGISTRO 1- lote 9'!$H$20 -> 880 | H34: =+G34*1000/F34 -> 139.10844 | I34: =+I33+H34 -> 1947.896 | J34: =+'REGISTRO 1- lote 9'!U20 -> 1450 | K34: =+J34-J27 -> 570 | L34: =+(J34-$J$6)/C34 -> 50.214286 | M34: =+I34/J34 -> 1.3433765 | N34: 1210-1350 | O34: =+O33+1 -> 28 | P34: =+'REGISTRO 1- lote 9'!$H$84 -> 6 | R34: =+R33-P34-Q34 -> 5830 | S34: =+'REGISTRO 1- lote 9'!$H$71 -> 800 | T34: =+S34*1000/R34 -> 137.22127 | U34: =+U33+T34 -> 1931.231 | V34: =+'REGISTRO 1- lote 9'!U71 -> 865 | W34: =+V34-V27 -> 410 | X34: =+(V34-$J$6)/O34 -> 29.321429 | Y34: =+U34/V34 -> 2.2326371 | Z34: 1150-1320
A35: =+A34+1 -> 45809 | B35: Semana 5 | C35: =+C34+1 -> 29 | D35: =+'REGISTRO 1- lote 9'!$B$34 -> 9 | F35: =+F34-D35-E35 -> 6317 | G35: =+'REGISTRO 1- lote 9'!$B$21 -> 920 | H35: =+G35*1000/F35 -> 145.63875 | I35: =+I34+H35 -> 2093.5347 | O35: =+O34+1 -> 29 | P35: =+'REGISTRO 1- lote 9'!$B$85 -> 3 | R35: =+R34-P35-Q35 -> 5827 | S35: =+'REGISTRO 1- lote 9'!$B$72 -> 800 | T35: =+S35*1000/R35 -> 137.29192 | U35: =+U34+T35 -> 2068.523
A36: =+A35+1 -> 45810 | C36: =+C35+1 -> 30 | D36: =+'REGISTRO 1- lote 9'!$C$34 -> 7 | F36: =+F35-D36-E36 -> 6310 | G36: =+'REGISTRO 1- lote 9'!$C$21 -> 920 | H36: =+G36*1000/F36 -> 145.80032 | I36: =+I35+H36 -> 2239.3351 | O36: =+O35+1 -> 30 | P36: =+'REGISTRO 1- lote 9'!$C$85 -> 4 | R36: =+R35-P36-Q36 -> 5823 | S36: =+'REGISTRO 1- lote 9'!$C$72 -> 800 | T36: =+S36*1000/R36 -> 137.38623 | U36: =+U35+T36 -> 2205.9092
A37: =+A36+1 -> 45811 | C37: =+C36+1 -> 31 | D37: =+'REGISTRO 1- lote 9'!$D$34 -> 8 | F37: =+F36-D37-E37 -> 6302 | G37: =+'REGISTRO 1- lote 9'!$D$21 -> 960 | H37: =+G37*1000/F37 -> 152.33259 | I37: =+I36+H37 -> 2391.6676 | O37: =+O36+1 -> 31 | P37: =+'REGISTRO 1- lote 9'!$D$85 -> 2 | R37: =+R36-P37-Q37 -> 5821 | S37: =+'REGISTRO 1- lote 9'!$D$72 -> 840 | T37: =+S37*1000/R37 -> 144.3051 | U37: =+U36+T37 -> 2350.2143
A38: =+A37+1 -> 45812 | C38: =+C37+1 -> 32 | D38: =+'REGISTRO 1- lote 9'!$E$34 -> 10 | F38: =+F37-D38-E38 -> 6292 | G38: =+'REGISTRO 1- lote 9'!$E$21 -> 1000 | H38: =+G38*1000/F38 -> 158.93198 | I38: =+I37+H38 -> 2550.5996 | O38: =+O37+1 -> 32 | P38: =+'REGISTRO 1- lote 9'!$E$85 -> 3 | R38: =+R37-P38-Q38 -> 5818 | S38: =+'REGISTRO 1- lote 9'!$E$72 -> 840 | T38: =+S38*1000/R38 -> 144.37951 | U38: =+U37+T38 -> 2494.5938
A39: =+A38+1 -> 45813 | C39: =+C38+1 -> 33 | D39: =+'REGISTRO 1- lote 9'!$F$34 -> 9 | F39: =+F38-D39-E39 -> 6283 | G39: =+'REGISTRO 1- lote 9'!$F$21 -> 1000 | H39: =+G39*1000/F39 -> 159.15964 | I39: =+I38+H39 -> 2709.7593 | O39: =+O38+1 -> 33 | P39: =+'REGISTRO 1- lote 9'!$F$85 -> 4 | R39: =+R38-P39-Q39 -> 5814 | S39: =+'REGISTRO 1- lote 9'!$F$72 -> 880 | T39: =+S39*1000/R39 -> 151.35879 | U39: =+U38+T39 -> 2645.9526
A40: =+A39+1 -> 45814 | C40: =+C39+1 -> 34 | D40: =+'REGISTRO 1- lote 9'!$G$34 -> 10 | F40: =+F39-D40-E40 -> 6273 | G40: =+'REGISTRO 1- lote 9'!$G$21 -> 1040 | H40: =+G40*1000/F40 -> 165.78989 | I40: =+I39+H40 -> 2875.5492 | O40: =+O39+1 -> 34 | P40: =+'REGISTRO 1- lote 9'!$G$85 -> 6 | R40: =+R39-P40-Q40 -> 5808 | S40: =+'REGISTRO 1- lote 9'!$G$72 -> 880 | T40: =+S40*1000/R40 -> 151.51515 | U40: =+U39+T40 -> 2797.4677
A41: =+A40+1 -> 45815 | C41: =+C40+1 -> 35 | D41: =+'REGISTRO 1- lote 9'!$H$34 -> 9 | F41: =+F40-D41-E41 -> 6264 | G41: =+'REGISTRO 1- lote 9'!$H$21 -> 1040 | H41: =+G41*1000/F41 -> 166.0281 | I41: =+I40+H41 -> 3041.5772 | J41: =+'REGISTRO 1- lote 9'!U21 -> 2050 | K41: =+J41-J34 -> 600 | L41: =+(J41-$J$6)/C41 -> 57.314286 | M41: =+I41/J41 -> 1.4836962 | N41: 1880-1950 | O41: =+O40+1 -> 35 | P41: =+'REGISTRO 1- lote 9'!$H$85 -> 4 | R41: =+R40-P41-Q41 -> 5804 | S41: =+'REGISTRO 1- lote 9'!$H$72 -> 880 | T41: =+S41*1000/R41 -> 151.61957 | U41: =+U40+T41 -> 2949.0873 | V41: =+'REGISTRO 1- lote 9'!U72 -> 1420 | W41: =+V41-V34 -> 555 | X41: =+(V41-$J$6)/O41 -> 39.314286 | Y41: =+U41/V41 -> 2.0768221 | Z41: 1750-1800
A42: =+A41+1 -> 45816 | B42: Semana 6 | C42: =+C41+1 -> 36 | D42: =+'REGISTRO 1- lote 9'!$B$35 -> 9 | F42: =+F41-D42-E42 -> 6255 | G42: =+'REGISTRO 1- lote 9'!$B$22 -> 1040 | H42: =+G42*1000/F42 -> 166.26699 | I42: =+I41+H42 -> 3207.8442 | K42: =+J42-J41 -> -2050 | L42: =+(J42-$J$6)/C42 -> -1.2222222 | M42: =+I42/J42 -> #DIV/0! | N42: Sube 100-90 gr dia | O42: =+O41+1 -> 36 | P42: =+'REGISTRO 1- lote 9'!$B$86 -> 4 | R42: =+R41-P42-Q42 -> 5800 | S42: =+'REGISTRO 1- lote 9'!$B$73 -> 880 | T42: =+S42*1000/R42 -> 151.72414 | U42: =+U41+T42 -> 3100.8115 | W42: =+V42-V41 -> -1420 | X42: =+(V42-$J$6)/O42 -> -1.2222222 | Y42: =+U42/V42 -> #DIV/0! | Z42: Sube: 70gr- 80 x dia
A43: =+A42+1 -> 45817 | C43: =+C42+1 -> 37 | D43: =+'REGISTRO 1- lote 9'!$C$35 -> 6 | F43: =+F42-D43-E43 -> 6249 | G43: =+'REGISTRO 1- lote 9'!$C$22 -> 1040 | H43: =+G43*1000/F43 -> 166.42663 | I43: =+I42+H43 -> 3374.2709 | K43: =+J43-J42 -> 0 | L43: =+(J43-$J$6)/C43 -> -1.1891892 | M43: =+I43/J43 -> #DIV/0! | O43: =+O42+1 -> 37 | P43: =+'REGISTRO 1- lote 9'!$C$86 -> 5 | R43: =+R42-P43-Q43 -> 5795 | S43: =+'REGISTRO 1- lote 9'!$C$73 -> 880 | T43: =+S43*1000/R43 -> 151.85505 | U43: =+U42+T43 -> 3252.6665 | W43: =+V43-V42 -> 0 | X43: =+(V43-$J$6)/O43 -> -1.1891892 | Y43: =+U43/V43 -> #DIV/0!
A44: =+A43+1 -> 45818 | C44: =+C43+1 -> 38 | D44: =+'REGISTRO 1- lote 9'!$D$35 -> 10 | F44: =+F43-D44-E44 -> 6239 | G44: =+'REGISTRO 1- lote 9'!$D$22 -> 1040 | H44: =+G44*1000/F44 -> 166.69338 | I44: =+I43+H44 -> 3540.9642 | K44: =+J44-J43 -> 0 | L44: =+(J44-$J$6)/C44 -> -1.1578947 | M44: =+I44/J44 -> #DIV/0! | O44: =+O43+1 -> 38 | P44: =+'REGISTRO 1- lote 9'!$D$86 -> 3 | R44: =+R43-P44-Q44 -> 5792 | S44: =+'REGISTRO 1- lote 9'!$D$73 -> 880 | T44: =+S44*1000/R44 -> 151.9337 | U44: =+U43+T44 -> 3404.6002 | W44: =+V44-V43 -> 0 | X44: =+(V44-$J$6)/O44 -> -1.1578947 | Y44: =+U44/V44 -> #DIV/0!
A45: =+A44+1 -> 45819 | C45: =+C44+1 -> 39 | D45: =+'REGISTRO 1- lote 9'!$E$35 -> 8 | F45: =+F44-D45-E45 -> 6231 | G45: =+'REGISTRO 1- lote 9'!$E$22 -> 1040 | H45: =+G45*1000/F45 -> 166.9074 | I45: =+I44+H45 -> 3707.8716 | K45: =+J45-J44 -> 0 | L45: =+(J45-$J$6)/C45 -> -1.1282051 | M45: =+I45/J45 -> #DIV/0! | O45: =+O44+1 -> 39 | P45: =+'REGISTRO 1- lote 9'!$E$86 -> 4 | R45: =+R44-P45-Q45 -> 5788 | S45: =+'REGISTRO 1- lote 9'!$E$73 -> 920 | T45: =+S45*1000/R45 -> 158.94955 | U45: =+U44+T45 -> 3563.5498 | W45: =+V45-V44 -> 0 | X45: =+(V45-$J$6)/O45 -> -1.1282051 | Y45: =+U45/V45 -> #DIV/0!
A46: =+A45+1 -> 45820 | C46: =+C45+1 -> 40 | D46: =+'REGISTRO 1- lote 9'!$F$35 -> 7 | F46: =+F45-D46-E46 -> 6224 | G46: =+'REGISTRO 1- lote 9'!$F$22 -> 1080 | H46: =+G46*1000/F46 -> 173.52185 | I46: =+I45+H46 -> 3881.3935 | K46: =+J46-J45 -> 0 | L46: =+(J46-$J$6)/C46 -> -1.1 | M46: =+I46/J46 -> #DIV/0! | O46: =+O45+1 -> 40 | P46: =+'REGISTRO 1- lote 9'!$F$86 -> 3 | R46: =+R45-P46-Q46 -> 5785 | S46: =+'REGISTRO 1- lote 9'!$F$73 -> 920 | T46: =+S46*1000/R46 -> 159.03198 | U46: =+U45+T46 -> 3722.5817 | W46: =+V46-V45 -> 0 | X46: =+(V46-$J$6)/O46 -> -1.1 | Y46: =+U46/V46 -> #DIV/0!
A47: =+A46+1 -> 45821 | C47: =+C46+1 -> 41 | D47: =+'REGISTRO 1- lote 9'!$G$35 -> 8 | F47: =+F46-D47-E47 -> 6216 | G47: =+'REGISTRO 1- lote 9'!$G$22 -> 1080 | H47: =+G47*1000/F47 -> 173.74517 | I47: =+I46+H47 -> 4055.1387 | K47: =+J47-J46 -> 0 | L47: =+(J47-$J$6)/C47 -> -1.0731707 | M47: =+I47/J47 -> #DIV/0! | O47: =+O46+1 -> 41 | P47: =+'REGISTRO 1- lote 9'!$G$86 -> 4 | R47: =+R46-P47-Q47 -> 5781 | S47: =+'REGISTRO 1- lote 9'!$G$73 -> 920 | T47: =+S47*1000/R47 -> 159.14202 | U47: =+U46+T47 -> 3881.7238 | W47: =+V47-V46 -> 0 | X47: =+(V47-$J$6)/O47 -> -1.0731707 | Y47: =+U47/V47 -> #DIV/0!
A48: =+A47+1 -> 45822 | C48: =+C47+1 -> 42 | D48: =+'REGISTRO 1- lote 9'!$H$35 -> 9 | F48: =+F47-D48-E48 -> 6207 | G48: =+'REGISTRO 1- lote 9'!$H$22 -> 1040 | H48: =+G48*1000/F48 -> 167.55276 | I48: =+I47+H48 -> 4222.6914 | K48: =+J48-J47 -> 0 | L48: =+(J48-$J$6)/C48 -> -1.047619 | M48: =+I48/J48 -> #DIV/0! | O48: =+O47+1 -> 42 | P48: =+'REGISTRO 1- lote 9'!$H$86 -> 3 | R48: =+R47-P48-Q48 -> 5778 | S48: =+'REGISTRO 1- lote 9'!$H$73 -> 920 | T48: =+S48*1000/R48 -> 159.22465 | U48: =+U47+T48 -> 4040.9484 | W48: =+V48-V47 -> 0 | X48: =+(V48-$J$6)/O48 -> -1.047619 | Y48: =+U48/V48 -> #DIV/0!
A49: =+A48+1 -> 45823 | B49: Semana 7 | C49: =+C48+1 -> 43 | D49: =+'REGISTRO 1- lote 9'!$B$36 -> 7 | F49: =+F48-D49-E49 -> 6200 | G49: =+'REGISTRO 1- lote 9'!$B$23 -> 1040 | H49: =+G49*1000/F49 -> 167.74194 | I49: =+I48+H49 -> 4390.4334 | K49: =+J49-J48 -> 0 | L49: =+(J49-$J$6)/C49 -> -1.0232558 | M49: =+I49/J49 -> #DIV/0! | O49: =+O48+1 -> 43 | P49: =+'REGISTRO 1- lote 9'!$B$87 -> 4 | R49: =+R48-P49-Q49 -> 5774 | S49: =+'REGISTRO 1- lote 9'!$B$74 -> 920 | T49: =+S49*1000/R49 -> 159.33495 | U49: =+U48+T49 -> 4200.2833 | W49: =+V49-V48 -> 0 | X49: =+(V49-$J$6)/O49 -> -1.0232558 | Y49: =+U49/V49 -> #DIV/0!
A50: =+A49+1 -> 45824 | C50: =+C49+1 -> 44 | D50: =+'REGISTRO 1- lote 9'!$C$36 -> 8 | F50: =+F49-D50-E50 -> 6192 | G50: =+'REGISTRO 1- lote 9'!$C$23 -> 1040 | H50: =+G50*1000/F50 -> 167.95866 | I50: =+I49+H50 -> 4558.392 | K50: =+J50-J49 -> 0 | L50: =+(J50-$J$6)/C50 -> -1 | M50: =+I50/J50 -> #DIV/0! | O50: =+O49+1 -> 44 | P50: =+'REGISTRO 1- lote 9'!$C$87 -> 3 | R50: =+R49-P50-Q50 -> 5771 | S50: =+'REGISTRO 1- lote 9'!$C$74 -> 920 | T50: =+S50*1000/R50 -> 159.41778 | U50: =+U49+T50 -> 4359.7011 | W50: =+V50-V49 -> 0 | X50: =+(V50-$J$6)/O50 -> -1 | Y50: =+U50/V50 -> #DIV/0!
A51: =+A50+1 -> 45825 | C51: =+C50+1 -> 45 | D51: =+'REGISTRO 1- lote 9'!$D$36 -> 7 | F51: =+F50-D51-E51 -> 6185 | G51: =+'REGISTRO 1- lote 9'!$D$23 -> 1000 | H51: =+G51*1000/F51 -> 161.68149 | I51: =+I50+H51 -> 4720.0735 | K51: =+J51-J50 -> 0 | L51: =+(J51-$J$6)/C51 -> -0.97777778 | M51: =+I51/J51 -> #DIV/0! | O51: =+O50+1 -> 45 | P51: =+'REGISTRO 1- lote 9'!$D$87 -> 4 | R51: =+R50-P51-Q51 -> 5767 | S51: =+'REGISTRO 1- lote 9'!$D$74 -> 920 | T51: =+S51*1000/R51 -> 159.52835 | U51: =+U50+T51 -> 4519.2295 | W51: =+V51-V50 -> 0 | X51: =+(V51-$J$6)/O51 -> -0.97777778 | Y51: =+U51/V51 -> #DIV/0!
A52: =+A51+1 -> 45826 | C52: =+C51+1 -> 46 | D52: =+'REGISTRO 1- lote 9'!$E$36 -> 9 | F52: =+F51-D52-E52 -> 6176 | G52: =+'REGISTRO 1- lote 9'!$E$23 -> 1000 | H52: =+G52*1000/F52 -> 161.9171 | I52: =+I51+H52 -> 4881.9906 | K52: =+J52-J51 -> 0 | L52: =+(J52-$J$6)/C52 -> -0.95652174 | M52: =+I52/J52 -> #DIV/0! | O52: =+O51+1 -> 46 | P52: =+'REGISTRO 1- lote 9'!$E$87 -> 5 | R52: =+R51-P52-Q52 -> 5762 | S52: =+'REGISTRO 1- lote 9'!$E$74 -> 920 | T52: =+S52*1000/R52 -> 159.66678 | U52: =+U51+T52 -> 4678.8963 | W52: =+V52-V51 -> 0 | X52: =+(V52-$J$6)/O52 -> -0.95652174 | Y52: =+U52/V52 -> #DIV/0!
A53: =+A52+1 -> 45827 | C53: =+C52+1 -> 47 | D53: =+'REGISTRO 1- lote 9'!$F$36 -> 6 | F53: =+F52-D53-E53 -> 6170 | G53: =+'REGISTRO 1- lote 9'!$F$23 -> 800 | H53: =+G53*1000/F53 -> 129.65964 | I53: =+I52+H53 -> 5011.6503 | K53: =+J53-J52 -> 0 | L53: =+(J53-$J$6)/C53 -> -0.93617021 | M53: =+I53/J53 -> #DIV/0! | O53: =+O52+1 -> 47 | P53: =+'REGISTRO 1- lote 9'!$F$87 -> 6 | R53: =+R52-P53-Q53 -> 5756 | S53: =+'REGISTRO 1- lote 9'!$F$74 -> 920 | T53: =+S53*1000/R53 -> 159.83322 | U53: =+U52+T53 -> 4838.7295 | W53: =+V53-V52 -> 0 | X53: =+(V53-$J$6)/O53 -> -0.93617021 | Y53: =+U53/V53 -> #DIV/0!
A54: =+A53+1 -> 45828 | C54: =+C53+1 -> 48 | D54: =+'REGISTRO 1- lote 9'!$G$36 -> 4 | F54: =+F53-D54-E54 -> 6166 | G54: =+'REGISTRO 1- lote 9'!$G$23 -> 720 | H54: =+G54*1000/F54 -> 116.76938 | I54: =+I53+H54 -> 5128.4196 | K54: =+J54-J53 -> 0 | L54: =+(J54-$J$6)/C54 -> -0.91666667 | M54: =+I54/J54 -> #DIV/0! | O54: =+O53+1 -> 48 | P54: =+'REGISTRO 1- lote 9'!$G$87 -> 3 | R54: =+R53-P54-Q54 -> 5753 | S54: =+'REGISTRO 1- lote 9'!$G$74 -> 800 | T54: =+S54*1000/R54 -> 139.05788 | U54: =+U53+T54 -> 4977.7874 | W54: =+V54-V53 -> 0 | X54: =+(V54-$J$6)/O54 -> -0.91666667 | Y54: =+U54/V54 -> #DIV/0!
A55: =+A54+1 -> 45829 | C55: =+C54+1 -> 49 | D55: =+'REGISTRO 1- lote 9'!$H$36 -> 6 | F55: =+F54-D55-E55 -> 6160 | G55: =+'REGISTRO 1- lote 9'!$H$23 -> 0 | H55: =+G55*1000/F55 -> 0 | I55: =+I54+H55 -> 5128.4196 | K55: =+J55-J54 -> 0 | L55: =+(J55-$J$6)/C55 -> -0.89795918 | M55: =+I55/J55 -> #DIV/0! | O55: =+O54+1 -> 49 | P55: =+'REGISTRO 1- lote 9'!$H$87 -> 5 | R55: =+R54-P55-Q55 -> 5748 | S55: =+'REGISTRO 1- lote 9'!$H$74 -> 600 | T55: =+S55*1000/R55 -> 104.38413 | U55: =+U54+T55 -> 5082.1715 | W55: =+V55-V54 -> 0 | X55: =+(V55-$J$6)/O55 -> -0.89795918 | Y55: =+U55/V55 -> #DIV/0!
A56: =+A55+1 -> 45830 | B56: Semana 8 | C56: =+C55+1 -> 50 | D56: =+'REGISTRO 1- lote 9'!$B$37 -> 0 | F56: =+F55-D56-E56 -> 6160 | G56: =+'REGISTRO 1- lote 9'!$B$24 -> 0 | H56: =+G56*1000/F56 -> 0 | I56: =+I55+H56 -> 5128.4196 | K56: =+J56-J55 -> 0 | L56: =+(J56-$J$6)/C56 -> -0.88 | M56: =+I56/J56 -> #DIV/0! | O56: =+O55+1 -> 50 | P56: =+'REGISTRO 1- lote 9'!$B$88 -> 0 | R56: =+R55-P56-Q56 -> 5748 | S56: =+'REGISTRO 1- lote 9'!$B$75 -> 0 | T56: =+S56*1000/R56 -> 0 | U56: =+U55+T56 -> 5082.1715 | W56: =+V56-V55 -> 0 | X56: =+(V56-$J$6)/O56 -> -0.88 | Y56: =+U56/V56 -> #DIV/0!
A57: =+A56+1 -> 45831 | C57: =+C56+1 -> 51 | D57: =+'REGISTRO 1- lote 9'!$C$37 -> 0 | F57: =+F56-D57-E57 -> 6160 | G57: =+'REGISTRO 1- lote 9'!$C$24 -> 0 | H57: =+G57*1000/F57 -> 0 | I57: =+I56+H57 -> 5128.4196 | K57: =+J57-J56 -> 0 | L57: =+(J57-$J$6)/C57 -> -0.8627451 | M57: =+I57/J57 -> #DIV/0! | O57: =+O56+1 -> 51 | P57: =+'REGISTRO 1- lote 9'!$C$88 -> 0 | R57: =+R56-P57-Q57 -> 5748 | S57: =+'REGISTRO 1- lote 9'!$C$75 -> 0 | T57: =+S57*1000/R57 -> 0 | U57: =+U56+T57 -> 5082.1715 | W57: =+V57-V56 -> 0 | X57: =+(V57-$J$6)/O57 -> -0.8627451 | Y57: =+U57/V57 -> #DIV/0!
A58: =+A57+1 -> 45832 | C58: =+C57+1 -> 52 | D58: =+'REGISTRO 1- lote 9'!$D$37 -> 0 | F58: =+F57-D58-E58 -> 6160 | G58: =+'REGISTRO 1- lote 9'!$D$24 -> 0 | H58: =+G58*1000/F58 -> 0 | I58: =+I57+H58 -> 5128.4196 | K58: =+J58-J57 -> 0 | L58: =+(J58-$J$6)/C58 -> -0.84615385 | M58: =+I58/J58 -> #DIV/0! | O58: =+O57+1 -> 52 | P58: =+'REGISTRO 1- lote 9'!$D$88 -> 0 | R58: =+R57-P58-Q58 -> 5748 | S58: =+'REGISTRO 1- lote 9'!$D$75 -> 0 | T58: =+S58*1000/R58 -> 0 | U58: =+U57+T58 -> 5082.1715 | W58: =+V58-V57 -> 0 | X58: =+(V58-$J$6)/O58 -> -0.84615385 | Y58: =+U58/V58 -> #DIV/0!
A59: =+A58+1 -> 45833 | C59: =+C58+1 -> 53 | D59: =+'REGISTRO 1- lote 9'!$E$37 -> 0 | F59: =+F58-D59-E59 -> 6160 | G59: =+'REGISTRO 1- lote 9'!$E$24 -> 0 | H59: =+G59*1000/F59 -> 0 | I59: =+I58+H59 -> 5128.4196 | K59: =+J59-J58 -> 0 | L59: =+(J59-$J$6)/C59 -> -0.83018868 | M59: =+I59/J59 -> #DIV/0! | O59: =+O58+1 -> 53 | P59: =+'REGISTRO 1- lote 9'!$E$88 -> 0 | R59: =+R58-P59-Q59 -> 5748 | S59: =+'REGISTRO 1- lote 9'!$E$75 -> 0 | T59: =+S59*1000/R59 -> 0 | U59: =+U58+T59 -> 5082.1715 | W59: =+V59-V58 -> 0 | X59: =+(V59-$J$6)/O59 -> -0.83018868 | Y59: =+U59/V59 -> #DIV/0!
A60: =+A59+1 -> 45834 | C60: =+C59+1 -> 54 | D60: =+'REGISTRO 1- lote 9'!$F$37 -> 0 | F60: =+F59-D60-E60 -> 6160 | G60: =+'REGISTRO 1- lote 9'!$F$24 -> 0 | H60: =+G60*1000/F60 -> 0 | I60: =+I59+H60 -> 5128.4196 | K60: =+J60-J59 -> 0 | L60: =+(J60-$J$6)/C60 -> -0.81481481 | M60: =+I60/J60 -> #DIV/0! | O60: =+O59+1 -> 54 | P60: =+'REGISTRO 1- lote 9'!$F$88 -> 0 | R60: =+R59-P60-Q60 -> 5748 | S60: =+'REGISTRO 1- lote 9'!$F$75 -> 0 | T60: =+S60*1000/R60 -> 0 | U60: =+U59+T60 -> 5082.1715 | W60: =+V60-V59 -> 0 | X60: =+(V60-$J$6)/O60 -> -0.81481481 | Y60: =+U60/V60 -> #DIV/0!
A61: =+A60+1 -> 45835 | C61: =+C60+1 -> 55 | D61: =+'REGISTRO 1- lote 9'!$G$37 -> 0 | F61: =+F60-D61-E61 -> 6160 | G61: =+'REGISTRO 1- lote 9'!$G$24 -> 0 | H61: =+G61*1000/F61 -> 0 | I61: =+I60+H61 -> 5128.4196 | K61: =+J61-J60 -> 0 | L61: =+(J61-$J$6)/C61 -> -0.8 | M61: =+I61/J61 -> #DIV/0! | O61: =+O60+1 -> 55 | P61: =+'REGISTRO 1- lote 9'!$G$88 -> 0 | R61: =+R60-P61-Q61 -> 5748 | S61: =+'REGISTRO 1- lote 9'!$G$75 -> 0 | T61: =+S61*1000/R61 -> 0 | U61: =+U60+T61 -> 5082.1715 | W61: =+V61-V60 -> 0 | X61: =+(V61-$J$6)/O61 -> -0.8 | Y61: =+U61/V61 -> #DIV/0!
A62: =+A61+1 -> 45836 | C62: =+C61+1 -> 56 | D62: =+'REGISTRO 1- lote 9'!$H$37 -> 0 | F62: =+F61-D62-E62 -> 6160 | G62: =+'REGISTRO 1- lote 9'!$H$24 -> 0 | H62: =+G62*1000/F62 -> 0 | I62: =+I61+H62 -> 5128.4196 | K62: =+J62-J61 -> 0 | L62: =+(J62-$J$6)/C62 -> -0.78571429 | M62: =+I62/J62 -> #DIV/0! | O62: =+O61+1 -> 56 | P62: =+'REGISTRO 1- lote 9'!$H$88 -> 0 | R62: =+R61-P62-Q62 -> 5748 | S62: =+'REGISTRO 1- lote 9'!$H$75 -> 0 | T62: =+S62*1000/R62 -> 0 | U62: =+U61+T62 -> 5082.1715 | W62: =+V62-V61 -> 0 | X62: =+(V62-$J$6)/O62 -> -0.78571429 | Y62: =+U62/V62 -> #DIV/0!
A63: =+A62+1 -> 45837 | B63: Semana 9 | C63: =+C62+1 -> 57 | D63: =+'REGISTRO 1- lote 9'!$B$38 -> 0 | F63: =+F62-D63-E63 -> 6160 | G63: =+'REGISTRO 1- lote 9'!$B$25 -> 0 | H63: =+G63*1000/F63 -> 0 | I63: =+I62+H63 -> 5128.4196 | K63: =+J63-J62 -> 0 | L63: =+(J63-$J$6)/C63 -> -0.77192982 | M63: =+I63/J63 -> #DIV/0! | O63: =+O62+1 -> 57 | P63: =+'REGISTRO 1- lote 9'!$B$89 -> 0 | R63: =+R62-P63-Q63 -> 5748 | S63: =+'REGISTRO 1- lote 9'!$B$76 -> 0 | T63: =+S63*1000/R63 -> 0 | U63: =+U62+T63 -> 5082.1715 | W63: =+V63-V62 -> 0 | X63: =+(V63-$J$6)/O63 -> -0.77192982 | Y63: =+U63/V63 -> #DIV/0!
A64: =+A63+1 -> 45838 | C64: =+C63+1 -> 58 | D64: =+'REGISTRO 1- lote 9'!$C$38 -> 0 | F64: =+F63-D64-E64 -> 6160 | G64: =+'REGISTRO 1- lote 9'!$C$25 -> 0 | H64: =+G64*1000/F64 -> 0 | I64: =+I63+H64 -> 5128.4196 | K64: =+J64-J63 -> 0 | L64: =+(J64-$J$6)/C64 -> -0.75862069 | M64: =+I64/J64 -> #DIV/0! | O64: =+O63+1 -> 58 | P64: =+'REGISTRO 1- lote 9'!$C$89 -> 0 | R64: =+R63-P64-Q64 -> 5748 | S64: =+'REGISTRO 1- lote 9'!$C$76 -> 0 | T64: =+S64*1000/R64 -> 0 | U64: =+U63+T64 -> 5082.1715 | W64: =+V64-V63 -> 0 | X64: =+(V64-$J$6)/O64 -> -0.75862069 | Y64: =+U64/V64 -> #DIV/0!
A65: =+A64+1 -> 45839 | C65: =+C64+1 -> 59 | D65: =+'REGISTRO 1- lote 9'!$D$38 -> 0 | F65: =+F64-D65-E65 -> 6160 | G65: =+'REGISTRO 1- lote 9'!$D$25 -> 0 | H65: =+G65*1000/F65 -> 0 | I65: =+I64+H65 -> 5128.4196 | K65: =+J65-J64 -> 0 | L65: =+(J65-$J$6)/C65 -> -0.74576271 | M65: =+I65/J65 -> #DIV/0! | O65: =+O64+1 -> 59 | P65: =+'REGISTRO 1- lote 9'!$D$89 -> 0 | R65: =+R64-P65-Q65 -> 5748 | S65: =+'REGISTRO 1- lote 9'!$D$76 -> 0 | T65: =+S65*1000/R65 -> 0 | U65: =+U64+T65 -> 5082.1715 | W65: =+V65-V64 -> 0 | X65: =+(V65-$J$6)/O65 -> -0.74576271 | Y65: =+U65/V65 -> #DIV/0!
A66: =+A65+1 -> 45840 | C66: =+C65+1 -> 60 | D66: =+'REGISTRO 1- lote 9'!$E$38 -> 0 | F66: =+F65-D66-E66 -> 6160 | G66: =+'REGISTRO 1- lote 9'!$E$25 -> 0 | H66: =+G66*1000/F66 -> 0 | I66: =+I65+H66 -> 5128.4196 | K66: =+J66-J65 -> 0 | L66: =+(J66-$J$6)/C66 -> -0.73333333 | M66: =+I66/J66 -> #DIV/0! | O66: =+O65+1 -> 60 | P66: =+'REGISTRO 1- lote 9'!$E$89 -> 0 | R66: =+R65-P66-Q66 -> 5748 | S66: =+'REGISTRO 1- lote 9'!$E$76 -> 0 | T66: =+S66*1000/R66 -> 0 | U66: =+U65+T66 -> 5082.1715 | W66: =+V66-V65 -> 0 | X66: =+(V66-$J$6)/O66 -> -0.73333333 | Y66: =+U66/V66 -> #DIV/0!
A67: =+A66+1 -> 45841 | C67: =+C66+1 -> 61 | D67: =+'REGISTRO 1- lote 9'!$F$38 -> 0 | F67: =+F66-D67-E67 -> 6160 | G67: =+'REGISTRO 1- lote 9'!$F$25 -> 0 | H67: =+G67*1000/F67 -> 0 | I67: =+I66+H67 -> 5128.4196 | K67: =+J67-J66 -> 0 | L67: =+(J67-$J$6)/C67 -> -0.72131148 | M67: =+I67/J67 -> #DIV/0! | O67: =+O66+1 -> 61 | P67: =+'REGISTRO 1- lote 9'!$F$89 -> 0 | R67: =+R66-P67-Q67 -> 5748 | S67: =+'REGISTRO 1- lote 9'!$F$76 -> 0 | T67: =+S67*1000/R67 -> 0 | U67: =+U66+T67 -> 5082.1715 | W67: =+V67-V66 -> 0 | X67: =+(V67-$J$6)/O67 -> -0.72131148 | Y67: =+U67/V67 -> #DIV/0!
A68: =+A67+1 -> 45842 | C68: =+C67+1 -> 62 | D68: =+'REGISTRO 1- lote 9'!$G$38 -> 0 | F68: =+F67-D68-E68 -> 6160 | G68: =+'REGISTRO 1- lote 9'!$G$25 -> 0 | H68: =+G68*1000/F68 -> 0 | I68: =+I67+H68 -> 5128.4196 | K68: =+J68-J67 -> 0 | L68: =+(J68-$J$6)/C68 -> -0.70967742 | M68: =+I68/J68 -> #DIV/0! | O68: =+O67+1 -> 62 | P68: =+'REGISTRO 1- lote 9'!$G$89 -> 0 | R68: =+R67-P68-Q68 -> 5748 | S68: =+'REGISTRO 1- lote 9'!$G$76 -> 0 | T68: =+S68*1000/R68 -> 0 | U68: =+U67+T68 -> 5082.1715 | W68: =+V68-V67 -> 0 | X68: =+(V68-$J$6)/O68 -> -0.70967742 | Y68: =+U68/V68 -> #DIV/0!
A69: =+A68+1 -> 45843 | C69: =+C68+1 -> 63 | D69: =+'REGISTRO 1- lote 9'!$H$38 -> 0 | F69: =+F68-D69-E69 -> 6160 | G69: =+'REGISTRO 1- lote 9'!$H$25 -> 0 | H69: =+G69*1000/F69 -> 0 | I69: =+I68+H69 -> 5128.4196 | K69: =+J69-J68 -> 0 | L69: =+(J69-$J$6)/C69 -> -0.6984127 | M69: =+I69/J69 -> #DIV/0! | O69: =+O68+1 -> 63 | P69: =+'REGISTRO 1- lote 9'!$H$89 -> 0 | R69: =+R68-P69-Q69 -> 5748 | S69: =+'REGISTRO 1- lote 9'!$H$76 -> 0 | T69: =+S69*1000/R69 -> 0 | U69: =+U68+T69 -> 5082.1715 | W69: =+V69-V68 -> 0 | X69: =+(V69-$J$6)/O69 -> -0.6984127 | Y69: =+U69/V69 -> #DIV/0!
E70: TOTAL | F70: =+F69 -> 6160 | G70: =+SUM(G6:G69) -> 32260 | Q70: TOTAL | R70: =+R69 -> 5748 | S70: =+SUM(S6:S69) -> 29580 | Y70: TOTAL | Z70: =+F70+R70 -> 11908 | AA70: =+G70+S70 -> 61840
E71: CONSUMO X POLLO | G71: =+G70/F70 -> 5.237013 | Q71: CONSUMO X POLLO | S71: =+S70/R70 -> 5.1461378 | Y71: CONSUMO X POLLO | AA71: =+AA70/Z70 -> 5.1931475

Sheet REGISTRO 2- lote 10
B1: AVICOLA SAN LORENZO
B2: GRANJA : | E2: =+'REGISTRO 1- lote 9'!E2 -> SAN LORENZO
B3: RESPONSABLE : | E3: =+'REGISTRO 1- lote 9'!E3 -> 0 | O3: MACHO
B5: GALPON | D5: LOTE | G5: INCUBADORA | K5: CANTIDAD INICIAL | O5: PESO PROMEDIO INIC.
B6: =+'REGISTRO 1- lote 9'!B6:C6 -> T1 | D6: =+'REGISTRO 1- lote 9'!D6:E6 -> 49 | G6: =+'REGISTRO 1- lote 9'!G6:J6 -> FINAVES | K6: 4660 | O6: 44
B8: FECHA INICIO | G8: =+'REGISTRO 1- lote 9'!G8:J8 -> 45780 | L8: DIAS DE ENGORDE: | P8: =(G9-G8)+1 -> 52
B9: FECHA TERMINACION | G9: =+PESAS!B19 -> 45831 | L9: DIAS PROMEDIO | P9: =+#REF! -> #REF!
B11: POLLOS VENDIDOS | Z11: conversion: kilos concentrado/ kilos en pie
B12: PESO TOTAL FINAL | L12: CONSUMO TOTAL DEL LOTE | Z12: se necesita xxx kilos concentrado para producir 1 kilo de pollo en pie
Z13: Entre mas bajo mejor
I14: TOTAL CONSUMO | Q14: CONSUMO POR AVE | U14: PESO
A15: KILOS CONSUMIDOS | I15: SEMANAL | M15: ACUMULADO | Q15: (Gramos) | T15: CONSUMO | U15: GRAMOS | V15: gramos | Z15: BULTOS CONSUMIDOS
A16: S/D | B16: =+'REGISTRO 1- lote 9'!B16 -> S | C16: =+'REGISTRO 1- lote 9'!C16 -> D | D16: =+'REGISTRO 1- lote 9'!D16 -> L | E16: =+'REGISTRO 1- lote 9'!E16 -> M | F16: =+'REGISTRO 1- lote 9'!F16 -> M | G16: =+'REGISTRO 1- lote 9'!G16 -> J | H16: =+'REGISTRO 1- lote 9'!H16 -> V | I16: Bultos | K16: Kilos | M16: Bultos | O16: Kilos | Q16: Diario | R16: Sem. | S16: Acumul. | T16: KL. | U16: PROMEDIO | V16: Ganancia dia | W16: Conversion | X16: VPI | Z16: S/D | AA16: =+B16 -> S | AB16: =+C16 -> D | AC16: =+D16 -> L | AD16: =+E16 -> M | AE16: =+F16 -> M | AF16: =+G16 -> J | AG16: =+H16 -> V | AH16: TOTAL
A17: 1 | B17: =+AA17*40 -> 80 | C17: =+AB17*40 -> 80 | D17: =+AC17*40 -> 80 | E17: =+AD17*40 -> 100 | F17: =+AE17*40 -> 120 | G17: =+AF17*40 -> 120 | H17: =+AG17*40 -> 160 | I17: =+K17/40 -> 18.5 | K17: =SUM(B17:H17) -> 740 | M17: =+I17 -> 18.5 | O17: =+K17 -> 740 | Q17: =+R17/7 -> 23.132229 | R17: =+K17*1000/S30 -> 161.9256 | S17: =+R17 -> 161.9256 | T17: =+O17/S30 -> 0.1619256 | U17: 193 | V17: =(U17-O6)/7 -> 21.285714 | W17: =+O17/(S30*(U17/1000)) -> 0.83899276 | X17: =+U17/O6 -> 4.3863636 | Z17: 1 | AA17: 2 | AB17: 2 | AC17: 2 | AD17: 2.5 | AE17: 3 | AF17: 3 | AG17: 4 | AH17: =+SUM(AA17:AG17) -> 18.5
A18: 2 | B18: =+AA18*40 -> 160 | C18: =+AB18*40 -> 160 | D18: =+AC18*40 -> 200 | E18: =+AD18*40 -> 240 | F18: =+AE18*40 -> 240 | G18: =+AF18*40 -> 280 | H18: =+AG18*40 -> 320 | I18: =+K18/40 -> 40 | K18: =SUM(B18:H18) -> 1600 | M18: =+M17+I18 -> 58.5 | O18: =+O17+K18 -> 2340 | Q18: =+R18/7 -> 50.368318 | R18: =+K18*1000/S31 -> 352.57823 | S18: =+O18*1000/S31 -> 515.64566 | T18: =+O18/S31 -> 0.51564566 | U18: 455 | V18: =+(U18-U17)/7 -> 37.428571 | W18: =+O18/(S31*(U18/1000)) -> 1.1332872 | X18: =+U18/U17 -> 2.357513 | Z18: 2 | AA18: 4 | AB18: 4 | AC18: 5 | AD18: 6 | AE18: 6 | AF18: 7 | AG18: 8 | AH18: =+SUM(AA18:AG18) -> 40
A19: 3 | B19: =+AA19*40 -> 320 | C19: =+AB19*40 -> 320 | D19: =+AC19*40 -> 360 | E19: =+AD19*40 -> 360 | F19: =+AE19*40 -> 400 | G19: =+AF19*40 -> 440 | H19: =+AG19*40 -> 480 | I19: =+K19/40 -> 67 | K19: =SUM(B19:H19) -> 2680 | M19: =+M18+I19 -> 125.5 | O19: =+O18+K19 -> 5020 | Q19: =+R19/7 -> 84.721651 | R19: =+K19*1000/S32 -> 593.05156 | S19: =+O19*1000/S32 -> 1110.8652 | T19: =+O19/S32 -> 1.1108652 | U19: 880 | V19: =+(U19-U18)/7 -> 60.714286 | W19: =+O19/(S32*(U19/1000)) -> 1.2623469 | X19: =+U19/U18 -> 1.9340659 | Z19: 3 | AA19: 8 | AB19: 8 | AC19: 9 | AD19: 9 | AE19: 10 | AF19: 11 | AG19: 12 | AH19: =+SUM(AA19:AG19) -> 67
A20: 4 | B20: =+AA20*40 -> 480 | C20: =+AB20*40 -> 480 | D20: =+AC20*40 -> 520 | E20: =+AD20*40 -> 560 | F20: =+AE20*40 -> 600 | G20: =+AF20*40 -> 640 | H20: =+AG20*40 -> 640 | I20: =+K20/40 -> 98 | K20: =SUM(B20:H20) -> 3920 | M20: =+M19+I20 -> 223.5 | O20: =+O19+K20 -> 8940 | Q20: =+R20/7 -> 124.49978 | R20: =+K20*1000/S33 -> 871.49844 | S20: =+O20*1000/S33 -> 1987.55 | T20: =+O20/S33 -> 1.98755 | U20: 1450 | V20: =+(U20-U19)/7 -> 81.428571 | W20: =+O20/(S33*(U20/1000)) -> 1.3707242 | X20: =+U20/U19 -> 1.6477273 | Z20: 4 | AA20: 12 | AB20: 12 | AC20: 13 | AD20: 14 | AE20: 15 | AF20: 16 | AG20: 16 | AH20: =+SUM(AA20:AG20) -> 98
A21: 5 | B21: =+AA21*40 -> 640 | C21: =+AB21*40 -> 640 | D21: =+AC21*40 -> 680 | E21: =+AD21*40 -> 680 | F21: =+AE21*40 -> 720 | G21: =+AF21*40 -> 720 | H21: =+AG21*40 -> 720 | I21: =+K21/40 -> 120 | K21: =SUM(B21:H21) -> 4800 | M21: =+M20+I21 -> 343.5 | O21: =+O20+K21 -> 13740 | Q21: =+R21/7 -> 153.57543 | R21: =+K21*1000/S34 -> 1075.028 | S21: =+O21*1000/S34 -> 3077.2676 | T21: =+O21/S34 -> 3.0772676 | U21: 8040 | V21: =+(U21-U20)/7 -> 941.42857 | W21: =+O21/(S34*(U21/1000)) -> 0.38274473 | X21: =+U21/U20 -> 5.5448276 | Z21: 5 | AA21: 16 | AB21: 16 | AC21: 17 | AD21: 17 | AE21: 18 | AF21: 18 | AG21: 18 | AH21: =+SUM(AA21:AG21) -> 120
A22: 6 | B22: =+AA22*40 -> 720 | C22: =+AB22*40 -> 720 | D22: =+AC22*40 -> 760 | E22: =+AD22*40 -> 760 | F22: =+AE22*40 -> 760 | G22: =+AF22*40 -> 760 | H22: =+AG22*40 -> 760 | I22: =+K22/40 -> 131 | K22: =SUM(B22:H22) -> 5240 | M22: =+M21+I22 -> 474.5 | O22: =+O21+K22 -> 18980 | Q22: =+R22/7 -> 168.9015 | R22: =+K22*1000/S35 -> 1182.3105 | S22: =+O22*1000/S35 -> 4282.491 | T22: =+O22/S35 -> 4.282491 | U22: 2660 | V22: =+(U22-U21)/7 -> -768.57143 | W22: =+O22/(S35*(U22/1000)) -> 1.609959 | X22: =+U22/U21 -> 0.33084577 | Z22: 6 | AA22: 18 | AB22: 18 | AC22: 19 | AD22: 19 | AE22: 19 | AF22: 19 | AG22: 19 | AH22: =+SUM(AA22:AG22) -> 131
A23: 7 | B23: =+AA23*40 -> 720 | C23: =+AB23*40 -> 720 | D23: =+AC23*40 -> 720 | E23: =+AD23*40 -> 720 | F23: =+AE23*40 -> 600 | G23: =+AF23*40 -> 400 | H23: =+AG23*40 -> 0 | I23: =+K23/40 -> 97 | K23: =SUM(B23:H23) -> 3880 | M23: =+M22+I23 -> 571.5 | O23: =+O22+K23 -> 22860 | Q23: =+R23/7 -> 126.03131 | R23: =+K23*1000/S36 -> 882.21919 | S23: =+O23*1000/S36 -> 5197.8172 | T23: =+O23/S36 -> 5.1978172 | V23: =+(U23-U22)/7 -> -380 | W23: =+O23/(S36*(U23/1000)) -> #DIV/0! | X23: =+U23/U22 -> 0 | Z23: 7 | AA23: 18 | AB23: 18 | AC23: 18 | AD23: 18 | AE23: 15 | AF23: 10 | AH23: =+SUM(AA23:AG23) -> 97
A24: 8 | B24: =+AA24*40 -> 0 | C24: =+AB24*40 -> 0 | D24: =+AC24*40 -> 0 | E24: =+AD24*40 -> 0 | F24: =+AE24*40 -> 0 | G24: =+AF24*40 -> 0 | H24: =+AG24*40 -> 0 | I24: =+K24/40 -> 0 | K24: =SUM(B24:H24) -> 0 | M24: =+M23+I24 -> 571.5 | O24: =+O23+K24 -> 22860 | Q24: =+R24/7 -> 0 | R24: =+K24*1000/S37 -> 0 | S24: =+O24*1000/S37 -> 5197.8172 | T24: =+O24/S37 -> 5.1978172 | V24: =+(U24-U23)/7 -> 0 | W24: =+O24/(S37*(U24/1000)) -> #DIV/0! | X24: =+U24/U23 -> #DIV/0! | Z24: 8 | AH24: =+SUM(AA24:AG24) -> 0
A25: 9 | B25: =+AA25*40 -> 0 | C25: =+AB25*40 -> 0 | D25: =+AC25*40 -> 0 | E25: =+AD25*40 -> 0 | F25: =+AE25*40 -> 0 | G25: =+AF25*40 -> 0 | H25: =+AG25*40 -> 0 | I25: =+K25/40 -> 0 | K25: =SUM(B25:H25) -> 0 | M25: =+M24+I25 -> 571.5 | O25: =+O24+K25 -> 22860 | Q25: =+R25/7 -> 0 | R25: =+K25*1000/S38 -> 0 | S25: =+O25*1000/S38 -> 5197.8172 | T25: =+O25/S38 -> 5.1978172 | V25: =+(U25-U24)/7 -> 0 | W25: =+O25/(S38*(U25/1000)) -> #DIV/0! | X25: =+U25/U24 -> #DIV/0! | Z25: 9 | AH25: =+SUM(AA25:AG25) -> 0
I27: TOTAL MORTALIDAD Y SELECCIÓN | S27: SALDO
B28: AVES MUERTAS POR DIA | I28: Mort./sem. | K28: Selec/Sem | M28: Mort.Acum. | O28: Selec.Acum. | Q28: Mort/Selec.Ac. | S28: AVES
A29: S/D | B29: =+B16 -> S | C29: =+C16 -> D | D29: =+D16 -> L | E29: =+E16 -> M | F29: =+F16 -> M | G29: =+G16 -> J | H29: =+H16 -> V | I29: No.A. | J29: % | K29: No.A. | L29: % | M29: No.A. | N29: % | O29: No.A. | P29: % | Q29: No.A. | R29: % | S29: (superv.)
A30: 1 | B30: =2+4 -> 6 | C30: =2+4 -> 6 | D30: =3+7 -> 10 | E30: =7+11 -> 18 | F30: 16 | G30: =9+7 -> 16 | H30: 18 | I30: =SUM(B30:H30) -> 90 | J30: =+I30/K6 -> 0.019313305 | M30: =+I30 -> 90 | N30: =+M30/K$6 -> 0.019313305 | Q30: =+M30+O30 -> 90 | R30: =+Q30/$K$6 -> 0.019313305 | S30: =+K6-I30-K30 -> 4570
A31: 2 | B31: 3 | C31: 4 | D31: 6 | E31: 5 | F31: 3 | G31: 4 | H31: 7 | I31: =SUM(B31:H31) -> 32 | J31: =+I31/S30 -> 0.0070021882 | M31: =+M30+I31 -> 122 | N31: =+M31/K$6 -> 0.026180258 | Q31: =+M31+O31 -> 122 | R31: =+Q31/$K$6 -> 0.026180258 | S31: =+S30-I31-K31 -> 4538
A32: 3 | B32: 3 | C32: 2 | D32: 3 | E32: 1 | F32: 4 | G32: 3 | H32: 3 | I32: =SUM(B32:H32) -> 19 | J32: =+I32/S31 -> 0.0041868665 | M32: =+M31+I32 -> 141 | N32: =+M32/K$6 -> 0.030257511 | Q32: =+M32+O32 -> 141 | R32: =+Q32/$K$6 -> 0.030257511 | S32: =+S31-I32-K32 -> 4519
A33: 4 | B33: 2 | C33: 1 | D33: 3 | E33: 2 | F33: 4 | G33: 3 | H33: 6 | I33: =SUM(B33:H33) -> 21 | J33: =+I33/S32 -> 0.0046470458 | M33: =+M32+I33 -> 162 | N33: =+M33/K$6 -> 0.034763948 | Q33: =+M33+O33 -> 162 | R33: =+Q33/$K$6 -> 0.034763948 | S33: =+S32-I33-K33 -> 4498
A34: 5 | B34: 4 | C34: 4 | D34: 6 | E34: 3 | F34: 4 | G34: 7 | H34: 5 | I34: =SUM(B34:H34) -> 33 | J34: =+I34/S33 -> 0.007336594 | M34: =+M33+I34 -> 195 | N34: =+M34/K$6 -> 0.041845494 | Q34: =+M34+O34 -> 195 | R34: =+Q34/$K$6 -> 0.041845494 | S34: =+S33-I34-K34 -> 4465
A35: 6 | B35: 3 | C35: 4 | D35: 5 | E35: 6 | F35: 5 | G35: 4 | H35: 6 | I35: =SUM(B35:H35) -> 33 | J35: =+I35/S34 -> 0.0073908175 | M35: =+M34+I35 -> 228 | N35: =+M35/K$6 -> 0.048927039 | Q35: =+M35+O35 -> 228 | R35: =+Q35/$K$6 -> 0.048927039 | S35: =+S34-I35-K35 -> 4432
A36: 7 | B36: 4 | C36: 5 | D36: 6 | E36: 5 | F36: 4 | G36: 4 | H36: 6 | I36: =SUM(B36:H36) -> 34 | J36: =+I36/S35 -> 0.0076714801 | M36: =+M35+I36 -> 262 | N36: =+M36/K$6 -> 0.056223176 | Q36: =+M36+O36 -> 262 | R36: =+Q36/$K$6 -> 0.056223176 | S36: =+S35-I36-K36 -> 4398
A37: 8 | I37: =SUM(B37:H37) -> 0 | J37: =+I37/S36 -> 0 | M37: =+M36+I37 -> 262 | N37: =+M37/K$6 -> 0.056223176 | Q37: =+M37+O37 -> 262 | R37: =+Q37/$K$6 -> 0.056223176 | S37: =+S36-I37-K37 -> 4398
A38: 9 | I38: =SUM(B38:H38) -> 0 | J38: =+I38/S37 -> 0 | M38: =+M37+I38 -> 262 | N38: =+M38/K$6 -> 0.056223176 | Q38: =+M38+O38 -> 262 | R38: =+Q38/$K$6 -> 0.056223176 | S38: =+S37-I38-K38 -> 4398
B40: PESO POR AVE | E40: Aumento | G40: Conversion | I40: PROGRAMA DE VACUNACION | O40: TRATAMIENTO
A41: S/D | B41: Mach | C41: Hemb. | D41: Prom. | E41: por ave/dia | G41: alimento | I41: DIA | J41: MES | K41: VACUNA | O41: DIA | P41: MES | Q41: DROGA / DOSIS
A42: 1 | D42: =+(B42+C42)/2 -> 0 | E42: =+D42/7 -> 0 | G42: =+S17/D42 -> #DIV/0!
A43: 2 | D43: =+(B43+C43)/2 -> 0 | E43: =(D43-D42)/7 -> 0 | G43: =+S18/D43 -> #DIV/0!
A44: 3 | D44: =+(B44+C44)/2 -> 0 | E44: =(D44-D43)/7 -> 0 | G44: =+S19/D44 -> #DIV/0!
A45: 4 | D45: =+(B45+C45)/2 -> 0 | E45: =(D45-D44)/7 -> 0 | G45: =+S20/D45 -> #DIV/0!
A46: 5 | D46: =+(B46+C46)/2 -> 0 | E46: =(D46-D45)/7 -> 0 | G46: =+S21/D46 -> #DIV/0!
A47: 6 | D47: =+(B47+C47)/2 -> 0 | E47: =(D47-D46)/7 -> 0 | G47: =+S22/D47 -> #DIV/0!
A48: 7 | D48: =+(B48+C48)/2 -> 0 | E48: =(D48-D47)/7 -> 0 | G48: =+S23/D48 -> #DIV/0!
A49: 8 | D49: =+(B49+C49)/2 -> 0 | E49: =(D49-D48)/7 -> 0 | G49: =+S24/D49 -> #DIV/0!
A50: 9 | D50: =+(B50+C50)/2 -> 0 | E50: =(D50-D49)/7 -> 0 | G50: =+S25/D50 -> #DIV/0!
B53: GRANJA AVICOLA SAN LORENZO
B54: RESPONSABLE : | E54: =+E3 -> 0 | O54: HEMBRA
B56: GALPON | D56: LOTE | G56: INCUBADORA | K56: CANTIDAD INICIAL | O56: PESO PROMEDIO INIC.
B57: =+B6 -> T1 | D57: =+D6 -> 49 | G57: =+G6 -> FINAVES | K57: 5100 | O57: 44
B59: FECHA INICIO | G59: =+G8 -> 45780 | L59: DIAS DE ENGORDE: | P59: =+P8 -> 52
B60: FECHA TERMINACION | G60: =+G9 -> 45831 | L60: DIAS PROMEDIO | P60: =+P9 -> #REF!
B62: POLLOS VENDIDOS | G62: =+G11 -> 0 | Z62: conversion: kilos concentrado/ kilos en pie
B63: PESO TOTAL FINAL | G63: =+G12 -> 0 | L63: CONSUMO TOTAL DEL LOTE | Z63: se necesita xxx kilos concentrado para producir 1 kilo de pollo en pie
Z64: Entre mas bajo mejor
I65: TOTAL CONSUMO | Q65: CONSUMO POR AVE | U65: PESO
A66: KILOS CONSUMIDOS | I66: SEMANAL | M66: ACUMULADO | Q66: (Gramos) | T66: CONSUMO | U66: GRAMOS | V66: gramos | Z66: BULTOS CONSUMIDOS
A67: S/D | B67: =+B16 -> S | C67: =+C16 -> D | D67: =+D16 -> L | E67: =+E16 -> M | F67: =+F16 -> M | G67: =+G16 -> J | H67: =+H16 -> V | I67: Bultos | K67: Kilos | M67: Bultos | O67: Kilos | Q67: Diario | R67: Sem. | S67: Acumul. | T67: KL. | U67: PROMEDIO | V67: Ganancia dia | W67: Conversion | X67: VPI | Z67: S/D | AA67: =+B67 -> S | AB67: =+C67 -> D | AC67: =+D67 -> L | AD67: =+E67 -> M | AE67: =+F67 -> M | AF67: =+G67 -> J | AG67: =+H67 -> V | AH67: TOTAL
A68: 1 | B68: =+AA68*40 -> 80 | C68: =+AB68*40 -> 80 | D68: =+AC68*40 -> 100 | E68: =+AD68*40 -> 120 | F68: =+AE68*40 -> 120 | G68: =+AF68*40 -> 120 | H68: =+AG68*40 -> 160 | I68: =+K68/40 -> 19.5 | K68: =SUM(B68:H68) -> 780 | M68: =+I68 -> 19.5 | O68: =+K68 -> 780 | Q68: =+R68/7 -> 22.108844 | R68: =+K68*1000/S81 -> 154.7619 | S68: =+R68 -> 154.7619 | T68: =+O68/S81 -> 0.1547619 | U68: 190 | V68: =(U68-O57)/7 -> 20.857143 | W68: =+O68/(S81*(U68/1000)) -> 0.81453634 | X68: =+U68/O57 -> 4.3181818 | Z68: 1 | AA68: 2 | AB68: 2 | AC68: 2.5 | AD68: 3 | AE68: 3 | AF68: 3 | AG68: 4 | AH68: =+SUM(AA68:AG68) -> 19.5
A69: 2 | B69: =+AA69*40 -> 160 | C69: =+AB69*40 -> 200 | D69: =+AC69*40 -> 200 | E69: =+AD69*40 -> 240 | F69: =+AE69*40 -> 280 | G69: =+AF69*40 -> 280 | H69: =+AG69*40 -> 320 | I69: =+K69/40 -> 42 | K69: =SUM(B69:H69) -> 1680 | M69: =+M68+I69 -> 61.5 | O69: =+O68+K69 -> 2460 | Q69: =+R69/7 -> 48.038431 | R69: =+K69*1000/S82 -> 336.26902 | S69: =+O69*1000/S82 -> 492.39392 | T69: =+O69/S82 -> 0.49239392 | U69: 445 | V69: =+(U69-U68)/7 -> 36.428571 | W69: =+O69/(S82*(U69/1000)) -> 1.1065032 | X69: =+U69/U68 -> 2.3421053 | Z69: 2 | AA69: 4 | AB69: 5 | AC69: 5 | AD69: 6 | AE69: 7 | AF69: 7 | AG69: 8 | AH69: =+SUM(AA69:AG69) -> 42
A70: 3 | B70: =+AA70*40 -> 320 | C70: =+AB70*40 -> 360 | D70: =+AC70*40 -> 400 | E70: =+AD70*40 -> 400 | F70: =+AE70*40 -> 400 | G70: =+AF70*40 -> 440 | H70: =+AG70*40 -> 440 | I70: =+K70/40 -> 69 | K70: =SUM(B70:H70) -> 2760 | M70: =+M69+I70 -> 130.5 | O70: =+O69+K70 -> 5220 | Q70: =+R70/7 -> 79.285283 | R70: =+K70*1000/S83 -> 554.99698 | S70: =+O70*1000/S83 -> 1049.6682 | T70: =+O70/S83 -> 1.0496682 | U70: 850 | V70: =+(U70-U69)/7 -> 57.857143 | W70: =+O70/(S83*(U70/1000)) -> 1.2349038 | X70: =+U70/U69 -> 1.9101124 | Z70: 3 | AA70: 8 | AB70: 9 | AC70: 10 | AD70: 10 | AE70: 10 | AF70: 11 | AG70: 11 | AH70: =+SUM(AA70:AG70) -> 69
A71: 4 | B71: =+AA71*40 -> 440 | C71: =+AB71*40 -> 480 | D71: =+AC71*40 -> 520 | E71: =+AD71*40 -> 600 | F71: =+AE71*40 -> 640 | G71: =+AF71*40 -> 680 | H71: =+AG71*40 -> 720 | I71: =+K71/40 -> 102 | K71: =SUM(B71:H71) -> 4080 | M71: =+M70+I71 -> 232.5 | O71: =+O70+K71 -> 9300 | Q71: =+R71/7 -> 117.93953 | R71: =+K71*1000/S84 -> 825.57669 | S71: =+O71*1000/S84 -> 1881.8292 | T71: =+O71/S84 -> 1.8818292 | U71: 1400 | V71: =+(U71-U70)/7 -> 78.571429 | W71: =+O71/(S84*(U71/1000)) -> 1.3441637 | X71: =+U71/U70 -> 1.6470588 | Z71: 4 | AA71: 11 | AB71: 12 | AC71: 13 | AD71: 15 | AE71: 16 | AF71: 17 | AG71: 18 | AH71: =+SUM(AA71:AG71) -> 102
A72: 5 | B72: =+AA72*40 -> 680 | C72: =+AB72*40 -> 680 | D72: =+AC72*40 -> 680 | E72: =+AD72*40 -> 720 | F72: =+AE72*40 -> 720 | G72: =+AF72*40 -> 720 | H72: =+AG72*40 -> 720 | I72: =+K72/40 -> 123 | K72: =SUM(B72:H72) -> 4920 | M72: =+M71+I72 -> 355.5 | O72: =+O71+K72 -> 14220 | Q72: =+R72/7 -> 142.77009 | R72: =+K72*1000/S85 -> 999.39062 | S72: =+O72*1000/S85 -> 2888.4826 | T72: =+O72/S85 -> 2.8884826 | U72: 1880 | V72: =+(U72-U71)/7 -> 68.571429 | W72: =+O72/(S85*(U72/1000)) -> 1.5364269 | X72: =+U72/U71 -> 1.3428571 | Z72: 5 | AA72: 17 | AB72: 17 | AC72: 17 | AD72: 18 | AE72: 18 | AF72: 18 | AG72: 18 | AH72: =+SUM(AA72:AG72) -> 123
A73: 6 | B73: =+AA73*40 -> 720 | C73: =+AB73*40 -> 760 | D73: =+AC73*40 -> 760 | E73: =+AD73*40 -> 760 | F73: =+AE73*40 -> 760 | G73: =+AF73*40 -> 760 | H73: =+AG73*40 -> 760 | I73: =+K73/40 -> 132 | K73: =SUM(B73:H73) -> 5280 | M73: =+M72+I73 -> 487.5 | O73: =+O72+K73 -> 19500 | Q73: =+R73/7 -> 153.87305 | R73: =+K73*1000/S86 -> 1077.1114 | S73: =+O73*1000/S86 -> 3977.9682 | T73: =+O73/S86 -> 3.9779682 | U73: 2340 | V73: =+(U73-U72)/7 -> 65.714286 | W73: =+O73/(S86*(U73/1000)) -> 1.6999864 | X73: =+U73/U72 -> 1.2446809 | Z73: 6 | AA73: 18 | AB73: 19 | AC73: 19 | AD73: 19 | AE73: 19 | AF73: 19 | AG73: 19 | AH73: =+SUM(AA73:AG73) -> 132
A74: 7 | B74: =+AA74*40 -> 760 | C74: =+AB74*40 -> 760 | D74: =+AC74*40 -> 760 | E74: =+AD74*40 -> 760 | F74: =+AE74*40 -> 760 | G74: =+AF74*40 -> 760 | H74: =+AG74*40 -> 760 | I74: =+K74/40 -> 133 | K74: =SUM(B74:H74) -> 5320 | M74: =+M73+I74 -> 620.5 | O74: =+O73+K74 -> 24820 | Q74: =+R74/7 -> 156.15369 | R74: =+K74*1000/S87 -> 1093.0758 | S74: =+O74*1000/S87 -> 5099.6507 | T74: =+O74/S87 -> 5.0996507 | V74: =+(U74-U73)/7 -> -334.28571 | W74: =+O74/(S87*(U74/1000)) -> #DIV/0! | X74: =+U74/U73 -> 0 | Z74: 7 | AA74: 19 | AB74: 19 | AC74: 19 | AD74: 19 | AE74: 19 | AF74: 19 | AG74: 19 | AH74: =+SUM(AA74:AG74) -> 133
A75: 8 | B75: =+AA75*40 -> 0 | C75: =+AB75*40 -> 0 | D75: =+AC75*40 -> 0 | E75: =+AD75*40 -> 0 | F75: =+AE75*40 -> 0 | G75: =+AF75*40 -> 0 | H75: =+AG75*40 -> 0 | I75: =+K75/40 -> 0 | K75: =SUM(B75:H75) -> 0 | M75: =+M74+I75 -> 620.5 | O75: =+O74+K75 -> 24820 | Q75: =+R75/7 -> 0 | R75: =+K75*1000/S88 -> 0 | S75: =+O75*1000/S88 -> 5099.6507 | T75: =+O75/S88 -> 5.0996507 | V75: =+(U75-U74)/7 -> 0 | W75: =+O75/(S88*(U75/1000)) -> #DIV/0! | X75: =+U75/U74 -> #DIV/0! | Z75: 8 | AH75: =+SUM(AA75:AG75) -> 0
A76: 9 | B76: =+AA76*40 -> 0 | C76: =+AB76*40 -> 0 | D76: =+AC76*40 -> 0 | E76: =+AD76*40 -> 0 | F76: =+AE76*40 -> 0 | G76: =+AF76*40 -> 0 | H76: =+AG76*40 -> 0 | I76: =+K76/40 -> 0 | K76: =SUM(B76:H76) -> 0 | M76: =+M75+I76 -> 620.5 | O76: =+O75+K76 -> 24820 | Q76: =+R76/7 -> 0 | R76: =+K76*1000/S89 -> 0 | S76: =+O76*1000/S89 -> 5099.6507 | T76: =+O76/S89 -> 5.0996507 | V76: =+(U76-U75)/7 -> 0 | W76: =+O76/(S89*(U76/1000)) -> #DIV/0! | X76: =+U76/U75 -> #DIV/0! | Z76: 9 | AH76: =+SUM(AA76:AG76) -> 0
I78: TOTAL MORTALIDAD Y SELECCIÓN | S78: SALDO
B79: AVES MUERTAS POR DIA | I79: Mort./sem. | K79: Selec/Sem | M79: Mort.Acum. | O79: Selec.Acum. | Q79: Mort/Selec.Ac. | S79: AVES
A80: S/D | B80: =+B67 -> S | C80: =+C67 -> D | D80: =+D67 -> L | E80: =+E67 -> M | F80: =+F67 -> M | G80: =+G67 -> J | H80: =+H67 -> V | I80: No.A. | J80: % | K80: No.A. | L80: % | M80: No.A. | N80: % | O80: No.A. | P80: % | Q80: No.A. | R80: % | S80: (superv.)
A81: 1 | B81: =3+6 -> 9 | C81: =2+4 -> 6 | D81: 6 | E81: 12 | F81: =2+9 -> 11 | G81: 5 | H81: 11 | I81: =SUM(B81:H81) -> 60 | J81: =+I81/K57 -> 0.011764706 | M81: =+I81 -> 60 | N81: =+M81/K$57 -> 0.011764706 | Q81: =+M81+O81 -> 60 | R81: =+Q81/$K$57 -> 0.011764706 | S81: =+K57-I81-K81 -> 5040
A82: 2 | B82: 4 | C82: 7 | D82: 6 | E82: 6 | F82: 5 | G82: 7 | H82: 9 | I82: =SUM(B82:H82) -> 44 | J82: =+I82/S81 -> 0.0087301587 | M82: =+M81+I82 -> 104 | N82: =+M82/K$57 -> 0.020392157 | Q82: =+M82+O82 -> 104 | R82: =+Q82/$K$57 -> 0.020392157 | S82: =+S81-I82-K82 -> 4996
A83: 3 | B83: 3 | C83: 2 | D83: 4 | E83: 5 | F83: 3 | G83: 2 | H83: 4 | I83: =SUM(B83:H83) -> 23 | J83: =+I83/S82 -> 0.0046036829 | M83: =+M82+I83 -> 127 | N83: =+M83/K$57 -> 0.024901961 | Q83: =+M83+O83 -> 127 | R83: =+Q83/$K$57 -> 0.024901961 | S83: =+S82-I83-K83 -> 4973
A84: 4 | B84: 3 | C84: 3 | D84: 6 | E84: 4 | F84: 6 | G84: 5 | H84: 4 | I84: =SUM(B84:H84) -> 31 | J84: =+I84/S83 -> 0.0062336618 | M84: =+M83+I84 -> 158 | N84: =+M84/K$57 -> 0.030980392 | Q84: =+M84+O84 -> 158 | R84: =+Q84/$K$57 -> 0.030980392 | S84: =+S83-I84-K84 -> 4942
A85: 5 | B85: 2 | C85: 3 | D85: 1 | E85: 4 | F85: 2 | G85: 5 | H85: 2 | I85: =SUM(B85:H85) -> 19 | J85: =+I85/S84 -> 0.0038445973 | M85: =+M84+I85 -> 177 | N85: =+M85/K$57 -> 0.034705882 | Q85: =+M85+O85 -> 177 | R85: =+Q85/$K$57 -> 0.034705882 | S85: =+S84-I85-K85 -> 4923
A86: 6 | B86: 3 | C86: 2 | D86: 4 | E86: 2 | F86: 3 | G86: 3 | H86: 4 | I86: =SUM(B86:H86) -> 21 | J86: =+I86/S85 -> 0.0042656917 | M86: =+M85+I86 -> 198 | N86: =+M86/K$57 -> 0.038823529 | Q86: =+M86+O86 -> 198 | R86: =+Q86/$K$57 -> 0.038823529 | S86: =+S85-I86-K86 -> 4902
A87: 7 | B87: 2 | C87: 4 | D87: 3 | E87: 6 | F87: 4 | G87: 7 | H87: 9 | I87: =SUM(B87:H87) -> 35 | J87: =+I87/S86 -> 0.0071399429 | M87: =+M86+I87 -> 233 | N87: =+M87/K$57 -> 0.045686275 | Q87: =+M87+O87 -> 233 | R87: =+Q87/$K$57 -> 0.045686275 | S87: =+S86-I87-K87 -> 4867
A88: 8 | I88: =SUM(B88:H88) -> 0 | J88: =+I88/S87 -> 0 | M88: =+M87+I88 -> 233 | N88: =+M88/K$57 -> 0.045686275 | Q88: =+M88+O88 -> 233 | R88: =+Q88/$K$57 -> 0.045686275 | S88: =+S87-I88-K88 -> 4867
A89: 9 | I89: =SUM(B89:H89) -> 0 | J89: =+I89/S88 -> 0 | M89: =+M88+I89 -> 233 | N89: =+M89/K$57 -> 0.045686275 | Q89: =+M89+O89 -> 233 | R89: =+Q89/$K$57 -> 0.045686275 | S89: =+S88-I89-K89 -> 4867
B91: PESO POR AVE | E91: Aumento | G91: Conversion | I91: PROGRAMA DE VACUNACION | O91: TRATAMIENTO
A92: S/D | B92: Mach | C92: Hemb. | D92: Prom. | E92: por ave/dia | G92: alimento | I92: DIA | J92: MES | K92: VACUNA | O92: DIA | P92: MES | Q92: DROGA / DOSIS
A93: 1 | D93: =+(B93+C93)/2 -> 0 | E93: =+D93/7 -> 0 | G93: =+S68/D93 -> #DIV/0!
A94: 2 | D94: =+(B94+C94)/2 -> 0 | E94: =(D94-D93)/7 -> 0 | G94: =+S69/D94 -> #DIV/0!
A95: 3 | D95: =+(B95+C95)/2 -> 0 | E95: =(D95-D94)/7 -> 0 | G95: =+S70/D95 -> #DIV/0!
A96: 4 | D96: =+(B96+C96)/2 -> 0 | E96: =(D96-D95)/7 -> 0 | G96: =+S71/D96 -> #DIV/0!
A97: 5 | D97: =+(B97+C97)/2 -> 0 | E97: =(D97-D96)/7 -> 0 | G97: =+S72/D97 -> #DIV/0!
A98: 6 | D98: =+(B98+C98)/2 -> 0 | E98: =(D98-D97)/7 -> 0 | G98: =+S73/D98 -> #DIV/0!
A99: 7 | D99: =+(B99+C99)/2 -> 0 | E99: =(D99-D98)/7 -> 0 | G99: =+S74/D99 -> #DIV/0!
A100: 8 | D100: =+(B100+C100)/2 -> 0 | E100: =(D100-D99)/7 -> 0 | G100: =+S75/D100 -> #DIV/0!
A101: 9 | D101: =+(B101+C101)/2 -> 0 | E101: =(D101-D100)/7 -> 0 | G101: =+S76/D101 -> #DIV/0!
B104: GRANJA AVICOLA SAN LORENZO
B105: RESPONSABLE : | E105: =+E54 -> 0 | O105: TOTAL
B107: GALPON | D107: LOTE | G107: INCUBADORA | K107: CANTIDAD INICIAL | O107: PESO PROMEDIO INIC.
B108: =+B57 -> T1 | D108: =+D57 -> 49 | G108: =+G57 -> FINAVES | K108: =+K6+K57 -> 9760
B110: FECHA INICIO | G110: =+G59 -> 45780 | L110: DIAS DE ENGORDE: | P110: =+P59 -> 52
B111: FECHA TERMINACION | G111: =+G60 -> 45831 | L111: DIAS PROMEDIO | P111: =+P60 -> #REF!
B113: POLLOS VENDIDOS | G113: =+G62 -> 0 | Z113: conversion: kilos concentrado/ kilos en pie
B114: PESO TOTAL FINAL | G114: =+G63 -> 0 | L114: CONSUMO TOTAL DEL LOTE | Z114: se necesita xxx kilos concentrado para producir 1 kilo de pollo en pie
Z115: Entre mas bajo mejor
I116: TOTAL CONSUMO | Q116: CONSUMO POR AVE | U116: PESO
A117: BULTOS CONSUMIDOS | I117: SEMANAL | M117: ACUMULADO | Q117: (Gramos) | T117: CONSUMO | U117: GRAMOS | V117: gramos
...

Sheet CONSUMO DIARIO 2
A1: GRANJA | B1: =+'REGISTRO 2- lote 10'!E2 -> SAN LORENZO
A2: GALPON: | B2: =+'REGISTRO 2- lote 10'!B6 -> T1 | C2: MACHOS | O2: HEMBRAS
A3: LOTE | B3: =+'REGISTRO 2- lote 10'!D6 -> 49
G4: CONSUMO DIARIO | S4: CONSUMO DIARIO
A5: FECHA | B5: SEMANA | C5: DIA | D5: MORTALIDAD | E5: SALIDA A PROCESO | F5: SALDO POLLITOS | G5: TOTAL KL | H5: X POLLO GR | I5: Acumul X P (gr) | J5: Peso pollito gr | K5: ganancia peso gr semanal | L5: Promedio ganancia peso gr dia | M5: CONVERSION | O5: DIA | P5: MORTALIDAD | Q5: SALIDA A PROCESO | R5: SALDO POLLITOS | S5: TOTAL KL | T5: X POLLO GR | U5: Acumul X P (gr) | V5: Peso pollito gr | W5: ganancia peso gr semanal | X5: Promedio ganancia peso gr dia | Y5: CONVERSION
A6: =+'REGISTRO 2- lote 10'!G8 -> 45780 | B6: Semana 1 | C6: 0 | F6: =+'REGISTRO 2- lote 10'!K6 -> 4660 | J6: =+'REGISTRO 2- lote 10'!O6 -> 44 | O6: 0 | R6: =+'REGISTRO 2- lote 10'!K57 -> 5100 | V6: =+'REGISTRO 2- lote 10'!O57 -> 44
A7: =+A6+1 -> 45781 | C7: 1 | D7: =+'REGISTRO 2- lote 10'!$B$30 -> 6 | F7: =+F6-D7-E7 -> 4654 | G7: =+'REGISTRO 2- lote 10'!$B$17 -> 80 | H7: =+G7*1000/F7 -> 17.189514 | I7: =+H7 -> 17.189514 | O7: 1 | P7: =+'REGISTRO 2- lote 10'!$B$81 -> 9 | R7: =+R6-P7-Q7 -> 5091 | S7: =+'REGISTRO 2- lote 10'!$B$68 -> 80 | T7: =+S7*1000/R7 -> 15.714005 | U7: =+T7 -> 15.714005
A8: =+A7+1 -> 45782 | C8: =+C7+1 -> 2 | D8: =+'REGISTRO 2- lote 10'!$C$30 -> 6 | F8: =+F7-D8-E8 -> 4648 | G8: =+'REGISTRO 2- lote 10'!$C$17 -> 80 | H8: =+G8*1000/F8 -> 17.211704 | I8: =+I7+H8 -> 34.401218 | O8: =+O7+1 -> 2 | P8: =+'REGISTRO 2- lote 10'!$C$81 -> 6 | R8: =+R7-P8-Q8 -> 5085 | S8: =+'REGISTRO 2- lote 10'!$C$68 -> 80 | T8: =+S8*1000/R8 -> 15.732547 | U8: =+U7+T8 -> 31.446552
A9: =+A8+1 -> 45783 | C9: =+C8+1 -> 3 | D9: =+'REGISTRO 2- lote 10'!$D$30 -> 10 | F9: =+F8-D9-E9 -> 4638 | G9: =+'REGISTRO 2- lote 10'!$D$17 -> 80 | H9: =+G9*1000/F9 -> 17.248814 | I9: =+I8+H9 -> 51.650032 | O9: =+O8+1 -> 3 | P9: =+'REGISTRO 2- lote 10'!$D$81 -> 6 | R9: =+R8-P9-Q9 -> 5079 | S9: =+'REGISTRO 2- lote 10'!$D$68 -> 100 | T9: =+S9*1000/R9 -> 19.688915 | U9: =+U8+T9 -> 51.135467
A10: =+A9+1 -> 45784 | C10: =+C9+1 -> 4 | D10: =+'REGISTRO 2- lote 10'!$E$30 -> 18 | F10: =+F9-D10-E10 -> 4620 | G10: =+'REGISTRO 2- lote 10'!$E$17 -> 100 | H10: =+G10*1000/F10 -> 21.645022 | I10: =+I9+H10 -> 73.295054 | O10: =+O9+1 -> 4 | P10: =+'REGISTRO 2- lote 10'!$E$81 -> 12 | R10: =+R9-P10-Q10 -> 5067 | S10: =+'REGISTRO 2- lote 10'!$E$68 -> 120 | T10: =+S10*1000/R10 -> 23.682652 | U10: =+U9+T10 -> 74.818119
A11: =+A10+1 -> 45785 | C11: =+C10+1 -> 5 | D11: =+'REGISTRO 2- lote 10'!$F$30 -> 16 | F11: =+F10-D11-E11 -> 4604 | G11: =+'REGISTRO 2- lote 10'!$F$17 -> 120 | H11: =+G11*1000/F11 -> 26.064292 | I11: =+I10+H11 -> 99.359346 | O11: =+O10+1 -> 5 | P11: =+'REGISTRO 2- lote 10'!$F$81 -> 11 | R11: =+R10-P11-Q11 -> 5056 | S11: =+'REGISTRO 2- lote 10'!$F$68 -> 120 | T11: =+S11*1000/R11 -> 23.734177 | U11: =+U10+T11 -> 98.552297
A12: =+A11+1 -> 45786 | C12: =+C11+1 -> 6 | D12: =+'REGISTRO 2- lote 10'!$G$30 -> 16 | F12: =+F11-D12-E12 -> 4588 | G12: =+'REGISTRO 2- lote 10'!$G$17 -> 120 | H12: =+G12*1000/F12 -> 26.155187 | I12: =+I11+H12 -> 125.51453 | O12: =+O11+1 -> 6 | P12: =+'REGISTRO 2- lote 10'!$G$81 -> 5 | R12: =+R11-P12-Q12 -> 5051 | S12: =+'REGISTRO 2- lote 10'!$G$68 -> 120 | T12: =+S12*1000/R12 -> 23.757672 | U12: =+U11+T12 -> 122.30997
A13: =+A12+1 -> 45787 | C13: =+C12+1 -> 7 | D13: =+'REGISTRO 2- lote 10'!$H$30 -> 18 | F13: =+F12-D13-E13 -> 4570 | G13: =+'REGISTRO 2- lote 10'!$H$17 -> 160 | H13: =+G13*1000/F13 -> 35.010941 | I13: =+I12+H13 -> 160.52547 | J13: =+'REGISTRO 2- lote 10'!U17 -> 193 | K13: =+J13-J6 -> 149 | L13: =+(J13-$J$6)/C13 -> 21.285714 | M13: =+I13/J13 -> 0.83173821 | N13: 160-190 | O13: =+O12+1 -> 7 | P13: =+'REGISTRO 2- lote 10'!$H$81 -> 11 | R13: =+R12-P13-Q13 -> 5040 | S13: =+'REGISTRO 2- lote 10'!$H$68 -> 160 | T13: =+S13*1000/R13 -> 31.746032 | U13: =+U12+T13 -> 154.056 | V13: =+'REGISTRO 2- lote 10'!U68 -> 190 | W13: =+V13-V6 -> 146 | X13: =+(V13-$J$6)/O13 -> 20.857143 | Y13: =+U13/V13 -> 0.81082105 | Z13: 160-185
A14: =+A13+1 -> 45788 | B14: Semana 2 | C14: =+C13+1 -> 8 | D14: =+'REGISTRO 2- lote 10'!$B$31 -> 3 | F14: =+F13-D14-E14 -> 4567 | G14: =+'REGISTRO 2- lote 10'!$B$18 -> 160 | H14: =+G14*1000/F14 -> 35.033939 | I14: =+I13+H14 -> 195.55941 | O14: =+O13+1 -> 8 | P14: =+'REGISTRO 2- lote 10'!$B$82 -> 4 | R14: =+R13-P14-Q14 -> 5036 | S14: =+'REGISTRO 2- lote 10'!$B$69 -> 160 | T14: =+S14*1000/R14 -> 31.771247 | U14: =+U13+T14 -> 185.82725
A15: =+A14+1 -> 45789 | C15: =+C14+1 -> 9 | D15: =+'REGISTRO 2- lote 10'!$C$31 -> 4 | F15: =+F14-D15-E15 -> 4563 | G15: =+'REGISTRO 2- lote 10'!$C$18 -> 160 | H15: =+G15*1000/F15 -> 35.06465 | I15: =+I14+H15 -> 230.62406 | O15: =+O14+1 -> 9 | P15: =+'REGISTRO 2- lote 10'!$C$82 -> 7 | R15: =+R14-P15-Q15 -> 5029 | S15: =+'REGISTRO 2- lote 10'!$C$69 -> 200 | T15: =+S15*1000/R15 -> 39.769338 | U15: =+U14+T15 -> 225.59658
A16: =+A15+1 -> 45790 | C16: =+C15+1 -> 10 | D16: =+'REGISTRO 2- lote 10'!$D$31 -> 6 | F16: =+F15-D16-E16 -> 4557 | G16: =+'REGISTRO 2- lote 10'!$D$18 -> 200 | H16: =+G16*1000/F16 -> 43.888523 | I16: =+I15+H16 -> 274.51259 | O16: =+O15+1 -> 10 | P16: =+'REGISTRO 2- lote 10'!$D$82 -> 6 | R16: =+R15-P16-Q16 -> 5023 | S16: =+'REGISTRO 2- lote 10'!$D$69 -> 200 | T16: =+S16*1000/R16 -> 39.816843 | U16: =+U15+T16 -> 265.41343
A17: =+A16+1 -> 45791 | C17: =+C16+1 -> 11 | D17: =+'REGISTRO 2- lote 10'!$E$31 -> 5 | F17: =+F16-D17-E17 -> 4552 | G17: =+'REGISTRO 2- lote 10'!$E$18 -> 240 | H17: =+G17*1000/F17 -> 52.724077 | I17: =+I16+H17 -> 327.23666 | O17: =+O16+1 -> 11 | P17: =+'REGISTRO 2- lote 10'!$E$82 -> 6 | R17: =+R16-P17-Q17 -> 5017 | S17: =+'REGISTRO 2- lote 10'!$E$69 -> 240 | T17: =+S17*1000/R17 -> 47.837353 | U17: =+U16+T17 -> 313.25078
A18: =+A17+1 -> 45792 | C18: =+C17+1 -> 12 | D18: =+'REGISTRO 2- lote 10'!$F$31 -> 3 | F18: =+F17-D18-E18 -> 4549 | G18: =+'REGISTRO 2- lote 10'!$F$18 -> 240 | H18: =+G18*1000/F18 -> 52.758848 | I18: =+I17+H18 -> 379.99551 | O18: =+O17+1 -> 12 | P18: =+'REGISTRO 2- lote 10'!$F$82 -> 5 | R18: =+R17-P18-Q18 -> 5012 | S18: =+'REGISTRO 2- lote 10'!$F$69 -> 280 | T18: =+S18*1000/R18 -> 55.865922 | U18: =+U17+T18 -> 369.1167
A19: =+A18+1 -> 45793 | C19: =+C18+1 -> 13 | D19: =+'REGISTRO 2- lote 10'!$G$31 -> 4 | F19: =+F18-D19-E19 -> 4545 | G19: =+'REGISTRO 2- lote 10'!$G$18 -> 280 | H19: =+G19*1000/F19 -> 61.606161 | I19: =+I18+H19 -> 441.60167 | O19: =+O18+1 -> 13 | P19: =+'REGISTRO 2- lote 10'!$G$82 -> 7 | R19: =+R18-P19-Q19 -> 5005 | S19: =+'REGISTRO 2- lote 10'!$G$69 -> 280 | T19: =+S19*1000/R19 -> 55.944056 | U19: =+U18+T19 -> 425.06076
A20: =+A19+1 -> 45794 | C20: =+C19+1 -> 14 | D20: =+'REGISTRO 2- lote 10'!$H$31 -> 7 | F20: =+F19-D20-E20 -> 4538 | G20: =+'REGISTRO 2- lote 10'!$H$18 -> 320 | H20: =+G20*1000/F20 -> 70.515646 | I20: =+I19+H20 -> 512.11732 | J20: =+'REGISTRO 2- lote 10'!U18 -> 455 | K20: =+J20-J13 -> 262 | L20: =+(J20-$J$6)/C20 -> 29.357143 | M20: =+I20/J20 -> 1.1255326 | N20: 380-390 | O20: =+O19+1 -> 14 | P20: =+'REGISTRO 2- lote 10'!$H$82 -> 9 | R20: =+R19-P20-Q20 -> 4996 | S20: =+'REGISTRO 2- lote 10'!$H$69 -> 320 | T20: =+S20*1000/R20 -> 64.051241 | U20: =+U19+T20 -> 489.112 | V20: =+'REGISTRO 2- lote 10'!U69 -> 445 | W20: =+V20-V13 -> 255 | X20: =+(V20-$J$6)/O20 -> 28.642857 | Y20: =+U20/V20 -> 1.0991281 | Z20: 375-380
A21: =+A20+1 -> 45795 | B21: Semana 3 | C21: =+C20+1 -> 15 | D21: =+'REGISTRO 2- lote 10'!$B$32 -> 3 | F21: =+F20-D21-E21 -> 4535 | G21: =+'REGISTRO 2- lote 10'!$B$19 -> 320 | H21: =+G21*1000/F21 -> 70.562293 | I21: =+I20+H21 -> 582.67961 | O21: =+O20+1 -> 15 | P21: =+'REGISTRO 2- lote 10'!$B$83 -> 3 | R21: =+R20-P21-Q21 -> 4993 | S21: =+'REGISTRO 2- lote 10'!$B$70 -> 320 | T21: =+S21*1000/R21 -> 64.089726 | U21: =+U20+T21 -> 553.20172
A22: =+A21+1 -> 45796 | C22: =+C21+1 -> 16 | D22: =+'REGISTRO 2- lote 10'!$C$32 -> 2 | F22: =+F21-D22-E22 -> 4533 | G22: =+'REGISTRO 2- lote 10'!$C$19 -> 320 | H22: =+G22*1000/F22 -> 70.593426 | I22: =+I21+H22 -> 653.27304 | O22: =+O21+1 -> 16 | P22: =+'REGISTRO 2- lote 10'!$C$83 -> 2 | R22: =+R21-P22-Q22 -> 4991 | S22: =+'REGISTRO 2- lote 10'!$C$70 -> 360 | T22: =+S22*1000/R22 -> 72.129834 | U22: =+U21+T22 -> 625.33156
A23: =+A22+1 -> 45797 | C23: =+C22+1 -> 17 | D23: =+'REGISTRO 2- lote 10'!$D$32 -> 3 | F23: =+F22-D23-E23 -> 4530 | G23: =+'REGISTRO 2- lote 10'!$D$19 -> 360 | H23: =+G23*1000/F23 -> 79.470199 | I23: =+I22+H23 -> 732.74324 | O23: =+O22+1 -> 17 | P23: =+'REGISTRO 2- lote 10'!$D$83 -> 4 | R23: =+R22-P23-Q23 -> 4987 | S23: =+'REGISTRO 2- lote 10'!$D$70 -> 400 | T23: =+S23*1000/R23 -> 80.208542 | U23: =+U22+T23 -> 705.5401
A24: =+A23+1 -> 45798 | C24: =+C23+1 -> 18 | D24: =+'REGISTRO 2- lote 10'!$E$32 -> 1 | F24: =+F23-D24-E24 -> 4529 | G24: =+'REGISTRO 2- lote 10'!$E$19 -> 360 | H24: =+G24*1000/F24 -> 79.487746 | I24: =+I23+H24 -> 812.23098 | O24: =+O23+1 -> 18 | P24: =+'REGISTRO 2- lote 10'!$E$83 -> 5 | R24: =+R23-P24-Q24 -> 4982 | S24: =+'REGISTRO 2- lote 10'!$E$70 -> 400 | T24: =+S24*1000/R24 -> 80.289041 | U24: =+U23+T24 -> 785.82914
A25: =+A24+1 -> 45799 | C25: =+C24+1 -> 19 | D25: =+'REGISTRO 2- lote 10'!$F$32 -> 4 | F25: =+F24-D25-E25 -> 4525 | G25: =+'REGISTRO 2- lote 10'!$F$19 -> 400 | H25: =+G25*1000/F25 -> 88.39779 | I25: =+I24+H25 -> 900.62877 | O25: =+O24+1 -> 19 | P25: =+'REGISTRO 2- lote 10'!$F$83 -> 3 | R25: =+R24-P25-Q25 -> 4979 | S25: =+'REGISTRO 2- lote 10'!$F$70 -> 400 | T25: =+S25*1000/R25 -> 80.337417 | U25: =+U24+T25 -> 866.16656
A26: =+A25+1 -> 45800 | C26: =+C25+1 -> 20 | D26: =+'REGISTRO 2- lote 10'!$G$32 -> 3 | F26: =+F25-D26-E26 -> 4522 | G26: =+'REGISTRO 2- lote 10'!$G$19 -> 440 | H26: =+G26*1000/F26 -> 97.302079 | I26: =+I25+H26 -> 997.93085 | O26: =+O25+1 -> 20 | P26: =+'REGISTRO 2- lote 10'!$G$83 -> 2 | R26: =+R25-P26-Q26 -> 4977 | S26: =+'REGISTRO 2- lote 10'!$G$70 -> 440 | T26: =+S26*1000/R26 -> 88.406671 | U26: =+U25+T26 -> 954.57323
A27: =+A26+1 -> 45801 | C27: =+C26+1 -> 21 | D27: =+'REGISTRO 2- lote 10'!$H$32 -> 3 | F27: =+F26-D27-E27 -> 4519 | G27: =+'REGISTRO 2- lote 10'!$H$19 -> 480 | H27: =+G27*1000/F27 -> 106.21819 | I27: =+I26+H27 -> 1104.149 | J27: =+'REGISTRO 2- lote 10'!U19 -> 880 | K27: =+J27-J20 -> 425 | L27: =+(J27-$J$6)/C27 -> 39.809524 | M27: =+I27/J27 -> 1.2547148 | N27: 730-780 | O27: =+O26+1 -> 21 | P27: =+'REGISTRO 2- lote 10'!$H$83 -> 4 | R27: =+R26-P27-Q27 -> 4973 | S27: =+'REGISTRO 2- lote 10'!$H$70 -> 440 | T27: =+S27*1000/R27 -> 88.47778 | U27: =+U26+T27 -> 1043.051 | V27: =+'REGISTRO 2- lote 10'!U70 -> 850 | W27: =+V27-V20 -> 405 | X27: =+(V27-$J$6)/O27 -> 38.380952 | Y27: =+U27/V27 -> 1.2271188 | Z27: 680-760
A28: =+A27+1 -> 45802 | B28: Semana 4 | C28: =+C27+1 -> 22 | D28: =+'REGISTRO 2- lote 10'!$B$33 -> 2 | F28: =+F27-D28-E28 -> 4517 | G28: =+'REGISTRO 2- lote 10'!$B$20 -> 480 | H28: =+G28*1000/F28 -> 106.26522 | I28: =+I27+H28 -> 1210.4143 | O28: =+O27+1 -> 22 | P28: =+'REGISTRO 2- lote 10'!$B$84 -> 3 | R28: =+R27-P28-Q28 -> 4970 | S28: =+'REGISTRO 2- lote 10'!$B$71 -> 440 | T28: =+S28*1000/R28 -> 88.531187 | U28: =+U27+T28 -> 1131.5822
A29: =+A28+1 -> 45803 | C29: =+C28+1 -> 23 | D29: =+'REGISTRO 2- lote 10'!$C$33 -> 1 | F29: =+F28-D29-E29 -> 4516 | G29: =+'REGISTRO 2- lote 10'!$C$20 -> 480 | H29: =+G29*1000/F29 -> 106.28875 | I29: =+I28+H29 -> 1316.703 | O29: =+O28+1 -> 23 | P29: =+'REGISTRO 2- lote 10'!$C$84 -> 3 | R29: =+R28-P29-Q29 -> 4967 | S29: =+'REGISTRO 2- lote 10'!$C$71 -> 480 | T29: =+S29*1000/R29 -> 96.63781 | U29: =+U28+T29 -> 1228.22
A30: =+A29+1 -> 45804 | C30: =+C29+1 -> 24 | D30: =+'REGISTRO 2- lote 10'!$D$33 -> 3 | F30: =+F29-D30-E30 -> 4513 | G30: =+'REGISTRO 2- lote 10'!$D$20 -> 520 | H30: =+G30*1000/F30 -> 115.22269 | I30: =+I29+H30 -> 1431.9257 | O30: =+O29+1 -> 24 | P30: =+'REGISTRO 2- lote 10'!$D$84 -> 6 | R30: =+R29-P30-Q30 -> 4961 | S30: =+'REGISTRO 2- lote 10'!$D$71 -> 520 | T30: =+S30*1000/R30 -> 104.81758 | U30: =+U29+T30 -> 1333.0376
A31: =+A30+1 -> 45805 | C31: =+C30+1 -> 25 | D31: =+'REGISTRO 2- lote 10'!$E$33 -> 2 | F31: =+F30-D31-E31 -> 4511 | G31: =+'REGISTRO 2- lote 10'!$E$20 -> 560 | H31: =+G31*1000/F31 -> 124.14099 | I31: =+I30+H31 -> 1556.0667 | O31: =+O30+1 -> 25 | P31: =+'REGISTRO 2- lote 10'!$E$84 -> 4 | R31: =+R30-P31-Q31 -> 4957 | S31: =+'REGISTRO 2- lote 10'!$E$71 -> 600 | T31: =+S31*1000/R31 -> 121.04095 | U31: =+U30+T31 -> 1454.0785
A32: =+A31+1 -> 45806 | C32: =+C31+1 -> 26 | D32: =+'REGISTRO 2- lote 10'!$F$33 -> 4 | F32: =+F31-D32-E32 -> 4507 | G32: =+'REGISTRO 2- lote 10'!$F$20 -> 600 | H32: =+G32*1000/F32 -> 133.12625 | I32: =+I31+H32 -> 1689.1929 | O32: =+O31+1 -> 26 | P32: =+'REGISTRO 2- lote 10'!$F$84 -> 6 | R32: =+R31-P32-Q32 -> 4951 | S32: =+'REGISTRO 2- lote 10'!$F$71 -> 640 | T32: =+S32*1000/R32 -> 129.26681 | U32: =+U31+T32 -> 1583.3453
A33: =+A32+1 -> 45807 | C33: =+C32+1 -> 27 | D33: =+'REGISTRO 2- lote 10'!$G$33 -> 3 | F33: =+F32-D33-E33 -> 4504 | G33: =+'REGISTRO 2- lote 10'!$G$20 -> 640 | H33: =+G33*1000/F33 -> 142.09591 | I33: =+I32+H33 -> 1831.2889 | O33: =+O32+1 -> 27 | P33: =+'REGISTRO 2- lote 10'!$G$84 -> 5 | R33: =+R32-P33-Q33 -> 4946 | S33: =+'REGISTRO 2- lote 10'!$G$71 -> 680 | T33: =+S33*1000/R33 -> 137.48484 | U33: =+U32+T33 -> 1720.8302
A34: =+A33+1 -> 45808 | C34: =+C33+1 -> 28 | D34: =+'REGISTRO 2- lote 10'!$H$33 -> 6 | F34: =+F33-D34-E34 -> 4498 | G34: =+'REGISTRO 2- lote 10'!$H$20 -> 640 | H34: =+G34*1000/F34 -> 142.28546 | I34: =+I33+H34 -> 1973.5743 | J34: =+'REGISTRO 2- lote 10'!U20 -> 1450 | K34: =+J34-J27 -> 570 | L34: =+(J34-$J$6)/C34 -> 50.214286 | M34: =+I34/J34 -> 1.3610857 | N34: 1210-1350 | O34: =+O33+1 -> 28 | P34: =+'REGISTRO 2- lote 10'!$H$84 -> 4 | R34: =+R33-P34-Q34 -> 4942 | S34: =+'REGISTRO 2- lote 10'!$H$71 -> 720 | T34: =+S34*1000/R34 -> 145.69 | U34: =+U33+T34 -> 1866.5202 | V34: =+'REGISTRO 2- lote 10'!U71 -> 1400 | W34: =+V34-V27 -> 550 | X34: =+(V34-$J$6)/O34 -> 48.428571 | Y34: =+U34/V34 -> 1.3332287 | Z34: 1150-1320
A35: =+A34+1 -> 45809 | B35: Semana 5 | C35: =+C34+1 -> 29 | D35: =+'REGISTRO 2- lote 10'!$B$34 -> 4 | F35: =+F34-D35-E35 -> 4494 | G35: =+'REGISTRO 2- lote 10'!$B$21 -> 640 | H35: =+G35*1000/F35 -> 142.41211 | I35: =+I34+H35 -> 2115.9864 | O35: =+O34+1 -> 29 | P35: =+'REGISTRO 2- lote 10'!$B$85 -> 2 | R35: =+R34-P35-Q35 -> 4940 | S35: =+'REGISTRO 2- lote 10'!$B$72 -> 680 | T35: =+S35*1000/R35 -> 137.65182 | U35: =+U34+T35 -> 2004.172
A36: =+A35+1 -> 45810 | C36: =+C35+1 -> 30 | D36: =+'REGISTRO 2- lote 10'!$C$34 -> 4 | F36: =+F35-D36-E36 -> 4490 | G36: =+'REGISTRO 2- lote 10'!$C$21 -> 640 | H36: =+G36*1000/F36 -> 142.53898 | I36: =+I35+H36 -> 2258.5254 | O36: =+O35+1 -> 30 | P36: =+'REGISTRO 2- lote 10'!$C$85 -> 3 | R36: =+R35-P36-Q36 -> 4937 | S36: =+'REGISTRO 2- lote 10'!$C$72 -> 680 | T36: =+S36*1000/R36 -> 137.73547 | U36: =+U35+T36 -> 2141.9075
A37: =+A36+1 -> 45811 | C37: =+C36+1 -> 31 | D37: =+'REGISTRO 2- lote 10'!$D$34 -> 6 | F37: =+F36-D37-E37 -> 4484 | G37: =+'REGISTRO 2- lote 10'!$D$21 -> 680 | H37: =+G37*1000/F37 -> 151.65031 | I37: =+I36+H37 -> 2410.1757 | O37: =+O36+1 -> 31 | P37: =+'REGISTRO 2- lote 10'!$D$85 -> 1 | R37: =+R36-P37-Q37 -> 4936 | S37: =+'REGISTRO 2- lote 10'!$D$72 -> 680 | T37: =+S37*1000/R37 -> 137.76337 | U37: =+U36+T37 -> 2279.6709
A38: =+A37+1 -> 45812 | C38: =+C37+1 -> 32 | D38: =+'REGISTRO 2- lote 10'!$E$34 -> 3 | F38: =+F37-D38-E38 -> 4481 | G38: =+'REGISTRO 2- lote 10'!$E$21 -> 680 | H38: =+G38*1000/F38 -> 151.75184 | I38: =+I37+H38 -> 2561.9275 | O38: =+O37+1 -> 32 | P38: =+'REGISTRO 2- lote 10'!$E$85 -> 4 | R38: =+R37-P38-Q38 -> 4932 | S38: =+'REGISTRO 2- lote 10'!$E$72 -> 720 | T38: =+S38*1000/R38 -> 145.9854 | U38: =+U37+T38 -> 2425.6563
A39: =+A38+1 -> 45813 | C39: =+C38+1 -> 33 | D39: =+'REGISTRO 2- lote 10'!$F$34 -> 4 | F39: =+F38-D39-E39 -> 4477 | G39: =+'REGISTRO 2- lote 10'!$F$21 -> 720 | H39: =+G39*1000/F39 -> 160.82198 | I39: =+I38+H39 -> 2722.7495 | O39: =+O38+1 -> 33 | P39: =+'REGISTRO 2- lote 10'!$F$85 -> 2 | R39: =+R38-P39-Q39 -> 4930 | S39: =+'REGISTRO 2- lote 10'!$F$72 -> 720 | T39: =+S39*1000/R39 -> 146.04462 | U39: =+U38+T39 -> 2571.7009
A40: =+A39+1 -> 45814 | C40: =+C39+1 -> 34 | D40: =+'REGISTRO 2- lote 10'!$G$34 -> 7 | F40: =+F39-D40-E40 -> 4470 | G40: =+'REGISTRO 2- lote 10'!$G$21 -> 720 | H40: =+G40*1000/F40 -> 161.07383 | I40: =+I39+H40 -> 2883.8234 | O40: =+O39+1 -> 34 | P40: =+'REGISTRO 2- lote 10'!$G$85 -> 5 | R40: =+R39-P40-Q40 -> 4925 | S40: =+'REGISTRO 2- lote 10'!$G$72 -> 720 | T40: =+S40*1000/R40 -> 146.19289 | U40: =+U39+T40 -> 2717.8938
A41: =+A40+1 -> 45815 | C41: =+C40+1 -> 35 | D41: =+'REGISTRO 2- lote 10'!$H$34 -> 5 | F41: =+F40-D41-E41 -> 4465 | G41: =+'REGISTRO 2- lote 10'!$H$21 -> 720 | H41: =+G41*1000/F41 -> 161.2542 | I41: =+I40+H41 -> 3045.0776 | J41: =+'REGISTRO 2- lote 10'!U21 -> 8040 | K41: =+J41-J34 -> 6590 | L41: =+(J41-$J$6)/C41 -> 228.45714 | M41: =+I41/J41 -> 0.37874099 | N41: 1880-1950 | O41: =+O40+1 -> 35 | P41: =+'REGISTRO 2- lote 10'!$H$85 -> 2 | R41: =+R40-P41-Q41 -> 4923 | S41: =+'REGISTRO 2- lote 10'!$H$72 -> 720 | T41: =+S41*1000/R41 -> 146.25229 | U41: =+U40+T41 -> 2864.1461 | V41: =+'REGISTRO 2- lote 10'!U72 -> 1880 | W41: =+V41-V34 -> 480 | X41: =+(V41-$J$6)/O41 -> 52.457143 | Y41: =+U41/V41 -> 1.5234819 | Z41: 1750-1800
A42: =+A41+1 -> 45816 | B42: Semana 6 | C42: =+C41+1 -> 36 | D42: =+'REGISTRO 2- lote 10'!$B$35 -> 3 | F42: =+F41-D42-E42 -> 4462 | G42: =+'REGISTRO 2- lote 10'!$B$22 -> 720 | H42: =+G42*1000/F42 -> 161.36262 | I42: =+I41+H42 -> 3206.4402 | K42: =+J42-J41 -> -8040 | L42: =+(J42-$J$6)/C42 -> -1.2222222 | M42: =+I42/J42 -> #DIV/0! | N42: Sube 100-90 gr dia | O42: =+O41+1 -> 36 | P42: =+'REGISTRO 2- lote 10'!$B$86 -> 3 | R42: =+R41-P42-Q42 -> 4920 | S42: =+'REGISTRO 2- lote 10'!$B$73 -> 720 | T42: =+S42*1000/R42 -> 146.34146 | U42: =+U41+T42 -> 3010.4875 | W42: =+V42-V41 -> -1880 | X42: =+(V42-$J$6)/O42 -> -1.2222222 | Y42: =+U42/V42 -> #DIV/0! | Z42: Sube: 70gr- 80 x dia
A43: =+A42+1 -> 45817 | C43: =+C42+1 -> 37 | D43: =+'REGISTRO 2- lote 10'!$C$35 -> 4 | F43: =+F42-D43-E43 -> 4458 | G43: =+'REGISTRO 2- lote 10'!$C$22 -> 720 | H43: =+G43*1000/F43 -> 161.5074 | I43: =+I42+H43 -> 3367.9476 | K43: =+J43-J42 -> 0 | L43: =+(J43-$J$6)/C43 -> -1.1891892 | M43: =+I43/J43 -> #DIV/0! | O43: =+O42+1 -> 37 | P43: =+'REGISTRO 2- lote 10'!$C$86 -> 2 | R43: =+R42-P43-Q43 -> 4918 | S43: =+'REGISTRO 2- lote 10'!$C$73 -> 760 | T43: =+S43*1000/R43 -> 154.53436 | U43: =+U42+T43 -> 3165.0219 | W43: =+V43-V42 -> 0 | X43: =+(V43-$J$6)/O43 -> -1.1891892 | Y43: =+U43/V43 -> #DIV/0!
A44: =+A43+1 -> 45818 | C44: =+C43+1 -> 38 | D44: =+'REGISTRO 2- lote 10'!$D$35 -> 5 | F44: =+F43-D44-E44 -> 4453 | G44: =+'REGISTRO 2- lote 10'!$D$22 -> 760 | H44: =+G44*1000/F44 -> 170.67146 | I44: =+I43+H44 -> 3538.619 | K44: =+J44-J43 -> 0 | L44: =+(J44-$J$6)/C44 -> -1.1578947 | M44: =+I44/J44 -> #DIV/0! | O44: =+O43+1 -> 38 | P44: =+'REGISTRO 2- lote 10'!$D$86 -> 4 | R44: =+R43-P44-Q44 -> 4914 | S44: =+'REGISTRO 2- lote 10'!$D$73 -> 760 | T44: =+S44*1000/R44 -> 154.66015 | U44: =+U43+T44 -> 3319.682 | W44: =+V44-V43 -> 0 | X44: =+(V44-$J$6)/O44 -> -1.1578947 | Y44: =+U44/V44 -> #DIV/0!
A45: =+A44+1 -> 45819 | C45: =+C44+1 -> 39 | D45: =+'REGISTRO 2- lote 10'!$E$35 -> 6 | F45: =+F44-D45-E45 -> 4447 | G45: =+'REGISTRO 2- lote 10'!$E$22 -> 760 | H45: =+G45*1000/F45 -> 170.90173 | I45: =+I44+H45 -> 3709.5208 | K45: =+J45-J44 -> 0 | L45: =+(J45-$J$6)/C45 -> -1.1282051 | M45: =+I45/J45 -> #DIV/0! | O45: =+O44+1 -> 39 | P45: =+'REGISTRO 2- lote 10'!$E$86 -> 2 | R45: =+R44-P45-Q45 -> 4912 | S45: =+'REGISTRO 2- lote 10'!$E$73 -> 760 | T45: =+S45*1000/R45 -> 154.72313 | U45: =+U44+T45 -> 3474.4052 | W45: =+V45-V44 -> 0 | X45: =+(V45-$J$6)/O45 -> -1.1282051 | Y45: =+U45/V45 -> #DIV/0!
A46: =+A45+1 -> 45820 | C46: =+C45+1 -> 40 | D46: =+'REGISTRO 2- lote 10'!$F$35 -> 5 | F46: =+F45-D46-E46 -> 4442 | G46: =+'REGISTRO 2- lote 10'!$F$22 -> 760 | H46: =+G46*1000/F46 -> 171.0941 | I46: =+I45+H46 -> 3880.6149 | K46: =+J46-J45 -> 0 | L46: =+(J46-$J$6)/C46 -> -1.1 | M46: =+I46/J46 -> #DIV/0! | O46: =+O45+1 -> 40 | P46: =+'REGISTRO 2- lote 10'!$F$86 -> 3 | R46: =+R45-P46-Q46 -> 4909 | S46: =+'REGISTRO 2- lote 10'!$F$73 -> 760 | T46: =+S46*1000/R46 -> 154.81768 | U46: =+U45+T46 -> 3629.2228 | W46: =+V46-V45 -> 0 | X46: =+(V46-$J$6)/O46 -> -1.1 | Y46: =+U46/V46 -> #DIV/0!
A47: =+A46+1 -> 45821 | C47: =+C46+1 -> 41 | D47: =+'REGISTRO 2- lote 10'!$G$35 -> 4 | F47: =+F46-D47-E47 -> 4438 | G47: =+'REGISTRO 2- lote 10'!$G$22 -> 760 | H47: =+G47*1000/F47 -> 171.24831 | I47: =+I46+H47 -> 4051.8632 | K47: =+J47-J46 -> 0 | L47: =+(J47-$J$6)/C47 -> -1.0731707 | M47: =+I47/J47 -> #DIV/0! | O47: =+O46+1 -> 41 | P47: =+'REGISTRO 2- lote 10'!$G$86 -> 3 | R47: =+R46-P47-Q47 -> 4906 | S47: =+'REGISTRO 2- lote 10'!$G$73 -> 760 | T47: =+S47*1000/R47 -> 154.91235 | U47: =+U46+T47 -> 3784.1352 | W47: =+V47-V46 -> 0 | X47: =+(V47-$J$6)/O47 -> -1.0731707 | Y47: =+U47/V47 -> #DIV/0!
A48: =+A47+1 -> 45822 | C48: =+C47+1 -> 42 | D48: =+'REGISTRO 2- lote 10'!$H$35 -> 6 | F48: =+F47-D48-E48 -> 4432 | G48: =+'REGISTRO 2- lote 10'!$H$22 -> 760 | H48: =+G48*1000/F48 -> 171.48014 | I48: =+I47+H48 -> 4223.3433 | K48: =+J48-J47 -> 0 | L48: =+(J48-$J$6)/C48 -> -1.047619 | M48: =+I48/J48 -> #DIV/0! | O48: =+O47+1 -> 42 | P48: =+'REGISTRO 2- lote 10'!$H$86 -> 4 | R48: =+R47-P48-Q48 -> 4902 | S48: =+'REGISTRO 2- lote 10'!$H$73 -> 760 | T48: =+S48*1000/R48 -> 155.03876 | U48: =+U47+T48 -> 3939.174 | W48: =+V48-V47 -> 0 | X48: =+(V48-$J$6)/O48 -> -1.047619 | Y48: =+U48/V48 -> #DIV/0!
A49: =+A48+1 -> 45823 | B49: Semana 7 | C49: =+C48+1 -> 43 | D49: =+'REGISTRO 2- lote 10'!$B$36 -> 4 | F49: =+F48-D49-E49 -> 4428 | G49: =+'REGISTRO 2- lote 10'!$B$23 -> 720 | H49: =+G49*1000/F49 -> 162.60163 | I49: =+I48+H49 -> 4385.9449 | K49: =+J49-J48 -> 0 | L49: =+(J49-$J$6)/C49 -> -1.0232558 | M49: =+I49/J49 -> #DIV/0! | O49: =+O48+1 -> 43 | P49: =+'REGISTRO 2- lote 10'!$B$87 -> 2 | R49: =+R48-P49-Q49 -> 4900 | S49: =+'REGISTRO 2- lote 10'!$B$74 -> 760 | T49: =+S49*1000/R49 -> 155.10204 | U49: =+U48+T49 -> 4094.276 | W49: =+V49-V48 -> 0 | X49: =+(V49-$J$6)/O49 -> -1.0232558 | Y49: =+U49/V49 -> #DIV/0!
A50: =+A49+1 -> 45824 | C50: =+C49+1 -> 44 | D50: =+'REGISTRO 2- lote 10'!$C$36 -> 5 | F50: =+F49-D50-E50 -> 4423 | G50: =+'REGISTRO 2- lote 10'!$C$23 -> 720 | H50: =+G50*1000/F50 -> 162.78544 | I50: =+I49+H50 -> 4548.7304 | K50: =+J50-J49 -> 0 | L50: =+(J50-$J$6)/C50 -> -1 | M50: =+I50/J50 -> #DIV/0! | O50: =+O49+1 -> 44 | P50: =+'REGISTRO 2- lote 10'!$C$87 -> 4 | R50: =+R49-P50-Q50 -> 4896 | S50: =+'REGISTRO 2- lote 10'!$C$74 -> 760 | T50: =+S50*1000/R50 -> 155.22876 | U50: =+U49+T50 -> 4249.5048 | W50: =+V50-V49 -> 0 | X50: =+(V50-$J$6)/O50 -> -1 | Y50: =+U50/V50 -> #DIV/0!
A51: =+A50+1 -> 45825 | C51: =+C50+1 -> 45 | D51: =+'REGISTRO 2- lote 10'!$D$36 -> 6 | F51: =+F50-D51-E51 -> 4417 | G51: =+'REGISTRO 2- lote 10'!$D$23 -> 720 | H51: =+G51*1000/F51 -> 163.00657 | I51: =+I50+H51 -> 4711.7369 | K51: =+J51-J50 -> 0 | L51: =+(J51-$J$6)/C51 -> -0.97777778 | M51: =+I51/J51 -> #DIV/0! | O51: =+O50+1 -> 45 | P51: =+'REGISTRO 2- lote 10'!$D$87 -> 3 | R51: =+R50-P51-Q51 -> 4893 | S51: =+'REGISTRO 2- lote 10'!$D$74 -> 760 | T51: =+S51*1000/R51 -> 155.32393 | U51: =+U50+T51 -> 4404.8287 | W51: =+V51-V50 -> 0 | X51: =+(V51-$J$6)/O51 -> -0.97777778 | Y51: =+U51/V51 -> #DIV/0!
A52: =+A51+1 -> 45826 | C52: =+C51+1 -> 46 | D52: =+'REGISTRO 2- lote 10'!$E$36 -> 5 | F52: =+F51-D52-E52 -> 4412 | G52: =+'REGISTRO 2- lote 10'!$E$23 -> 720 | H52: =+G52*1000/F52 -> 163.1913 | I52: =+I51+H52 -> 4874.9282 | K52: =+J52-J51 -> 0 | L52: =+(J52-$J$6)/C52 -> -0.95652174 | M52: =+I52/J52 -> #DIV/0! | O52: =+O51+1 -> 46 | P52: =+'REGISTRO 2- lote 10'!$E$87 -> 6 | R52: =+R51-P52-Q52 -> 4887 | S52: =+'REGISTRO 2- lote 10'!$E$74 -> 760 | T52: =+S52*1000/R52 -> 155.51463 | U52: =+U51+T52 -> 4560.3433 | W52: =+V52-V51 -> 0 | X52: =+(V52-$J$6)/O52 -> -0.95652174 | Y52: =+U52/V52 -> #DIV/0!
A53: =+A52+1 -> 45827 | C53: =+C52+1 -> 47 | D53: =+'REGISTRO 2- lote 10'!$F$36 -> 4 | F53: =+F52-D53-E53 -> 4408 | G53: =+'REGISTRO 2- lote 10'!$F$23 -> 600 | H53: =+G53*1000/F53 -> 136.11615 | I53: =+I52+H53 -> 5011.0444 | K53: =+J53-J52 -> 0 | L53: =+(J53-$J$6)/C53 -> -0.93617021 | M53: =+I53/J53 -> #DIV/0! | O53: =+O52+1 -> 47 | P53: =+'REGISTRO 2- lote 10'!$F$87 -> 4 | R53: =+R52-P53-Q53 -> 4883 | S53: =+'REGISTRO 2- lote 10'!$F$74 -> 760 | T53: =+S53*1000/R53 -> 155.64202 | U53: =+U52+T53 -> 4715.9853 | W53: =+V53-V52 -> 0 | X53: =+(V53-$J$6)/O53 -> -0.93617021 | Y53: =+U53/V53 -> #DIV/0!
A54: =+A53+1 -> 45828 | C54: =+C53+1 -> 48 | D54: =+'REGISTRO 2- lote 10'!$G$36 -> 4 | F54: =+F53-D54-E54 -> 4404 | G54: =+'REGISTRO 2- lote 10'!$G$23 -> 400 | H54: =+G54*1000/F54 -> 90.826521 | I54: =+I53+H54 -> 5101.8709 | K54: =+J54-J53 -> 0 | L54: =+(J54-$J$6)/C54 -> -0.91666667 | M54: =+I54/J54 -> #DIV/0! | O54: =+O53+1 -> 48 | P54: =+'REGISTRO 2- lote 10'!$G$87 -> 7 | R54: =+R53-P54-Q54 -> 4876 | S54: =+'REGISTRO 2- lote 10'!$G$74 -> 760 | T54: =+S54*1000/R54 -> 155.86546 | U54: =+U53+T54 -> 4871.8508 | W54: =+V54-V53 -> 0 | X54: =+(V54-$J$6)/O54 -> -0.91666667 | Y54: =+U54/V54 -> #DIV/0!
A55: =+A54+1 -> 45829 | C55: =+C54+1 -> 49 | D55: =+'REGISTRO 2- lote 10'!$H$36 -> 6 | F55: =+F54-D55-E55 -> 4398 | G55: =+'REGISTRO 2- lote 10'!$H$23 -> 0 | H55: =+G55*1000/F55 -> 0 | I55: =+I54+H55 -> 5101.8709 | K55: =+J55-J54 -> 0 | L55: =+(J55-$J$6)/C55 -> -0.89795918 | M55: =+I55/J55 -> #DIV/0! | O55: =+O54+1 -> 49 | P55: =+'REGISTRO 2- lote 10'!$H$87 -> 9 | R55: =+R54-P55-Q55 -> 4867 | S55: =+'REGISTRO 2- lote 10'!$H$74 -> 760 | T55: =+S55*1000/R55 -> 156.15369 | U55: =+U54+T55 -> 5028.0045 | W55: =+V55-V54 -> 0 | X55: =+(V55-$J$6)/O55 -> -0.89795918 | Y55: =+U55/V55 -> #DIV/0!
A56: =+A55+1 -> 45830 | B56: Semana 8 | C56: =+C55+1 -> 50 | D56: =+'REGISTRO 2- lote 10'!$B$37 -> 0 | F56: =+F55-D56-E56 -> 4398 | G56: =+'REGISTRO 2- lote 10'!$B$24 -> 0 | H56: =+G56*1000/F56 -> 0 | I56: =+I55+H56 -> 5101.8709 | K56: =+J56-J55 -> 0 | L56: =+(J56-$J$6)/C56 -> -0.88 | M56: =+I56/J56 -> #DIV/0! | O56: =+O55+1 -> 50 | P56: =+'REGISTRO 2- lote 10'!$B$88 -> 0 | R56: =+R55-P56-Q56 -> 4867 | S56: =+'REGISTRO 2- lote 10'!$B$75 -> 0 | T56: =+S56*1000/R56 -> 0 | U56: =+U55+T56 -> 5028.0045 | W56: =+V56-V55 -> 0 | X56: =+(V56-$J$6)/O56 -> -0.88 | Y56: =+U56/V56 -> #DIV/0!
A57: =+A56+1 -> 45831 | C57: =+C56+1 -> 51 | D57: =+'REGISTRO 2- lote 10'!$C$37 -> 0 | F57: =+F56-D57-E57 -> 4398 | G57: =+'REGISTRO 2- lote 10'!$C$24 -> 0 | H57: =+G57*1000/F57 -> 0 | I57: =+I56+H57 -> 5101.8709 | K57: =+J57-J56 -> 0 | L57: =+(J57-$J$6)/C57 -> -0.8627451 | M57: =+I57/J57 -> #DIV/0! | O57: =+O56+1 -> 51 | P57: =+'REGISTRO 2- lote 10'!$C$88 -> 0 | R57: =+R56-P57-Q57 -> 4867 | S57: =+'REGISTRO 2- lote 10'!$C$75 -> 0 | T57: =+S57*1000/R57 -> 0 | U57: =+U56+T57 -> 5028.0045 | W57: =+V57-V56 -> 0 | X57: =+(V57-$J$6)/O57 -> -0.8627451 | Y57: =+U57/V57 -> #DIV/0!
A58: =+A57+1 -> 45832 | C58: =+C57+1 -> 52 | D58: =+'REGISTRO 2- lote 10'!$D$37 -> 0 | F58: =+F57-D58-E58 -> 4398 | G58: =+'REGISTRO 2- lote 10'!$D$24 -> 0 | H58: =+G58*1000/F58 -> 0 | I58: =+I57+H58 -> 5101.8709 | K58: =+J58-J57 -> 0 | L58: =+(J58-$J$6)/C58 -> -0.84615385 | M58: =+I58/J58 -> #DIV/0! | O58: =+O57+1 -> 52 | P58: =+'REGISTRO 2- lote 10'!$D$88 -> 0 | R58: =+R57-P58-Q58 -> 4867 | S58: =+'REGISTRO 2- lote 10'!$D$75 -> 0 | T58: =+S58*1000/R58 -> 0 | U58: =+U57+T58 -> 5028.0045 | W58: =+V58-V57 -> 0 | X58: =+(V58-$J$6)/O58 -> -0.84615385 | Y58: =+U58/V58 -> #DIV/0!
A59: =+A58+1 -> 45833 | C59: =+C58+1 -> 53 | D59: =+'REGISTRO 2- lote 10'!$E$37 -> 0 | F59: =+F58-D59-E59 -> 4398 | G59: =+'REGISTRO 2- lote 10'!$E$24 -> 0 | H59: =+G59*1000/F59 -> 0 | I59: =+I58+H59 -> 5101.8709 | K59: =+J59-J58 -> 0 | L59: =+(J59-$J$6)/C59 -> -0.83018868 | M59: =+I59/J59 -> #DIV/0! | O59: =+O58+1 -> 53 | P59: =+'REGISTRO 2- lote 10'!$E$88 -> 0 | R59: =+R58-P59-Q59 -> 4867 | S59: =+'REGISTRO 2- lote 10'!$E$75 -> 0 | T59: =+S59*1000/R59 -> 0 | U59: =+U58+T59 -> 5028.0045 | W59: =+V59-V58 -> 0 | X59: =+(V59-$J$6)/O59 -> -0.83018868 | Y59: =+U59/V59 -> #DIV/0!
A60: =+A59+1 -> 45834 | C60: =+C59+1 -> 54 | D60: =+'REGISTRO 2- lote 10'!$F$37 -> 0 | F60: =+F59-D60-E60 -> 4398 | G60: =+'REGISTRO 2- lote 10'!$F$24 -> 0 | H60: =+G60*1000/F60 -> 0 | I60: =+I59+H60 -> 5101.8709 | K60: =+J60-J59 -> 0 | L60: =+(J60-$J$6)/C60 -> -0.81481481 | M60: =+I60/J60 -> #DIV/0! | O60: =+O59+1 -> 54 | P60: =+'REGISTRO 2- lote 10'!$F$88 -> 0 | R60: =+R59-P60-Q60 -> 4867 | S60: =+'REGISTRO 2- lote 10'!$F$75 -> 0 | T60: =+S60*1000/R60 -> 0 | U60: =+U59+T60 -> 5028.0045 | W60: =+V60-V59 -> 0 | X60: =+(V60-$J$6)/O60 -> -0.81481481 | Y60: =+U60/V60 -> #DIV/0!
A61: =+A60+1 -> 45835 | C61: =+C60+1 -> 55 | D61: =+'REGISTRO 2- lote 10'!$G$37 -> 0 | F61: =+F60-D61-E61 -> 4398 | G61: =+'REGISTRO 2- lote 10'!$G$24 -> 0 | H61: =+G61*1000/F61 -> 0 | I61: =+I60+H61 -> 5101.8709 | K61: =+J61-J60 -> 0 | L61: =+(J61-$J$6)/C61 -> -0.8 | M61: =+I61/J61 -> #DIV/0! | O61: =+O60+1 -> 55 | P61: =+'REGISTRO 2- lote 10'!$G$88 -> 0 | R61: =+R60-P61-Q61 -> 4867 | S61: =+'REGISTRO 2- lote 10'!$G$75 -> 0 | T61: =+S61*1000/R61 -> 0 | U61: =+U60+T61 -> 5028.0045 | W61: =+V61-V60 -> 0 | X61: =+(V61-$J$6)/O61 -> -0.8 | Y61: =+U61/V61 -> #DIV/0!
A62: =+A61+1 -> 45836 | C62: =+C61+1 -> 56 | D62: =+'REGISTRO 2- lote 10'!$H$37 -> 0 | F62: =+F61-D62-E62 -> 4398 | G62: =+'REGISTRO 2- lote 10'!$H$24 -> 0 | H62: =+G62*1000/F62 -> 0 | I62: =+I61+H62 -> 5101.8709 | K62: =+J62-J61 -> 0 | L62: =+(J62-$J$6)/C62 -> -0.78571429 | M62: =+I62/J62 -> #DIV/0! | O62: =+O61+1 -> 56 | P62: =+'REGISTRO 2- lote 10'!$H$88 -> 0 | R62: =+R61-P62-Q62 -> 4867 | S62: =+'REGISTRO 2- lote 10'!$H$75 -> 0 | T62: =+S62*1000/R62 -> 0 | U62: =+U61+T62 -> 5028.0045 | W62: =+V62-V61 -> 0 | X62: =+(V62-$J$6)/O62 -> -0.78571429 | Y62: =+U62/V62 -> #DIV/0!
A63: =+A62+1 -> 45837 | B63: Semana 9 | C63: =+C62+1 -> 57 | D63: =+'REGISTRO 2- lote 10'!$B$38 -> 0 | F63: =+F62-D63-E63 -> 4398 | G63: =+'REGISTRO 2- lote 10'!$B$25 -> 0 | H63: =+G63*1000/F63 -> 0 | I63: =+I62+H63 -> 5101.8709 | K63: =+J63-J62 -> 0 | L63: =+(J63-$J$6)/C63 -> -0.77192982 | M63: =+I63/J63 -> #DIV/0! | O63: =+O62+1 -> 57 | P63: =+'REGISTRO 2- lote 10'!$B$89 -> 0 | R63: =+R62-P63-Q63 -> 4867 | S63: =+'REGISTRO 2- lote 10'!$B$76 -> 0 | T63: =+S63*1000/R63 -> 0 | U63: =+U62+T63 -> 5028.0045 | W63: =+V63-V62 -> 0 | X63: =+(V63-$J$6)/O63 -> -0.77192982 | Y63: =+U63/V63 -> #DIV/0!
A64: =+A63+1 -> 45838 | C64: =+C63+1 -> 58 | D64: =+'REGISTRO 2- lote 10'!$C$38 -> 0 | F64: =+F63-D64-E64 -> 4398 | G64: =+'REGISTRO 2- lote 10'!$C$25 -> 0 | H64: =+G64*1000/F64 -> 0 | I64: =+I63+H64 -> 5101.8709 | K64: =+J64-J63 -> 0 | L64: =+(J64-$J$6)/C64 -> -0.75862069 | M64: =+I64/J64 -> #DIV/0! | O64: =+O63+1 -> 58 | P64: =+'REGISTRO 2- lote 10'!$C$89 -> 0 | R64: =+R63-P64-Q64 -> 4867 | S64: =+'REGISTRO 2- lote 10'!$C$76 -> 0 | T64: =+S64*1000/R64 -> 0 | U64: =+U63+T64 -> 5028.0045 | W64: =+V64-V63 -> 0 | X64: =+(V64-$J$6)/O64 -> -0.75862069 | Y64: =+U64/V64 -> #DIV/0!
A65: =+A64+1 -> 45839 | C65: =+C64+1 -> 59 | D65: =+'REGISTRO 2- lote 10'!$D$38 -> 0 | F65: =+F64-D65-E65 -> 4398 | G65: =+'REGISTRO 2- lote 10'!$D$25 -> 0 | H65: =+G65*1000/F65 -> 0 | I65: =+I64+H65 -> 5101.8709 | K65: =+J65-J64 -> 0 | L65: =+(J65-$J$6)/C65 -> -0.74576271 | M65: =+I65/J65 -> #DIV/0! | O65: =+O64+1 -> 59 | P65: =+'REGISTRO 2- lote 10'!$D$89 -> 0 | R65: =+R64-P65-Q65 -> 4867 | S65: =+'REGISTRO 2- lote 10'!$D$76 -> 0 | T65: =+S65*1000/R65 -> 0 | U65: =+U64+T65 -> 5028.0045 | W65: =+V65-V64 -> 0 | X65: =+(V65-$J$6)/O65 -> -0.74576271 | Y65: =+U65/V65 -> #DIV/0!
A66: =+A65+1 -> 45840 | C66: =+C65+1 -> 60 | D66: =+'REGISTRO 2- lote 10'!$E$38 -> 0 | F66: =+F65-D66-E66 -> 4398 | G66: =+'REGISTRO 2- lote 10'!$E$25 -> 0 | H66: =+G66*1000/F66 -> 0 | I66: =+I65+H66 -> 5101.8709 | K66: =+J66-J65 -> 0 | L66: =+(J66-$J$6)/C66 -> -0.73333333 | M66: =+I66/J66 -> #DIV/0! | O66: =+O65+1 -> 60 | P66: =+'REGISTRO 2- lote 10'!$E$89 -> 0 | R66: =+R65-P66-Q66 -> 4867 | S66: =+'REGISTRO 2- lote 10'!$E$76 -> 0 | T66: =+S66*1000/R66 -> 0 | U66: =+U65+T66 -> 5028.0045 | W66: =+V66-V65 -> 0 | X66: =+(V66-$J$6)/O66 -> -0.73333333 | Y66: =+U66/V66 -> #DIV/0!
A67: =+A66+1 -> 45841 | C67: =+C66+1 -> 61 | D67: =+'REGISTRO 2- lote 10'!$F$38 -> 0 | F67: =+F66-D67-E67 -> 4398 | G67: =+'REGISTRO 2- lote 10'!$F$25 -> 0 | H67: =+G67*1000/F67 -> 0 | I67: =+I66+H67 -> 5101.8709 | K67: =+J67-J66 -> 0 | L67: =+(J67-$J$6)/C67 -> -0.72131148 | M67: =+I67/J67 -> #DIV/0! | O67: =+O66+1 -> 61 | P67: =+'REGISTRO 2- lote 10'!$F$89 -> 0 | R67: =+R66-P67-Q67 -> 4867 | S67: =+'REGISTRO 2- lote 10'!$F$76 -> 0 | T67: =+S67*1000/R67 -> 0 | U67: =+U66+T67 -> 5028.0045 | W67: =+V67-V66 -> 0 | X67: =+(V67-$J$6)/O67 -> -0.72131148 | Y67: =+U67/V67 -> #DIV/0!
A68: =+A67+1 -> 45842 | C68: =+C67+1 -> 62 | D68: =+'REGISTRO 2- lote 10'!$G$38 -> 0 | F68: =+F67-D68-E68 -> 4398 | G68: =+'REGISTRO 2- lote 10'!$G$25 -> 0 | H68: =+G68*1000/F68 -> 0 | I68: =+I67+H68 -> 5101.8709 | K68: =+J68-J67 -> 0 | L68: =+(J68-$J$6)/C68 -> -0.70967742 | M68: =+I68/J68 -> #DIV/0! | O68: =+O67+1 -> 62 | P68: =+'REGISTRO 2- lote 10'!$G$89 -> 0 | R68: =+R67-P68-Q68 -> 4867 | S68: =+'REGISTRO 2- lote 10'!$G$76 -> 0 | T68: =+S68*1000/R68 -> 0 | U68: =+U67+T68 -> 5028.0045 | W68: =+V68-V67 -> 0 | X68: =+(V68-$J$6)/O68 -> -0.70967742 | Y68: =+U68/V68 -> #DIV/0!
A69: =+A68+1 -> 45843 | C69: =+C68+1 -> 63 | D69: =+'REGISTRO 2- lote 10'!$H$38 -> 0 | F69: =+F68-D69-E69 -> 4398 | G69: =+'REGISTRO 2- lote 10'!$H$25 -> 0 | H69: =+G69*1000/F69 -> 0 | I69: =+I68+H69 -> 5101.8709 | K69: =+J69-J68 -> 0 | L69: =+(J69-$J$6)/C69 -> -0.6984127 | M69: =+I69/J69 -> #DIV/0! | O69: =+O68+1 -> 63 | P69: =+'REGISTRO 2- lote 10'!$H$89 -> 0 | R69: =+R68-P69-Q69 -> 4867 | S69: =+'REGISTRO 2- lote 10'!$H$76 -> 0 | T69: =+S69*1000/R69 -> 0 | U69: =+U68+T69 -> 5028.0045 | W69: =+V69-V68 -> 0 | X69: =+(V69-$J$6)/O69 -> -0.6984127 | Y69: =+U69/V69 -> #DIV/0!
E70: TOTAL | F70: =+F69 -> 4398 | G70: =+SUM(G6:G69) -> 22860 | Q70: TOTAL | R70: =+R69 -> 4867 | S70: =+SUM(S6:S69) -> 24820 | Y70: TOTAL | Z70: =+F70+R70 -> 9265 | AA70: =+G70+S70 -> 47680
E71: CONSUMO X POLLO | G71: =+G70/F70 -> 5.1978172 | Q71: CONSUMO X POLLO | S71: =+S70/R70 -> 5.0996507 | Y71: CONSUMO X POLLO | AA71: =+AA70/Z70 -> 5.1462493

Sheet REGISTRO TOTAL
B1: AVICOLA SAN LORENZO
B2: GRANJA : | E2: SAN LORENZO
B3: RESPONSABLE : | E3: =+'REGISTRO 1- lote 9'!E3 -> 0 | O3: MACHO
B5: GALPON | D5: LOTE | G5: INCUBADORA | K5: CANTIDAD INICIAL | O5: PESO PROMEDIO INIC.
B6: =+'REGISTRO 1- lote 9'!B6:C6 -> T1 | D6: =+'REGISTRO 1- lote 9'!D6:E6 -> 49 | G6: =+'REGISTRO 1- lote 9'!G6:J6 -> FINAVES | K6: =+'REGISTRO 2- lote 10'!K6:N6+'REGISTRO 1- lote 9'!K6:N6 -> 11238 | O6: =+('REGISTRO 1- lote 9'!O6:R6+'REGISTRO 2- lote 10'!O6:R6)/2 -> 44
B8: FECHA INICIO | G8: =+'REGISTRO 2- lote 10'!G8:J8 -> 45780 | L8: DIAS DE ENGORDE: | P8: =(G9-G8)+1 -> 52
B9: FECHA TERMINACION | G9: =+PESAS!B19 -> 45831 | L9: DIAS PROMEDIO
B11: POLLOS VENDIDOS | G11: =+PESAS!M39 -> 10553 | Z11: conversion: kilos concentrado/ kilos en pie
B12: PESO TOTAL FINAL | G12: =+PESAS!M40 -> 32404.24 | L12: CONSUMO TOTAL DEL LOTE | Q12: =+T25 -> 5.2206857 | Z12: se necesita xxx kilos concentrado para producir 1 kilo de pollo en pie
Z13: Entre mas bajo mejor
I14: TOTAL CONSUMO | Q14: CONSUMO POR AVE | U14: PESO
A15: KILOS CONSUMIDOS | I15: SEMANAL | M15: ACUMULADO | Q15: (Gramos) | T15: CONSUMO | U15: GRAMOS | V15: gramos | Z15: BULTOS CONSUMIDOS
A16: S/D | B16: =+'REGISTRO 2- lote 10'!B16 -> S | C16: =+'REGISTRO 2- lote 10'!C16 -> D | D16: =+'REGISTRO 2- lote 10'!D16 -> L | E16: =+'REGISTRO 2- lote 10'!E16 -> M | F16: =+'REGISTRO 2- lote 10'!F16 -> M | G16: =+'REGISTRO 2- lote 10'!G16 -> J | H16: =+'REGISTRO 2- lote 10'!H16 -> V | I16: Bultos | K16: Kilos | M16: Bultos | O16: Kilos | Q16: Diario | R16: Sem. | S16: Acumul. | T16: KL. | U16: PROMEDIO | V16: Ganancia dia | W16: Conversion | X16: VPI | Z16: S/D | AA16: =+B16 -> S | AB16: =+C16 -> D | AC16: =+D16 -> L | AD16: =+E16 -> M | AE16: =+F16 -> M | AF16: =+G16 -> J | AG16: =+H16 -> V | AH16: TOTAL
A17: 1 | B17: =+'REGISTRO 2- lote 10'!B17+'REGISTRO 1- lote 9'!B17 -> 160 | C17: =+'REGISTRO 2- lote 10'!C17+'REGISTRO 1- lote 9'!C17 -> 160 | D17: =+'REGISTRO 2- lote 10'!D17+'REGISTRO 1- lote 9'!D17 -> 200 | E17: =+'REGISTRO 2- lote 10'!E17+'REGISTRO 1- lote 9'!E17 -> 260 | F17: =+'REGISTRO 2- lote 10'!F17+'REGISTRO 1- lote 9'!F17 -> 280 | G17: =+'REGISTRO 2- lote 10'!G17+'REGISTRO 1- lote 9'!G17 -> 320 | H17: =+'REGISTRO 2- lote 10'!H17+'REGISTRO 1- lote 9'!H17 -> 400 | I17: =+K17/40 -> 44.5 | K17: =SUM(B17:H17) -> 1780 | M17: =+I17 -> 44.5 | O17: =+K17 -> 1780 | Q17: =+R17/7 -> 23.066556 | R17: =+K17*1000/S30 -> 161.46589 | S17: =+R17 -> 161.46589 | T17: =+O17/S30 -> 0.16146589 | U17: =+('REGISTRO 1- lote 9'!U17+'REGISTRO 2- lote 10'!U17)/2 -> 194 | V17: =(U17-O6)/7 -> 21.428571 | W17: =+O17/(S30*(U17/1000)) -> 0.83229842 | X17: =+U17/O6 -> 4.4090909 | Z17: 1 | AA17: =+'REGISTRO 2- lote 10'!AA17+'REGISTRO 1- lote 9'!AA17 -> 4 | AB17: =+'REGISTRO 2- lote 10'!AB17+'REGISTRO 1- lote 9'!AB17 -> 4 | AC17: =+'REGISTRO 2- lote 10'!AC17+'REGISTRO 1- lote 9'!AC17 -> 5 | AD17: =+'REGISTRO 2- lote 10'!AD17+'REGISTRO 1- lote 9'!AD17 -> 6.5 | AE17: =+'REGISTRO 2- lote 10'!AE17+'REGISTRO 1- lote 9'!AE17 -> 7 | AF17: =+'REGISTRO 2- lote 10'!AF17+'REGISTRO 1- lote 9'!AF17 -> 8 | AG17: =+'REGISTRO 2- lote 10'!AG17+'REGISTRO 1- lote 9'!AG17 -> 10 | AH17: =+SUM(AA17:AG17) -> 44.5
A18: 2 | B18: =+'REGISTRO 2- lote 10'!B18+'REGISTRO 1- lote 9'!B18 -> 400 | C18: =+'REGISTRO 2- lote 10'!C18+'REGISTRO 1- lote 9'!C18 -> 400 | D18: =+'REGISTRO 2- lote 10'!D18+'REGISTRO 1- lote 9'!D18 -> 480 | E18: =+'REGISTRO 2- lote 10'!E18+'REGISTRO 1- lote 9'!E18 -> 560 | F18: =+'REGISTRO 2- lote 10'!F18+'REGISTRO 1- lote 9'!F18 -> 600 | G18: =+'REGISTRO 2- lote 10'!G18+'REGISTRO 1- lote 9'!G18 -> 660 | H18: =+'REGISTRO 2- lote 10'!H18+'REGISTRO 1- lote 9'!H18 -> 720 | I18: =+K18/40 -> 95.5 | K18: =SUM(B18:H18) -> 3820 | M18: =+M17+I18 -> 140 | O18: =+O17+K18 -> 5600 | Q18: =+R18/7 -> 49.905284 | R18: =+K18*1000/S31 -> 349.33699 | S18: =+O18*1000/S31 -> 512.11706 | T18: =+O18/S31 -> 0.51211706 | U18: =+('REGISTRO 1- lote 9'!U18+'REGISTRO 2- lote 10'!U18)/2 -> 455 | V18: =+(U18-U17)/7 -> 37.285714 | W18: =+O18/(S31*(U18/1000)) -> 1.125532 | X18: =+U18/U17 -> 2.3453608 | Z18: 2 | AA18: =+'REGISTRO 2- lote 10'!AA18+'REGISTRO 1- lote 9'!AA18 -> 10 | AB18: =+'REGISTRO 2- lote 10'!AB18+'REGISTRO 1- lote 9'!AB18 -> 10 | AC18: =+'REGISTRO 2- lote 10'!AC18+'REGISTRO 1- lote 9'!AC18 -> 12 | AD18: =+'REGISTRO 2- lote 10'!AD18+'REGISTRO 1- lote 9'!AD18 -> 14 | AE18: =+'REGISTRO 2- lote 10'!AE18+'REGISTRO 1- lote 9'!AE18 -> 15 | AF18: =+'REGISTRO 2- lote 10'!AF18+'REGISTRO 1- lote 9'!AF18 -> 16.5 | AG18: =+'REGISTRO 2- lote 10'!AG18+'REGISTRO 1- lote 9'!AG18 -> 18 | AH18: =+SUM(AA18:AG18) -> 95.5
A19: 3 | B19: =+'REGISTRO 2- lote 10'!B19+'REGISTRO 1- lote 9'!B19 -> 720 | C19: =+'REGISTRO 2- lote 10'!C19+'REGISTRO 1- lote 9'!C19 -> 760 | D19: =+'REGISTRO 2- lote 10'!D19+'REGISTRO 1- lote 9'!D19 -> 840 | E19: =+'REGISTRO 2- lote 10'!E19+'REGISTRO 1- lote 9'!E19 -> 880 | F19: =+'REGISTRO 2- lote 10'!F19+'REGISTRO 1- lote 9'!F19 -> 960 | G19: =+'REGISTRO 2- lote 10'!G19+'REGISTRO 1- lote 9'!G19 -> 1040 | H19: =+'REGISTRO 2- lote 10'!H19+'REGISTRO 1- lote 9'!H19 -> 1080 | I19: =+K19/40 -> 157 | K19: =SUM(B19:H19) -> 6280 | M19: =+M18+I19 -> 297 | O19: =+O18+K19 -> 11880 | Q19: =+R19/7 -> 82.511069 | R19: =+K19*1000/S32 -> 577.57749 | S19: =+O19*1000/S32 -> 1092.6147 | T19: =+O19/S32 -> 1.0926147 | U19: =+('REGISTRO 1- lote 9'!U19+'REGISTRO 2- lote 10'!U19)/2 -> 880 | V19: =+(U19-U18)/7 -> 60.714286 | W19: =+O19/(S32*(U19/1000)) -> 1.2416077 | X19: =+U19/U18 -> 1.9340659 | Z19: 3 | AA19: =+'REGISTRO 2- lote 10'!AA19+'REGISTRO 1- lote 9'!AA19 -> 18 | AB19: =+'REGISTRO 2- lote 10'!AB19+'REGISTRO 1- lote 9'!AB19 -> 19 | AC19: =+'REGISTRO 2- lote 10'!AC19+'REGISTRO 1- lote 9'!AC19 -> 21 | AD19: =+'REGISTRO 2- lote 10'!AD19+'REGISTRO 1- lote 9'!AD19 -> 22 | AE19: =+'REGISTRO 2- lote 10'!AE19+'REGISTRO 1- lote 9'!AE19 -> 24 | AF19: =+'REGISTRO 2- lote 10'!AF19+'REGISTRO 1- lote 9'!AF19 -> 26 | AG19: =+'REGISTRO 2- lote 10'!AG19+'REGISTRO 1- lote 9'!AG19 -> 27 | AH19: =+SUM(AA19:AG19) -> 157
A20: 4 | B20: =+'REGISTRO 2- lote 10'!B20+'REGISTRO 1- lote 9'!B20 -> 1160 | C20: =+'REGISTRO 2- lote 10'!C20+'REGISTRO 1- lote 9'!C20 -> 1200 | D20: =+'REGISTRO 2- lote 10'!D20+'REGISTRO 1- lote 9'!D20 -> 1280 | E20: =+'REGISTRO 2- lote 10'!E20+'REGISTRO 1- lote 9'!E20 -> 1360 | F20: =+'REGISTRO 2- lote 10'!F20+'REGISTRO 1- lote 9'!F20 -> 1440 | G20: =+'REGISTRO 2- lote 10'!G20+'REGISTRO 1- lote 9'!G20 -> 1520 | H20: =+'REGISTRO 2- lote 10'!H20+'REGISTRO 1- lote 9'!H20 -> 1520 | I20: =+K20/40 -> 237 | K20: =SUM(B20:H20) -> 9480 | M20: =+M19+I20 -> 534 | O20: =+O19+K20 -> 21360 | Q20: =+R20/7 -> 125.11878 | R20: =+K20*1000/S33 -> 875.83149 | S20: =+O20*1000/S33 -> 1973.3925 | T20: =+O20/S33 -> 1.9733925 | U20: =+('REGISTRO 1- lote 9'!U20+'REGISTRO 2- lote 10'!U20)/2 -> 1450 | V20: =+(U20-U19)/7 -> 81.428571 | W20: =+O20/(S33*(U20/1000)) -> 1.3609603 | X20: =+U20/U19 -> 1.6477273 | Z20: 4 | AA20: =+'REGISTRO 2- lote 10'!AA20+'REGISTRO 1- lote 9'!AA20 -> 29 | AB20: =+'REGISTRO 2- lote 10'!AB20+'REGISTRO 1- lote 9'!AB20 -> 30 | AC20: =+'REGISTRO 2- lote 10'!AC20+'REGISTRO 1- lote 9'!AC20 -> 32 | AD20: =+'REGISTRO 2- lote 10'!AD20+'REGISTRO 1- lote 9'!AD20 -> 34 | AE20: =+'REGISTRO 2- lote 10'!AE20+'REGISTRO 1- lote 9'!AE20 -> 36 | AF20: =+'REGISTRO 2- lote 10'!AF20+'REGISTRO 1- lote 9'!AF20 -> 38 | AG20: =+'REGISTRO 2- lote 10'!AG20+'REGISTRO 1- lote 9'!AG20 -> 38 | AH20: =+SUM(AA20:AG20) -> 237
A21: 5 | B21: =+'REGISTRO 2- lote 10'!B21+'REGISTRO 1- lote 9'!B21 -> 1560 | C21: =+'REGISTRO 2- lote 10'!C21+'REGISTRO 1- lote 9'!C21 -> 1560 | D21: =+'REGISTRO 2- lote 10'!D21+'REGISTRO 1- lote 9'!D21 -> 1640 | E21: =+'REGISTRO 2- lote 10'!E21+'REGISTRO 1- lote 9'!E21 -> 1680 | F21: =+'REGISTRO 2- lote 10'!F21+'REGISTRO 1- lote 9'!F21 -> 1720 | G21: =+'REGISTRO 2- lote 10'!G21+'REGISTRO 1- lote 9'!G21 -> 1760 | H21: =+'REGISTRO 2- lote 10'!H21+'REGISTRO 1- lote 9'!H21 -> 1760 | I21: =+K21/40 -> 292 | K21: =SUM(B21:H21) -> 11680 | M21: =+M20+I21 -> 826 | O21: =+O20+K21 -> 33040 | Q21: =+R21/7 -> 155.51975 | R21: =+K21*1000/S34 -> 1088.6383 | S21: =+O21*1000/S34 -> 3079.5041 | T21: =+O21/S34 -> 3.0795041 | U21: =+('REGISTRO 1- lote 9'!U21+'REGISTRO 2- lote 10'!U21)/2 -> 5045 | V21: =+(U21-U20)/7 -> 513.57143 | W21: =+O21/(S34*(U21/1000)) -> 0.61040717 | X21: =+U21/U20 -> 3.4793103 | Z21: 5 | AA21: =+'REGISTRO 2- lote 10'!AA21+'REGISTRO 1- lote 9'!AA21 -> 39 | AB21: =+'REGISTRO 2- lote 10'!AB21+'REGISTRO 1- lote 9'!AB21 -> 39 | AC21: =+'REGISTRO 2- lote 10'!AC21+'REGISTRO 1- lote 9'!AC21 -> 41 | AD21: =+'REGISTRO 2- lote 10'!AD21+'REGISTRO 1- lote 9'!AD21 -> 42 | AE21: =+'REGISTRO 2- lote 10'!AE21+'REGISTRO 1- lote 9'!AE21 -> 43 | AF21: =+'REGISTRO 2- lote 10'!AF21+'REGISTRO 1- lote 9'!AF21 -> 44 | AG21: =+'REGISTRO 2- lote 10'!AG21+'REGISTRO 1- lote 9'!AG21 -> 44 | AH21: =+SUM(AA21:AG21) -> 292
A22: 6 | B22: =+'REGISTRO 2- lote 10'!B22+'REGISTRO 1- lote 9'!B22 -> 1760 | C22: =+'REGISTRO 2- lote 10'!C22+'REGISTRO 1- lote 9'!C22 -> 1760 | D22: =+'REGISTRO 2- lote 10'!D22+'REGISTRO 1- lote 9'!D22 -> 1800 | E22: =+'REGISTRO 2- lote 10'!E22+'REGISTRO 1- lote 9'!E22 -> 1800 | F22: =+'REGISTRO 2- lote 10'!F22+'REGISTRO 1- lote 9'!F22 -> 1840 | G22: =+'REGISTRO 2- lote 10'!G22+'REGISTRO 1- lote 9'!G22 -> 1840 | H22: =+'REGISTRO 2- lote 10'!H22+'REGISTRO 1- lote 9'!H22 -> 1800 | I22: =+K22/40 -> 315 | K22: =SUM(B22:H22) -> 12600 | M22: =+M21+I22 -> 1141 | O22: =+O21+K22 -> 45640 | Q22: =+R22/7 -> 169.18883 | R22: =+K22*1000/S35 -> 1184.3218 | S22: =+O22*1000/S35 -> 4289.8769 | T22: =+O22/S35 -> 4.2898769 | U22: =+('REGISTRO 1- lote 9'!U22+'REGISTRO 2- lote 10'!U22)/2 -> 2670 | V22: =+(U22-U21)/7 -> -339.28571 | W22: =+O22/(S35*(U22/1000)) -> 1.6066955 | X22: =+U22/U21 -> 0.52923687 | Z22: 6 | AA22: =+'REGISTRO 2- lote 10'!AA22+'REGISTRO 1- lote 9'!AA22 -> 44 | AB22: =+'REGISTRO 2- lote 10'!AB22+'REGISTRO 1- lote 9'!AB22 -> 44 | AC22: =+'REGISTRO 2- lote 10'!AC22+'REGISTRO 1- lote 9'!AC22 -> 45 | AD22: =+'REGISTRO 2- lote 10'!AD22+'REGISTRO 1- lote 9'!AD22 -> 45 | AE22: =+'REGISTRO 2- lote 10'!AE22+'REGISTRO 1- lote 9'!AE22 -> 46 | AF22: =+'REGISTRO 2- lote 10'!AF22+'REGISTRO 1- lote 9'!AF22 -> 46 | AG22: =+'REGISTRO 2- lote 10'!AG22+'REGISTRO 1- lote 9'!AG22 -> 45 | AH22: =+SUM(AA22:AG22) -> 315
A23: 7 | B23: =+'REGISTRO 2- lote 10'!B23+'REGISTRO 1- lote 9'!B23 -> 1760 | C23: =+'REGISTRO 2- lote 10'!C23+'REGISTRO 1- lote 9'!C23 -> 1760 | D23: =+'REGISTRO 2- lote 10'!D23+'REGISTRO 1- lote 9'!D23 -> 1720 | E23: =+'REGISTRO 2- lote 10'!E23+'REGISTRO 1- lote 9'!E23 -> 1720 | F23: =+'REGISTRO 2- lote 10'!F23+'REGISTRO 1- lote 9'!F23 -> 1400 | G23: =+'REGISTRO 2- lote 10'!G23+'REGISTRO 1- lote 9'!G23 -> 1120 | H23: =+'REGISTRO 2- lote 10'!H23+'REGISTRO 1- lote 9'!H23 -> 0 | I23: =+K23/40 -> 237 | K23: =SUM(B23:H23) -> 9480 | M23: =+M22+I23 -> 1378 | O23: =+O22+K23 -> 55120 | Q23: =+R23/7 -> 128.27105 | R23: =+K23*1000/S36 -> 897.89733 | S23: =+O23*1000/S36 -> 5220.6857 | T23: =+O23/S36 -> 5.2206857 | U23: =+('REGISTRO 1- lote 9'!U23+'REGISTRO 2- lote 10'!U23)/2 -> 0 | V23: =+(U23-U22)/7 -> -381.42857 | W23: =+O23/(S36*(U23/1000)) -> #DIV/0! | X23: =+U23/U22 -> 0 | Z23: 7 | AA23: =+'REGISTRO 2- lote 10'!AA23+'REGISTRO 1- lote 9'!AA23 -> 44 | AB23: =+'REGISTRO 2- lote 10'!AB23+'REGISTRO 1- lote 9'!AB23 -> 44 | AC23: =+'REGISTRO 2- lote 10'!AC23+'REGISTRO 1- lote 9'!AC23 -> 43 | AD23: =+'REGISTRO 2- lote 10'!AD23+'REGISTRO 1- lote 9'!AD23 -> 43 | AE23: =+'REGISTRO 2- lote 10'!AE23+'REGISTRO 1- lote 9'!AE23 -> 35 | AF23: =+'REGISTRO 2- lote 10'!AF23+'REGISTRO 1- lote 9'!AF23 -> 28 | AG23: =+'REGISTRO 2- lote 10'!AG23+'REGISTRO 1- lote 9'!AG23 -> 0 | AH23: =+SUM(AA23:AG23) -> 237
A24: 8 | B24: =+'REGISTRO 2- lote 10'!B24+'REGISTRO 1- lote 9'!B24 -> 0 | C24: =+'REGISTRO 2- lote 10'!C24+'REGISTRO 1- lote 9'!C24 -> 0 | D24: =+'REGISTRO 2- lote 10'!D24+'REGISTRO 1- lote 9'!D24 -> 0 | E24: =+'REGISTRO 2- lote 10'!E24+'REGISTRO 1- lote 9'!E24 -> 0 | F24: =+'REGISTRO 2- lote 10'!F24+'REGISTRO 1- lote 9'!F24 -> 0 | G24: =+'REGISTRO 2- lote 10'!G24+'REGISTRO 1- lote 9'!G24 -> 0 | H24: =+'REGISTRO 2- lote 10'!H24+'REGISTRO 1- lote 9'!H24 -> 0 | I24: =+K24/40 -> 0 | K24: =SUM(B24:H24) -> 0 | M24: =+M23+I24 -> 1378 | O24: =+O23+K24 -> 55120 | Q24: =+R24/7 -> 0 | R24: =+K24*1000/S37 -> 0 | S24: =+O24*1000/S37 -> 5220.6857 | T24: =+O24/S37 -> 5.2206857 | U24: =+('REGISTRO 1- lote 9'!U24+'REGISTRO 2- lote 10'!U24)/2 -> 0 | V24: =+(U24-U23)/7 -> 0 | W24: =+O24/(S37*(U24/1000)) -> #DIV/0! | X24: =+U24/U23 -> #DIV/0! | Z24: 8 | AA24: =+'REGISTRO 2- lote 10'!AA24+'REGISTRO 1- lote 9'!AA24 -> 0 | AB24: =+'REGISTRO 2- lote 10'!AB24+'REGISTRO 1- lote 9'!AB24 -> 0 | AC24: =+'REGISTRO 2- lote 10'!AC24+'REGISTRO 1- lote 9'!AC24 -> 0 | AD24: =+'REGISTRO 2- lote 10'!AD24+'REGISTRO 1- lote 9'!AD24 -> 0 | AE24: =+'REGISTRO 2- lote 10'!AE24+'REGISTRO 1- lote 9'!AE24 -> 0 | AF24: =+'REGISTRO 2- lote 10'!AF24+'REGISTRO 1- lote 9'!AF24 -> 0 | AG24: =+'REGISTRO 2- lote 10'!AG24+'REGISTRO 1- lote 9'!AG24 -> 0 | AH24: =+SUM(AA24:AG24) -> 0
A25: 9 | B25: =+'REGISTRO 2- lote 10'!B25+'REGISTRO 1- lote 9'!B25 -> 0 | C25: =+'REGISTRO 2- lote 10'!C25+'REGISTRO 1- lote 9'!C25 -> 0 | D25: =+'REGISTRO 2- lote 10'!D25+'REGISTRO 1- lote 9'!D25 -> 0 | E25: =+'REGISTRO 2- lote 10'!E25+'REGISTRO 1- lote 9'!E25 -> 0 | F25: =+'REGISTRO 2- lote 10'!F25+'REGISTRO 1- lote 9'!F25 -> 0 | G25: =+'REGISTRO 2- lote 10'!G25+'REGISTRO 1- lote 9'!G25 -> 0 | H25: =+'REGISTRO 2- lote 10'!H25+'REGISTRO 1- lote 9'!H25 -> 0 | I25: =+K25/40 -> 0 | K25: =SUM(B25:H25) -> 0 | M25: =+M24+I25 -> 1378 | O25: =+O24+K25 -> 55120 | Q25: =+R25/7 -> 0 | R25: =+K25*1000/S38 -> 0 | S25: =+O25*1000/S38 -> 5220.6857 | T25: =+O25/S38 -> 5.2206857 | V25: =+(U25-U24)/7 -> 0 | W25: =+O25/(S38*(U25/1000)) -> #DIV/0! | X25: =+U25/U24 -> #DIV/0! | Z25: 9 | AA25: =+'REGISTRO 2- lote 10'!AA25+'REGISTRO 1- lote 9'!AA25 -> 0 | AB25: =+'REGISTRO 2- lote 10'!AB25+'REGISTRO 1- lote 9'!AB25 -> 0 | AC25: =+'REGISTRO 2- lote 10'!AC25+'REGISTRO 1- lote 9'!AC25 -> 0 | AD25: =+'REGISTRO 2- lote 10'!AD25+'REGISTRO 1- lote 9'!AD25 -> 0 | AE25: =+'REGISTRO 2- lote 10'!AE25+'REGISTRO 1- lote 9'!AE25 -> 0 | AF25: =+'REGISTRO 2- lote 10'!AF25+'REGISTRO 1- lote 9'!AF25 -> 0 | AG25: =+'REGISTRO 2- lote 10'!AG25+'REGISTRO 1- lote 9'!AG25 -> 0 | AH25: =+SUM(AA25:AG25) -> 0
I27: TOTAL MORTALIDAD Y SELECCIÓN | S27: SALDO
B28: AVES MUERTAS POR DIA | I28: Mort./sem. | K28: Selec/Sem | M28: Mort.Acum. | O28: Selec.Acum. | Q28: Mort/Selec.Ac. | S28: AVES
A29: S/D | B29: =+B16 -> S | C29: =+C16 -> D | D29: =+D16 -> L | E29: =+E16 -> M | F29: =+F16 -> M | G29: =+G16 -> J | H29: =+H16 -> V | I29: No.A. | J29: % | K29: No.A. | L29: % | M29: No.A. | N29: % | O29: No.A. | P29: % | Q29: No.A. | R29: % | S29: (superv.)
A30: 1 | B30: =+'REGISTRO 2- lote 10'!B30+'REGISTRO 1- lote 9'!B30 -> 15 | C30: =+'REGISTRO 2- lote 10'!C30+'REGISTRO 1- lote 9'!C30 -> 12 | D30: =+'REGISTRO 2- lote 10'!D30+'REGISTRO 1- lote 9'!D30 -> 20 | E30: =+'REGISTRO 2- lote 10'!E30+'REGISTRO 1- lote 9'!E30 -> 42 | F30: =+'REGISTRO 2- lote 10'!F30+'REGISTRO 1- lote 9'!F30 -> 47 | G30: =+'REGISTRO 2- lote 10'!G30+'REGISTRO 1- lote 9'!G30 -> 36 | H30: =+'REGISTRO 2- lote 10'!H30+'REGISTRO 1- lote 9'!H30 -> 42 | I30: =SUM(B30:H30) -> 214 | J30: =+I30/K6 -> 0.019042534 | M30: =+I30 -> 214 | N30: =+M30/K$6 -> 0.019042534 | Q30: =+M30+O30 -> 214 | R30: =+Q30/$K$6 -> 0.019042534 | S30: =+K6-I30-K30 -> 11024
A31: 2 | B31: =+'REGISTRO 2- lote 10'!B31+'REGISTRO 1- lote 9'!B31 -> 7 | C31: =+'REGISTRO 2- lote 10'!C31+'REGISTRO 1- lote 9'!C31 -> 10 | D31: =+'REGISTRO 2- lote 10'!D31+'REGISTRO 1- lote 9'!D31 -> 13 | E31: =+'REGISTRO 2- lote 10'!E31+'REGISTRO 1- lote 9'!E31 -> 12 | F31: =+'REGISTRO 2- lote 10'!F31+'REGISTRO 1- lote 9'!F31 -> 12 | G31: =+'REGISTRO 2- lote 10'!G31+'REGISTRO 1- lote 9'!G31 -> 14 | H31: =+'REGISTRO 2- lote 10'!H31+'REGISTRO 1- lote 9'!H31 -> 21 | I31: =SUM(B31:H31) -> 89 | J31: =+I31/S30 -> 0.0080732946 | M31: =+M30+I31 -> 303 | N31: =+M31/K$6 -> 0.026962093 | Q31: =+M31+O31 -> 303 | R31: =+Q31/$K$6 -> 0.026962093 | S31: =+S30-I31-K31 -> 10935
A32: 3 | B32: =+'REGISTRO 2- lote 10'!B32+'REGISTRO 1- lote 9'!B32 -> 8 | C32: =+'REGISTRO 2- lote 10'!C32+'REGISTRO 1- lote 9'!C32 -> 9 | D32: =+'REGISTRO 2- lote 10'!D32+'REGISTRO 1- lote 9'!D32 -> 9 | E32: =+'REGISTRO 2- lote 10'!E32+'REGISTRO 1- lote 9'!E32 -> 9 | F32: =+'REGISTRO 2- lote 10'!F32+'REGISTRO 1- lote 9'!F32 -> 8 | G32: =+'REGISTRO 2- lote 10'!G32+'REGISTRO 1- lote 9'!G32 -> 9 | H32: =+'REGISTRO 2- lote 10'!H32+'REGISTRO 1- lote 9'!H32 -> 10 | I32: =SUM(B32:H32) -> 62 | J32: =+I32/S31 -> 0.0056698674 | M32: =+M31+I32 -> 365 | N32: =+M32/K$6 -> 0.032479089 | Q32: =+M32+O32 -> 365 | R32: =+Q32/$K$6 -> 0.032479089 | S32: =+S31-I32-K32 -> 10873
A33: 4 | B33: =+'REGISTRO 2- lote 10'!B33+'REGISTRO 1- lote 9'!B33 -> 5 | C33: =+'REGISTRO 2- lote 10'!C33+'REGISTRO 1- lote 9'!C33 -> 5 | D33: =+'REGISTRO 2- lote 10'!D33+'REGISTRO 1- lote 9'!D33 -> 9 | E33: =+'REGISTRO 2- lote 10'!E33+'REGISTRO 1- lote 9'!E33 -> 5 | F33: =+'REGISTRO 2- lote 10'!F33+'REGISTRO 1- lote 9'!F33 -> 9 | G33: =+'REGISTRO 2- lote 10'!G33+'REGISTRO 1- lote 9'!G33 -> 7 | H33: =+'REGISTRO 2- lote 10'!H33+'REGISTRO 1- lote 9'!H33 -> 9 | I33: =SUM(B33:H33) -> 49 | J33: =+I33/S32 -> 0.0045065759 | M33: =+M32+I33 -> 414 | N33: =+M33/K$6 -> 0.036839295 | Q33: =+M33+O33 -> 414 | R33: =+Q33/$K$6 -> 0.036839295 | S33: =+S32-I33-K33 -> 10824
A34: 5 | B34: =+'REGISTRO 2- lote 10'!B34+'REGISTRO 1- lote 9'!B34 -> 13 | C34: =+'REGISTRO 2- lote 10'!C34+'REGISTRO 1- lote 9'!C34 -> 11 | D34: =+'REGISTRO 2- lote 10'!D34+'REGISTRO 1- lote 9'!D34 -> 14 | E34: =+'REGISTRO 2- lote 10'!E34+'REGISTRO 1- lote 9'!E34 -> 13 | F34: =+'REGISTRO 2- lote 10'!F34+'REGISTRO 1- lote 9'!F34 -> 13 | G34: =+'REGISTRO 2- lote 10'!G34+'REGISTRO 1- lote 9'!G34 -> 17 | H34: =+'REGISTRO 2- lote 10'!H34+'REGISTRO 1- lote 9'!H34 -> 14 | I34: =SUM(B34:H34) -> 95 | J34: =+I34/S33 -> 0.0087767923 | M34: =+M33+I34 -> 509 | N34: =+M34/K$6 -> 0.045292757 | Q34: =+M34+O34 -> 509 | R34: =+Q34/$K$6 -> 0.045292757 | S34: =+S33-I34-K34 -> 10729
A35: 6 | B35: =+'REGISTRO 2- lote 10'!B35+'REGISTRO 1- lote 9'!B35 -> 12 | C35: =+'REGISTRO 2- lote 10'!C35+'REGISTRO 1- lote 9'!C35 -> 10 | D35: =+'REGISTRO 2- lote 10'!D35+'REGISTRO 1- lote 9'!D35 -> 15 | E35: =+'REGISTRO 2- lote 10'!E35+'REGISTRO 1- lote 9'!E35 -> 14 | F35: =+'REGISTRO 2- lote 10'!F35+'REGISTRO 1- lote 9'!F35 -> 12 | G35: =+'REGISTRO 2- lote 10'!G35+'REGISTRO 1- lote 9'!G35 -> 12 | H35: =+'REGISTRO 2- lote 10'!H35+'REGISTRO 1- lote 9'!H35 -> 15 | I35: =SUM(B35:H35) -> 90 | J35: =+I35/S34 -> 0.0083884798 | M35: =+M34+I35 -> 599 | N35: =+M35/K$6 -> 0.053301299 | Q35: =+M35+O35 -> 599 | R35: =+Q35/$K$6 -> 0.053301299 | S35: =+S34-I35-K35 -> 10639
A36: 7 | B36: =+'REGISTRO 2- lote 10'!B36+'REGISTRO 1- lote 9'!B36 -> 11 | C36: =+'REGISTRO 2- lote 10'!C36+'REGISTRO 1- lote 9'!C36 -> 13 | D36: =+'REGISTRO 2- lote 10'!D36+'REGISTRO 1- lote 9'!D36 -> 13 | E36: =+'REGISTRO 2- lote 10'!E36+'REGISTRO 1- lote 9'!E36 -> 14 | F36: =+'REGISTRO 2- lote 10'!F36+'REGISTRO 1- lote 9'!F36 -> 10 | G36: =+'REGISTRO 2- lote 10'!G36+'REGISTRO 1- lote 9'!G36 -> 8 | H36: =+'REGISTRO 2- lote 10'!H36+'REGISTRO 1- lote 9'!H36 -> 12 | I36: =SUM(B36:H36) -> 81 | J36: =+I36/S35 -> 0.0076134975 | M36: =+M35+I36 -> 680 | N36: =+M36/K$6 -> 0.060508987 | Q36: =+M36+O36 -> 680 | R36: =+Q36/$K$6 -> 0.060508987 | S36: =+S35-I36-K36 -> 10558
A37: 8 | B37: =+'REGISTRO 2- lote 10'!B37+'REGISTRO 1- lote 9'!B37 -> 0 | C37: =+'REGISTRO 2- lote 10'!C37+'REGISTRO 1- lote 9'!C37 -> 0 | D37: =+'REGISTRO 2- lote 10'!D37+'REGISTRO 1- lote 9'!D37 -> 0 | E37: =+'REGISTRO 2- lote 10'!E37+'REGISTRO 1- lote 9'!E37 -> 0 | F37: =+'REGISTRO 2- lote 10'!F37+'REGISTRO 1- lote 9'!F37 -> 0 | G37: =+'REGISTRO 2- lote 10'!G37+'REGISTRO 1- lote 9'!G37 -> 0 | H37: =+'REGISTRO 2- lote 10'!H37+'REGISTRO 1- lote 9'!H37 -> 0 | I37: =SUM(B37:H37) -> 0 | J37: =+I37/S36 -> 0 | M37: =+M36+I37 -> 680 | N37: =+M37/K$6 -> 0.060508987 | Q37: =+M37+O37 -> 680 | R37: =+Q37/$K$6 -> 0.060508987 | S37: =+S36-I37-K37 -> 10558
A38: 9 | B38: =+'REGISTRO 2- lote 10'!B38+'REGISTRO 1- lote 9'!B38 -> 0 | C38: =+'REGISTRO 2- lote 10'!C38+'REGISTRO 1- lote 9'!C38 -> 0 | D38: =+'REGISTRO 2- lote 10'!D38+'REGISTRO 1- lote 9'!D38 -> 0 | E38: =+'REGISTRO 2- lote 10'!E38+'REGISTRO 1- lote 9'!E38 -> 0 | F38: =+'REGISTRO 2- lote 10'!F38+'REGISTRO 1- lote 9'!F38 -> 0 | G38: =+'REGISTRO 2- lote 10'!G38+'REGISTRO 1- lote 9'!G38 -> 0 | H38: =+'REGISTRO 2- lote 10'!H38+'REGISTRO 1- lote 9'!H38 -> 0 | I38: =SUM(B38:H38) -> 0 | J38: =+I38/S37 -> 0 | M38: =+M37+I38 -> 680 | N38: =+M38/K$6 -> 0.060508987 | Q38: =+M38+O38 -> 680 | R38: =+Q38/$K$6 -> 0.060508987 | S38: =+S37-I38-K38 -> 10558
B40: PESO POR AVE | E40: Aumento | G40: Conversion | I40: PROGRAMA DE VACUNACION | O40: TRATAMIENTO
A41: S/D | B41: Mach | C41: Hemb. | D41: Prom. | E41: por ave/dia | G41: alimento | I41: DIA | J41: MES | K41: VACUNA | O41: DIA | P41: MES | Q41: DROGA / DOSIS
A42: 1 | D42: =+(B42+C42)/2 -> 0 | E42: =+D42/7 -> 0 | G42: =+S17/D42 -> #DIV/0!
A43: 2 | D43: =+(B43+C43)/2 -> 0 | E43: =(D43-D42)/7 -> 0 | G43: =+S18/D43 -> #DIV/0!
A44: 3 | D44: =+(B44+C44)/2 -> 0 | E44: =(D44-D43)/7 -> 0 | G44: =+S19/D44 -> #DIV/0!
A45: 4 | D45: =+(B45+C45)/2 -> 0 | E45: =(D45-D44)/7 -> 0 | G45: =+S20/D45 -> #DIV/0!
A46: 5 | D46: =+(B46+C46)/2 -> 0 | E46: =(D46-D45)/7 -> 0 | G46: =+S21/D46 -> #DIV/0!
A47: 6 | D47: =+(B47+C47)/2 -> 0 | E47: =(D47-D46)/7 -> 0 | G47: =+S22/D47 -> #DIV/0!
A48: 7 | D48: =+(B48+C48)/2 -> 0 | E48: =(D48-D47)/7 -> 0 | G48: =+S23/D48 -> #DIV/0!
A49: 8 | D49: =+(B49+C49)/2 -> 0 | E49: =(D49-D48)/7 -> 0 | G49: =+S24/D49 -> #DIV/0!
A50: 9 | D50: =+(B50+C50)/2 -> 0 | E50: =(D50-D49)/7 -> 0 | G50: =+S25/D50 -> #DIV/0!
B53: GRANJA AVICOLA SAN LORENZO
B54: RESPONSABLE : | E54: =+E3 -> 0 | O54: HEMBRA
B56: GALPON | D56: LOTE | G56: INCUBADORA | K56: CANTIDAD INICIAL | O56: PESO PROMEDIO INIC.
B57: =+B6 -> T1 | D57: =+D6 -> 49 | G57: =+G6 -> FINAVES | K57: =+'REGISTRO 2- lote 10'!K57:N57+'REGISTRO 1- lote 9'!K57:N57 -> 11118 | O57: =+('REGISTRO 1- lote 9'!O57:R57+'REGISTRO 2- lote 10'!O57:R57)/2 -> 44
B59: FECHA INICIO | G59: =+'REGISTRO 2- lote 10'!G59:J59 -> 45780 | L59: DIAS DE ENGORDE: | P59: =+P8 -> 52
B60: FECHA TERMINACION | G60: =+G9 -> 45831 | L60: DIAS PROMEDIO | P60: =+P9 -> 0
B62: POLLOS VENDIDOS | G62: =+PESAS!N39 -> 10643 | Z62: conversion: kilos concentrado/ kilos en pie
B63: PESO TOTAL FINAL | G63: =+PESAS!N40 -> 30904.89 | L63: CONSUMO TOTAL DEL LOTE | R63: =+T76 -> 5.1248234 | Z63: se necesita xxx kilos concentrado para producir 1 kilo de pollo en pie
Z64: Entre mas bajo mejor
I65: TOTAL CONSUMO | Q65: CONSUMO POR AVE | U65: PESO
A66: KILOS CONSUMIDOS | I66: SEMANAL | M66: ACUMULADO | Q66: (Gramos) | T66: CONSUMO | U66: GRAMOS | V66: gramos | Z66: BULTOS CONSUMIDOS
A67: S/D | B67: =+B16 -> S | C67: =+C16 -> D | D67: =+D16 -> L | E67: =+E16 -> M | F67: =+F16 -> M | G67: =+G16 -> J | H67: =+H16 -> V | I67: Bultos | K67: Kilos | M67: Bultos | O67: Kilos | Q67: Diario | R67: Sem. | S67: Acumul. | T67: KL. | U67: PROMEDIO | V67: Ganancia dia | W67: Conversion | X67: VPI | Z67: S/D | AA67: =+B67 -> S | AB67: =+C67 -> D | AC67: =+D67 -> L | AD67: =+E67 -> M | AE67: =+F67 -> M | AF67: =+G67 -> J | AG67: =+H67 -> V | AH67: TOTAL
A68: 1 | B68: =+'REGISTRO 2- lote 10'!B68+'REGISTRO 1- lote 9'!B68 -> 180 | C68: =+'REGISTRO 2- lote 10'!C68+'REGISTRO 1- lote 9'!C68 -> 200 | D68: =+'REGISTRO 2- lote 10'!D68+'REGISTRO 1- lote 9'!D68 -> 220 | E68: =+'REGISTRO 2- lote 10'!E68+'REGISTRO 1- lote 9'!E68 -> 260 | F68: =+'REGISTRO 2- lote 10'!F68+'REGISTRO 1- lote 9'!F68 -> 280 | G68: =+'REGISTRO 2- lote 10'!G68+'REGISTRO 1- lote 9'!G68 -> 280 | H68: =+'REGISTRO 2- lote 10'!H68+'REGISTRO 1- lote 9'!H68 -> 320 | I68: =+K68/40 -> 43.5 | K68: =SUM(B68:H68) -> 1740 | M68: =+I68 -> 43.5 | O68: =+K68 -> 1740 | Q68: =+R68/7 -> 22.667466 | R68: =+K68*1000/S81 -> 158.67226 | S68: =+R68 -> 158.67226 | T68: =+O68/S81 -> 0.15867226 | U68: =+('REGISTRO 1- lote 9'!U68+'REGISTRO 2- lote 10'!U68)/2 -> 95 | V68: =(U68-O57)/7 -> 7.2857143 | W68: =+O68/(S81*(U68/1000)) -> 1.6702343 | X68: =+U68/O57 -> 2.1590909 | Z68: 1 | AA68: =+'REGISTRO 2- lote 10'!AA68+'REGISTRO 1- lote 9'!AA68 -> 4.5 | AB68: =+'REGISTRO 2- lote 10'!AB68+'REGISTRO 1- lote 9'!AB68 -> 5 | AC68: =+'REGISTRO 2- lote 10'!AC68+'REGISTRO 1- lote 9'!AC68 -> 5.5 | AD68: =+'REGISTRO 2- lote 10'!AD68+'REGISTRO 1- lote 9'!AD68 -> 6.5 | AE68: =+'REGISTRO 2- lote 10'!AE68+'REGISTRO 1- lote 9'!AE68 -> 7 | AF68: =+'REGISTRO 2- lote 10'!AF68+'REGISTRO 1- lote 9'!AF68 -> 7 | AG68: =+'REGISTRO 2- lote 10'!AG68+'REGISTRO 1- lote 9'!AG68 -> 8 | AH68: =+SUM(AA68:AG68) -> 43.5
A69: 2 | B69: =+'REGISTRO 2- lote 10'!B69+'REGISTRO 1- lote 9'!B69 -> 360 | C69: =+'REGISTRO 2- lote 10'!C69+'REGISTRO 1- lote 9'!C69 -> 420 | D69: =+'REGISTRO 2- lote 10'!D69+'REGISTRO 1- lote 9'!D69 -> 440 | E69: =+'REGISTRO 2- lote 10'!E69+'REGISTRO 1- lote 9'!E69 -> 520 | F69: =+'REGISTRO 2- lote 10'!F69+'REGISTRO 1- lote 9'!F69 -> 640 | G69: =+'REGISTRO 2- lote 10'!G69+'REGISTRO 1- lote 9'!G69 -> 640 | H69: =+'REGISTRO 2- lote 10'!H69+'REGISTRO 1- lote 9'!H69 -> 720 | I69: =+K69/40 -> 93.5 | K69: =SUM(B69:H69) -> 3740 | M69: =+M68+I69 -> 137 | O69: =+O68+K69 -> 5480 | Q69: =+R69/7 -> 49.116172 | R69: =+K69*1000/S82 -> 343.8132 | S69: =+O69*1000/S82 -> 503.76908 | T69: =+O69/S82 -> 0.50376908 | U69: =+('REGISTRO 1- lote 9'!U69+'REGISTRO 2- lote 10'!U69)/2 -> 320 | V69: =+(U69-U68)/7 -> 32.142857 | W69: =+O69/(S82*(U69/1000)) -> 1.5742784 | X69: =+U69/U68 -> 3.3684211 | Z69: 2 | AA69: =+'REGISTRO 2- lote 10'!AA69+'REGISTRO 1- lote 9'!AA69 -> 9 | AB69: =+'REGISTRO 2- lote 10'!AB69+'REGISTRO 1- lote 9'!AB69 -> 10.5 | AC69: =+'REGISTRO 2- lote 10'!AC69+'REGISTRO 1- lote 9'!AC69 -> 11 | AD69: =+'REGISTRO 2- lote 10'!AD69+'REGISTRO 1- lote 9'!AD69 -> 13 | AE69: =+'REGISTRO 2- lote 10'!AE69+'REGISTRO 1- lote 9'!AE69 -> 16 | AF69: =+'REGISTRO 2- lote 10'!AF69+'REGISTRO 1- lote 9'!AF69 -> 16 | AG69: =+'REGISTRO 2- lote 10'!AG69+'REGISTRO 1- lote 9'!AG69 -> 18 | AH69: =+SUM(AA69:AG69) -> 93.5
A70: 3 | B70: =+'REGISTRO 2- lote 10'!B70+'REGISTRO 1- lote 9'!B70 -> 760 | C70: =+'REGISTRO 2- lote 10'!C70+'REGISTRO 1- lote 9'!C70 -> 800 | D70: =+'REGISTRO 2- lote 10'!D70+'REGISTRO 1- lote 9'!D70 -> 880 | E70: =+'REGISTRO 2- lote 10'!E70+'REGISTRO 1- lote 9'!E70 -> 880 | F70: =+'REGISTRO 2- lote 10'!F70+'REGISTRO 1- lote 9'!F70 -> 920 | G70: =+'REGISTRO 2- lote 10'!G70+'REGISTRO 1- lote 9'!G70 -> 1000 | H70: =+'REGISTRO 2- lote 10'!H70+'REGISTRO 1- lote 9'!H70 -> 1000 | I70: =+K70/40 -> 156 | K70: =SUM(B70:H70) -> 6240 | M70: =+M69+I70 -> 293 | O70: =+O69+K70 -> 11720 | Q70: =+R70/7 -> 82.280651 | R70: =+K70*1000/S83 -> 575.96456 | S70: =+O70*1000/S83 -> 1081.7796 | T70: =+O70/S83 -> 1.0817796 | U70: =+('REGISTRO 1- lote 9'!U70+'REGISTRO 2- lote 10'!U70)/2 -> 652.5 | V70: =+(U70-U69)/7 -> 47.5 | W70: =+O70/(S83*(U70/1000)) -> 1.6578997 | X70: =+U70/U69 -> 2.0390625 | Z70: 3 | AA70: =+'REGISTRO 2- lote 10'!AA70+'REGISTRO 1- lote 9'!AA70 -> 19 | AB70: =+'REGISTRO 2- lote 10'!AB70+'REGISTRO 1- lote 9'!AB70 -> 20 | AC70: =+'REGISTRO 2- lote 10'!AC70+'REGISTRO 1- lote 9'!AC70 -> 22 | AD70: =+'REGISTRO 2- lote 10'!AD70+'REGISTRO 1- lote 9'!AD70 -> 22 | AE70: =+'REGISTRO 2- lote 10'!AE70+'REGISTRO 1- lote 9'!AE70 -> 23 | AF70: =+'REGISTRO 2- lote 10'!AF70+'REGISTRO 1- lote 9'!AF70 -> 25 | AG70: =+'REGISTRO 2- lote 10'!AG70+'REGISTRO 1- lote 9'!AG70 -> 25 | AH70: =+SUM(AA70:AG70) -> 156
A71: 4 | B71: =+'REGISTRO 2- lote 10'!B71+'REGISTRO 1- lote 9'!B71 -> 1000 | C71: =+'REGISTRO 2- lote 10'!C71+'REGISTRO 1- lote 9'!C71 -> 1080 | D71: =+'REGISTRO 2- lote 10'!D71+'REGISTRO 1- lote 9'!D71 -> 1160 | E71: =+'REGISTRO 2- lote 10'!E71+'REGISTRO 1- lote 9'!E71 -> 1320 | F71: =+'REGISTRO 2- lote 10'!F71+'REGISTRO 1- lote 9'!F71 -> 1400 | G71: =+'REGISTRO 2- lote 10'!G71+'REGISTRO 1- lote 9'!G71 -> 1440 | H71: =+'REGISTRO 2- lote 10'!H71+'REGISTRO 1- lote 9'!H71 -> 1520 | I71: =+K71/40 -> 223 | K71: =SUM(B71:H71) -> 8920 | M71: =+M70+I71 -> 516 | O71: =+O70+K71 -> 20640 | Q71: =+R71/7 -> 118.29611 | R71: =+K71*1000/S84 -> 828.07278 | S71: =+O71*1000/S84 -> 1916.0787 | T71: =+O71/S84 -> 1.9160787 | U71: =+('REGISTRO 1- lote 9'!U71+'REGISTRO 2- lote 10'!U71)/2 -> 1132.5 | V71: =+(U71-U70)/7 -> 68.571429 | W71: =+O71/(S84*(U71/1000)) -> 1.6919017 | X71: =+U71/U70 -> 1.7356322 | Z71: 4 | AA71: =+'REGISTRO 2- lote 10'!AA71+'REGISTRO 1- lote 9'!AA71 -> 25 | AB71: =+'REGISTRO 2- lote 10'!AB71+'REGISTRO 1- lote 9'!AB71 -> 27 | AC71: =+'REGISTRO 2- lote 10'!AC71+'REGISTRO 1- lote 9'!AC71 -> 29 | AD71: =+'REGISTRO 2- lote 10'!AD71+'REGISTRO 1- lote 9'!AD71 -> 33 | AE71: =+'REGISTRO 2- lote 10'!AE71+'REGISTRO 1- lote 9'!AE71 -> 35 | AF71: =+'REGISTRO 2- lote 10'!AF71+'REGISTRO 1- lote 9'!AF71 -> 36 | AG71: =+'REGISTRO 2- lote 10'!AG71+'REGISTRO 1- lote 9'!AG71 -> 38 | AH71: =+SUM(AA71:AG71) -> 223
A72: 5 | B72: =+'REGISTRO 2- lote 10'!B72+'REGISTRO 1- lote 9'!B72 -> 1480 | C72: =+'REGISTRO 2- lote 10'!C72+'REGISTRO 1- lote 9'!C72 -> 1480 | D72: =+'REGISTRO 2- lote 10'!D72+'REGISTRO 1- lote 9'!D72 -> 1520 | E72: =+'REGISTRO 2- lote 10'!E72+'REGISTRO 1- lote 9'!E72 -> 1560 | F72: =+'REGISTRO 2- lote 10'!F72+'REGISTRO 1- lote 9'!F72 -> 1600 | G72: =+'REGISTRO 2- lote 10'!G72+'REGISTRO 1- lote 9'!G72 -> 1600 | H72: =+'REGISTRO 2- lote 10'!H72+'REGISTRO 1- lote 9'!H72 -> 1600 | I72: =+K72/40 -> 271 | K72: =SUM(B72:H72) -> 10840 | M72: =+M71+I72 -> 787 | O72: =+O71+K72 -> 31480 | Q72: =+R72/7 -> 144.36202 | R72: =+K72*1000/S85 -> 1010.5342 | S72: =+O72*1000/S85 -> 2934.6509 | T72: =+O72/S85 -> 2.9346509 | U72: =+('REGISTRO 1- lote 9'!U72+'REGISTRO 2- lote 10'!U72)/2 -> 1650 | V72: =+(U72-U71)/7 -> 73.928571 | W72: =+O72/(S85*(U72/1000)) -> 1.7785763 | X72: =+U72/U71 -> 1.4569536 | Z72: 5 | AA72: =+'REGISTRO 2- lote 10'!AA72+'REGISTRO 1- lote 9'!AA72 -> 37 | AB72: =+'REGISTRO 2- lote 10'!AB72+'REGISTRO 1- lote 9'!AB72 -> 37 | AC72: =+'REGISTRO 2- lote 10'!AC72+'REGISTRO 1- lote 9'!AC72 -> 38 | AD72: =+'REGISTRO 2- lote 10'!AD72+'REGISTRO 1- lote 9'!AD72 -> 39 | AE72: =+'REGISTRO 2- lote 10'!AE72+'REGISTRO 1- lote 9'!AE72 -> 40 | AF72: =+'REGISTRO 2- lote 10'!AF72+'REGISTRO 1- lote 9'!AF72 -> 40 | AG72: =+'REGISTRO 2- lote 10'!AG72+'REGISTRO 1- lote 9'!AG72 -> 40 | AH72: =+SUM(AA72:AG72) -> 271
A73: 6 | B73: =+'REGISTRO 2- lote 10'!B73+'REGISTRO 1- lote 9'!B73 -> 1600 | C73: =+'REGISTRO 2- lote 10'!C73+'REGISTRO 1- lote 9'!C73 -> 1640 | D73: =+'REGISTRO 2- lote 10'!D73+'REGISTRO 1- lote 9'!D73 -> 1640 | E73: =+'REGISTRO 2- lote 10'!E73+'REGISTRO 1- lote 9'!E73 -> 1680 | F73: =+'REGISTRO 2- lote 10'!F73+'REGISTRO 1- lote 9'!F73 -> 1680 | G73: =+'REGISTRO 2- lote 10'!G73+'REGISTRO 1- lote 9'!G73 -> 1680 | H73: =+'REGISTRO 2- lote 10'!H73+'REGISTRO 1- lote 9'!H73 -> 1680 | I73: =+K73/40 -> 290 | K73: =SUM(B73:H73) -> 11600 | M73: =+M72+I73 -> 1077 | O73: =+O72+K73 -> 43080 | Q73: =+R73/7 -> 155.16319 | R73: =+K73*1000/S86 -> 1086.1423 | S73: =+O73*1000/S86 -> 4033.7079 | T73: =+O73/S86 -> 4.0337079 | U73: =+('REGISTRO 1- lote 9'!U73+'REGISTRO 2- lote 10'!U73)/2 -> 2115 | V73: =+(U73-U72)/7 -> 66.428571 | W73: =+O73/(S86*(U73/1000)) -> 1.9071905 | X73: =+U73/U72 -> 1.2818182 | Z73: 6 | AA73: =+'REGISTRO 2- lote 10'!AA73+'REGISTRO 1- lote 9'!AA73 -> 40 | AB73: =+'REGISTRO 2- lote 10'!AB73+'REGISTRO 1- lote 9'!AB73 -> 41 | AC73: =+'REGISTRO 2- lote 10'!AC73+'REGISTRO 1- lote 9'!AC73 -> 41 | AD73: =+'REGISTRO 2- lote 10'!AD73+'REGISTRO 1- lote 9'!AD73 -> 42 | AE73: =+'REGISTRO 2- lote 10'!AE73+'REGISTRO 1- lote 9'!AE73 -> 42 | AF73: =+'REGISTRO 2- lote 10'!AF73+'REGISTRO 1- lote 9'!AF73 -> 42 | AG73: =+'REGISTRO 2- lote 10'!AG73+'REGISTRO 1- lote 9'!AG73 -> 42 | AH73: =+SUM(AA73:AG73) -> 290
A74: 7 | B74: =+'REGISTRO 2- lote 10'!B74+'REGISTRO 1- lote 9'!B74 -> 1680 | C74: =+'REGISTRO 2- lote 10'!C74+'REGISTRO 1- lote 9'!C74 -> 1680 | D74: =+'REGISTRO 2- lote 10'!D74+'REGISTRO 1- lote 9'!D74 -> 1680 | E74: =+'REGISTRO 2- lote 10'!E74+'REGISTRO 1- lote 9'!E74 -> 1680 | F74: =+'REGISTRO 2- lote 10'!F74+'REGISTRO 1- lote 9'!F74 -> 1680 | G74: =+'REGISTRO 2- lote 10'!G74+'REGISTRO 1- lote 9'!G74 -> 1560 | H74: =+'REGISTRO 2- lote 10'!H74+'REGISTRO 1- lote 9'!H74 -> 1360 | I74: =+K74/40 -> 283 | K74: =SUM(B74:H74) -> 11320 | M74: =+M73+I74 -> 1360 | O74: =+O73+K74 -> 54400 | Q74: =+R74/7 -> 152.34506 | R74: =+K74*1000/S87 -> 1066.4154 | S74: =+O74*1000/S87 -> 5124.8234 | T74: =+O74/S87 -> 5.1248234 | U74: =+('REGISTRO 1- lote 9'!U74+'REGISTRO 2- lote 10'!U74)/2 -> 1180 | V74: =+(U74-U73)/7 -> -133.57143 | W74: =+O74/(S87*(U74/1000)) -> 4.3430706 | X74: =+U74/U73 -> 0.55791962 | Z74: 7 | AA74: =+'REGISTRO 2- lote 10'!AA74+'REGISTRO 1- lote 9'!AA74 -> 42 | AB74: =+'REGISTRO 2- lote 10'!AB74+'REGISTRO 1- lote 9'!AB74 -> 42 | AC74: =+'REGISTRO 2- lote 10'!AC74+'REGISTRO 1- lote 9'!AC74 -> 42 | AD74: =+'REGISTRO 2- lote 10'!AD74+'REGISTRO 1- lote 9'!AD74 -> 42 | AE74: =+'REGISTRO 2- lote 10'!AE74+'REGISTRO 1- lote 9'!AE74 -> 42 | AF74: =+'REGISTRO 2- lote 10'!AF74+'REGISTRO 1- lote 9'!AF74 -> 39 | AG74: =+'REGISTRO 2- lote 10'!AG74+'REGISTRO 1- lote 9'!AG74 -> 34 | AH74: =+SUM(AA74:AG74) -> 283
A75: 8 | B75: =+'REGISTRO 2- lote 10'!B75+'REGISTRO 1- lote 9'!B75 -> 0 | C75: =+'REGISTRO 2- lote 10'!C75+'REGISTRO 1- lote 9'!C75 -> 0 | D75: =+'REGISTRO 2- lote 10'!D75+'REGISTRO 1- lote 9'!D75 -> 0 | E75: =+'REGISTRO 2- lote 10'!E75+'REGISTRO 1- lote 9'!E75 -> 0 | F75: =+'REGISTRO 2- lote 10'!F75+'REGISTRO 1- lote 9'!F75 -> 0 | G75: =+'REGISTRO 2- lote 10'!G75+'REGISTRO 1- lote 9'!G75 -> 0 | H75: =+'REGISTRO 2- lote 10'!H75+'REGISTRO 1- lote 9'!H75 -> 0 | I75: =+K75/40 -> 0 | K75: =SUM(B75:H75) -> 0 | M75: =+M74+I75 -> 1360 | O75: =+O74+K75 -> 54400 | Q75: =+R75/7 -> 0 | R75: =+K75*1000/S88 -> 0 | S75: =+O75*1000/S88 -> 5124.8234 | T75: =+O75/S88 -> 5.1248234 | U75: =+('REGISTRO 1- lote 9'!U75+'REGISTRO 2- lote 10'!U75)/2 -> 0 | V75: =+(U75-U74)/7 -> -168.57143 | W75: =+O75/(S88*(U75/1000)) -> #DIV/0! | X75: =+U75/U74 -> 0 | Z75: 8 | AA75: =+'REGISTRO 2- lote 10'!AA75+'REGISTRO 1- lote 9'!AA75 -> 0 | AB75: =+'REGISTRO 2- lote 10'!AB75+'REGISTRO 1- lote 9'!AB75 -> 0 | AC75: =+'REGISTRO 2- lote 10'!AC75+'REGISTRO 1- lote 9'!AC75 -> 0 | AD75: =+'REGISTRO 2- lote 10'!AD75+'REGISTRO 1- lote 9'!AD75 -> 0 | AE75: =+'REGISTRO 2- lote 10'!AE75+'REGISTRO 1- lote 9'!AE75 -> 0 | AF75: =+'REGISTRO 2- lote 10'!AF75+'REGISTRO 1- lote 9'!AF75 -> 0 | AG75: =+'REGISTRO 2- lote 10'!AG75+'REGISTRO 1- lote 9'!AG75 -> 0 | AH75: =+SUM(AA75:AG75) -> 0
A76: 9 | B76: =+'REGISTRO 2- lote 10'!B76+'REGISTRO 1- lote 9'!B76 -> 0 | C76: =+'REGISTRO 2- lote 10'!C76+'REGISTRO 1- lote 9'!C76 -> 0 | D76: =+'REGISTRO 2- lote 10'!D76+'REGISTRO 1- lote 9'!D76 -> 0 | E76: =+'REGISTRO 2- lote 10'!E76+'REGISTRO 1- lote 9'!E76 -> 0 | F76: =+'REGISTRO 2- lote 10'!F76+'REGISTRO 1- lote 9'!F76 -> 0 | G76: =+'REGISTRO 2- lote 10'!G76+'REGISTRO 1- lote 9'!G76 -> 0 | H76: =+'REGISTRO 2- lote 10'!H76+'REGISTRO 1- lote 9'!H76 -> 0 | I76: =+K76/40 -> 0 | K76: =SUM(B76:H76) -> 0 | M76: =+M75+I76 -> 1360 | O76: =+O75+K76 -> 54400 | Q76: =+R76/7 -> 0 | R76: =+K76*1000/S89 -> 0 | S76: =+O76*1000/S89 -> 5124.8234 | T76: =+O76/S89 -> 5.1248234 | V76: =+(U76-U75)/7 -> 0 | W76: =+O76/(S89*(U76/1000)) -> #DIV/0! | X76: =+U76/U75 -> #DIV/0! | Z76: 9 | AA76: =+'REGISTRO 2- lote 10'!AA76+'REGISTRO 1- lote 9'!AA76 -> 0 | AB76: =+'REGISTRO 2- lote 10'!AB76+'REGISTRO 1- lote 9'!AB76 -> 0 | AC76: =+'REGISTRO 2- lote 10'!AC76+'REGISTRO 1- lote 9'!AC76 -> 0 | AD76: =+'REGISTRO 2- lote 10'!AD76+'REGISTRO 1- lote 9'!AD76 -> 0 | AE76: =+'REGISTRO 2- lote 10'!AE76+'REGISTRO 1- lote 9'!AE76 -> 0 | AF76: =+'REGISTRO 2- lote 10'!AF76+'REGISTRO 1- lote 9'!AF76 -> 0 | AG76: =+'REGISTRO 2- lote 10'!AG76+'REGISTRO 1- lote 9'!AG76 -> 0 | AH76: =+SUM(AA76:AG76) -> 0
I78: TOTAL MORTALIDAD Y SELECCIÓN | S78: SALDO
B79: AVES MUERTAS POR DIA | I79: Mort./sem. | K79: Selec/Sem | M79: Mort.Acum. | O79: Selec.Acum. | Q79: Mort/Selec.Ac. | S79: AVES
A80: S/D | B80: =+B67 -> S | C80: =+C67 -> D | D80: =+D67 -> L | E80: =+E67 -> M | F80: =+F67 -> M | G80: =+G67 -> J | H80: =+H67 -> V | I80: No.A. | J80: % | K80: No.A. | L80: % | M80: No.A. | N80: % | O80: No.A. | P80: % | Q80: No.A. | R80: % | S80: (superv.)
A81: 1 | B81: =+'REGISTRO 2- lote 10'!B81+'REGISTRO 1- lote 9'!B81 -> 17 | C81: =+'REGISTRO 2- lote 10'!C81+'REGISTRO 1- lote 9'!C81 -> 15 | D81: =+'REGISTRO 2- lote 10'!D81+'REGISTRO 1- lote 9'!D81 -> 14 | E81: =+'REGISTRO 2- lote 10'!E81+'REGISTRO 1- lote 9'!E81 -> 37 | F81: =+'REGISTRO 2- lote 10'!F81+'REGISTRO 1- lote 9'!F81 -> 27 | G81: =+'REGISTRO 2- lote 10'!G81+'REGISTRO 1- lote 9'!G81 -> 17 | H81: =+'REGISTRO 2- lote 10'!H81+'REGISTRO 1- lote 9'!H81 -> 25 | I81: =SUM(B81:H81) -> 152 | J81: =+I81/K57 -> 0.013671524 | M81: =+I81 -> 152 | N81: =+M81/K$57 -> 0.013671524 | Q81: =+M81+O81 -> 152 | R81: =+Q81/$K$57 -> 0.013671524 | S81: =+K57-I81-K81 -> 10966
A82: 2 | B82: =+'REGISTRO 2- lote 10'!B82+'REGISTRO 1- lote 9'!B82 -> 9 | C82: =+'REGISTRO 2- lote 10'!C82+'REGISTRO 1- lote 9'!C82 -> 13 | D82: =+'REGISTRO 2- lote 10'!D82+'REGISTRO 1- lote 9'!D82 -> 11 | E82: =+'REGISTRO 2- lote 10'!E82+'REGISTRO 1- lote 9'!E82 -> 13 | F82: =+'REGISTRO 2- lote 10'!F82+'REGISTRO 1- lote 9'!F82 -> 12 | G82: =+'REGISTRO 2- lote 10'!G82+'REGISTRO 1- lote 9'!G82 -> 12 | H82: =+'REGISTRO 2- lote 10'!H82+'REGISTRO 1- lote 9'!H82 -> 18 | I82: =SUM(B82:H82) -> 88 | J82: =+I82/S81 -> 0.0080248039 | M82: =+M81+I82 -> 240 | N82: =+M82/K$57 -> 0.021586616 | Q82: =+M82+O82 -> 240 | R82: =+Q82/$K$57 -> 0.021586616 | S82: =+S81-I82-K82 -> 10878
A83: 3 | B83: =+'REGISTRO 2- lote 10'!B83+'REGISTRO 1- lote 9'!B83 -> 5 | C83: =+'REGISTRO 2- lote 10'!C83+'REGISTRO 1- lote 9'!C83 -> 5 | D83: =+'REGISTRO 2- lote 10'!D83+'REGISTRO 1- lote 9'!D83 -> 9 | E83: =+'REGISTRO 2- lote 10'!E83+'REGISTRO 1- lote 9'!E83 -> 7 | F83: =+'REGISTRO 2- lote 10'!F83+'REGISTRO 1- lote 9'!F83 -> 5 | G83: =+'REGISTRO 2- lote 10'!G83+'REGISTRO 1- lote 9'!G83 -> 6 | H83: =+'REGISTRO 2- lote 10'!H83+'REGISTRO 1- lote 9'!H83 -> 7 | I83: =SUM(B83:H83) -> 44 | J83: =+I83/S82 -> 0.0040448612 | M83: =+M82+I83 -> 284 | N83: =+M83/K$57 -> 0.025544163 | Q83: =+M83+O83 -> 284 | R83: =+Q83/$K$57 -> 0.025544163 | S83: =+S82-I83-K83 -> 10834
A84: 4 | B84: =+'REGISTRO 2- lote 10'!B84+'REGISTRO 1- lote 9'!B84 -> 6 | C84: =+'REGISTRO 2- lote 10'!C84+'REGISTRO 1- lote 9'!C84 -> 8 | D84: =+'REGISTRO 2- lote 10'!D84+'REGISTRO 1- lote 9'!D84 -> 8 | E84: =+'REGISTRO 2- lote 10'!E84+'REGISTRO 1- lote 9'!E84 -> 10 | F84: =+'REGISTRO 2- lote 10'!F84+'REGISTRO 1- lote 9'!F84 -> 10 | G84: =+'REGISTRO 2- lote 10'!G84+'REGISTRO 1- lote 9'!G84 -> 10 | H84: =+'REGISTRO 2- lote 10'!H84+'REGISTRO 1- lote 9'!H84 -> 10 | I84: =SUM(B84:H84) -> 62 | J84: =+I84/S83 -> 0.0057227248 | M84: =+M83+I84 -> 346 | N84: =+M84/K$57 -> 0.031120705 | Q84: =+M84+O84 -> 346 | R84: =+Q84/$K$57 -> 0.031120705 | S84: =+S83-I84-K84 -> 10772
A85: 5 | B85: =+'REGISTRO 2- lote 10'!B85+'REGISTRO 1- lote 9'!B85 -> 5 | C85: =+'REGISTRO 2- lote 10'!C85+'REGISTRO 1- lote 9'!C85 -> 7 | D85: =+'REGISTRO 2- lote 10'!D85+'REGISTRO 1- lote 9'!D85 -> 3 | E85: =+'REGISTRO 2- lote 10'!E85+'REGISTRO 1- lote 9'!E85 -> 7 | F85: =+'REGISTRO 2- lote 10'!F85+'REGISTRO 1- lote 9'!F85 -> 6 | G85: =+'REGISTRO 2- lote 10'!G85+'REGISTRO 1- lote 9'!G85 -> 11 | H85: =+'REGISTRO 2- lote 10'!H85+'REGISTRO 1- lote 9'!H85 -> 6 | I85: =SUM(B85:H85) -> 45 | J85: =+I85/S84 -> 0.0041774972 | M85: =+M84+I85 -> 391 | N85: =+M85/K$57 -> 0.035168196 | Q85: =+M85+O85 -> 391 | R85: =+Q85/$K$57 -> 0.035168196 | S85: =+S84-I85-K85 -> 10727
A86: 6 | B86: =+'REGISTRO 2- lote 10'!B86+'REGISTRO 1- lote 9'!B86 -> 7 | C86: =+'REGISTRO 2- lote 10'!C86+'REGISTRO 1- lote 9'!C86 -> 7 | D86: =+'REGISTRO 2- lote 10'!D86+'REGISTRO 1- lote 9'!D86 -> 7 | E86: =+'REGISTRO 2- lote 10'!E86+'REGISTRO 1- lote 9'!E86 -> 6 | F86: =+'REGISTRO 2- lote 10'!F86+'REGISTRO 1- lote 9'!F86 -> 6 | G86: =+'REGISTRO 2- lote 10'!G86+'REGISTRO 1- lote 9'!G86 -> 7 | H86: =+'REGISTRO 2- lote 10'!H86+'REGISTRO 1- lote 9'!H86 -> 7 | I86: =SUM(B86:H86) -> 47 | J86: =+I86/S85 -> 0.0043814673 | M86: =+M85+I86 -> 438 | N86: =+M86/K$57 -> 0.039395575 | Q86: =+M86+O86 -> 438 | R86: =+Q86/$K$57 -> 0.039395575 | S86: =+S85-I86-K86 -> 10680
A87: 7 | B87: =+'REGISTRO 2- lote 10'!B87+'REGISTRO 1- lote 9'!B87 -> 6 | C87: =+'REGISTRO 2- lote 10'!C87+'REGISTRO 1- lote 9'!C87 -> 7 | D87: =+'REGISTRO 2- lote 10'!D87+'REGISTRO 1- lote 9'!D87 -> 7 | E87: =+'REGISTRO 2- lote 10'!E87+'REGISTRO 1- lote 9'!E87 -> 11 | F87: =+'REGISTRO 2- lote 10'!F87+'REGISTRO 1- lote 9'!F87 -> 10 | G87: =+'REGISTRO 2- lote 10'!G87+'REGISTRO 1- lote 9'!G87 -> 10 | H87: =+'REGISTRO 2- lote 10'!H87+'REGISTRO 1- lote 9'!H87 -> 14 | I87: =SUM(B87:H87) -> 65 | J87: =+I87/S86 -> 0.0060861423 | M87: =+M86+I87 -> 503 | N87: =+M87/K$57 -> 0.04524195 | Q87: =+M87+O87 -> 503 | R87: =+Q87/$K$57 -> 0.04524195 | S87: =+S86-I87-K87 -> 10615
A88: 8 | B88: =+'REGISTRO 2- lote 10'!B88+'REGISTRO 1- lote 9'!B88 -> 0 | C88: =+'REGISTRO 2- lote 10'!C88+'REGISTRO 1- lote 9'!C88 -> 0 | D88: =+'REGISTRO 2- lote 10'!D88+'REGISTRO 1- lote 9'!D88 -> 0 | E88: =+'REGISTRO 2- lote 10'!E88+'REGISTRO 1- lote 9'!E88 -> 0 | F88: =+'REGISTRO 2- lote 10'!F88+'REGISTRO 1- lote 9'!F88 -> 0 | G88: =+'REGISTRO 2- lote 10'!G88+'REGISTRO 1- lote 9'!G88 -> 0 | H88: =+'REGISTRO 2- lote 10'!H88+'REGISTRO 1- lote 9'!H88 -> 0 | I88: =SUM(B88:H88) -> 0 | J88: =+I88/S87 -> 0 | M88: =+M87+I88 -> 503 | N88: =+M88/K$57 -> 0.04524195 | Q88: =+M88+O88 -> 503 | R88: =+Q88/$K$57 -> 0.04524195 | S88: =+S87-I88-K88 -> 10615
A89: 9 | B89: =+'REGISTRO 2- lote 10'!B89+'REGISTRO 1- lote 9'!B89 -> 0 | C89: =+'REGISTRO 2- lote 10'!C89+'REGISTRO 1- lote 9'!C89 -> 0 | D89: =+'REGISTRO 2- lote 10'!D89+'REGISTRO 1- lote 9'!D89 -> 0 | E89: =+'REGISTRO 2- lote 10'!E89+'REGISTRO 1- lote 9'!E89 -> 0 | F89: =+'REGISTRO 2- lote 10'!F89+'REGISTRO 1- lote 9'!F89 -> 0 | G89: =+'REGISTRO 2- lote 10'!G89+'REGISTRO 1- lote 9'!G89 -> 0 | H89: =+'REGISTRO 2- lote 10'!H89+'REGISTRO 1- lote 9'!H89 -> 0 | I89: =SUM(B89:H89) -> 0 | J89: =+I89/S88 -> 0 | M89: =+M88+I89 -> 503 | N89: =+M89/K$57 -> 0.04524195 | Q89: =+M89+O89 -> 503 | R89: =+Q89/$K$57 -> 0.04524195 | S89: =+S88-I89-K89 -> 10615
B91: PESO POR AVE | E91: Aumento | G91: Conversion | I91: PROGRAMA DE VACUNACION | O91: TRATAMIENTO
A92: S/D | B92: Mach | C92: Hemb. | D92: Prom. | E92: por ave/dia | G92: alimento | I92: DIA | J92: MES | K92: VACUNA | O92: DIA | P92: MES | Q92: DROGA / DOSIS
A93: 1 | D93: =+(B93+C93)/2 -> 0 | E93: =+D93/7 -> 0 | G93: =+S68/D93 -> #DIV/0!
A94: 2 | D94: =+(B94+C94)/2 -> 0 | E94: =(D94-D93)/7 -> 0 | G94: =+S69/D94 -> #DIV/0!
A95: 3 | D95: =+(B95+C95)/2 -> 0 | E95: =(D95-D94)/7 -> 0 | G95: =+S70/D95 -> #DIV/0!
A96: 4 | D96: =+(B96+C96)/2 -> 0 | E96: =(D96-D95)/7 -> 0 | G96: =+S71/D96 -> #DIV/0!
A97: 5 | D97: =+(B97+C97)/2 -> 0 | E97: =(D97-D96)/7 -> 0 | G97: =+S72/D97 -> #DIV/0!
A98: 6 | D98: =+(B98+C98)/2 -> 0 | E98: =(D98-D97)/7 -> 0 | G98: =+S73/D98 -> #DIV/0!
A99: 7 | D99: =+(B99+C99)/2 -> 0 | E99: =(D99-D98)/7 -> 0 | G99: =+S74/D99 -> #DIV/0!
A100: 8 | D100: =+(B100+C100)/2 -> 0 | E100: =(D100-D99)/7 -> 0 | G100: =+S75/D100 -> #DIV/0!
A101: 9 | D101: =+(B101+C101)/2 -> 0 | E101: =(D101-D100)/7 -> 0 | G101: =+S76/D101 -> #DIV/0!
B104: GRANJA AVICOLA SAN LORENZO
B105: RESPONSABLE : | E105: =+E54 -> 0 | O105: TOTAL
B107: GALPON | D107: LOTE | G107: INCUBADORA | K107: CANTIDAD INICIAL | O107: PESO PROMEDIO INIC.
B108: =+B57 -> T1 | D108: =+D57 -> 49 | G108: =+G57 -> FINAVES | K108: =+K6+K57 -> 22356 | O108: =+(O6+O57)/2 -> 44
B110: FECHA INICIO | G110: =+G59 -> 45780 | L110: DIAS DE ENGORDE: | P110: =+P59 -> 52
B111: FECHA TERMINACION | G111: =+G60 -> 45831 | L111: DIAS PROMEDIO | P111: =+P60 -> 0
B113: POLLOS VENDIDOS | G113: =+G11+G62 -> 21196 | Z113: conversion: kilos concentrado/ kilos en pie
B114: PESO TOTAL FINAL | G114: =+G12+G63 -> 63309.13 | L114: CONSUMO TOTAL DEL LOTE | R114: =+T127 -> 5.1726255 | Z114: se necesita xxx kilos concentrado para producir 1 kilo de pollo en pie
Z115: Entre mas bajo mejor
I116: TOTAL CONSUMO | Q116: CONSUMO POR AVE | U116: PESO
A117: BULTOS CONSUMIDOS | I117: SEMANAL | M117: ACUMULADO | Q117: (Gramos) | T117: CONSUMO | U117: GRAMOS | V117: gramos
...

Sheet CONSUMO DIARIO TOTAL
A1: GRANJA | B1: =+'REGISTRO TOTAL'!E2 -> SAN LORENZO
A2: GALPON: | B2: =+'REGISTRO TOTAL'!B6 -> T1 | C2: MACHOS | O2: HEMBRAS
A3: LOTE | B3: =+'REGISTRO TOTAL'!D6 -> 49
G4: CONSUMO DIARIO | S4: CONSUMO DIARIO
A5: FECHA | B5: SEMANA | C5: DIA | D5: MORTALIDAD | E5: SALIDA A PROCESO | F5: SALDO POLLITOS | G5: TOTAL KL | H5: X POLLO GR | I5: Acumul X P (gr) | J5: Peso pollito gr | K5: ganancia peso gr semanal | L5: Promedio ganancia peso gr dia | M5: CONVERSION | O5: DIA | P5: MORTALIDAD | Q5: SALIDA A PROCESO | R5: SALDO POLLITOS | S5: TOTAL KL | T5: X POLLO GR | U5: Acumul X P (gr) | V5: Peso pollito gr | W5: ganancia peso gr semanal | X5: Promedio ganancia peso gr dia | Y5: CONVERSION
A6: =+'REGISTRO TOTAL'!G8 -> 45780 | B6: Semana 1 | C6: 0 | F6: =+'REGISTRO TOTAL'!K6 -> 11238 | J6: =+'REGISTRO TOTAL'!O6 -> 44 | O6: 0 | R6: =+'REGISTRO TOTAL'!K57 -> 11118 | V6: =+'REGISTRO TOTAL'!O57 -> 44
A7: =+A6+1 -> 45781 | C7: 1 | D7: =+'REGISTRO TOTAL'!$B$30 -> 15 | F7: =+F6-D7-E7 -> 11223 | G7: =+'REGISTRO TOTAL'!$B$17 -> 160 | H7: =+G7*1000/F7 -> 14.256438 | I7: =+H7 -> 14.256438 | O7: 1 | P7: =+'REGISTRO TOTAL'!$B$81 -> 17 | R7: =+R6-P7-Q7 -> 11101 | S7: =+'REGISTRO TOTAL'!$B$68 -> 180 | T7: =+S7*1000/R7 -> 16.214755 | U7: =+T7 -> 16.214755
A8: =+A7+1 -> 45782 | C8: =+C7+1 -> 2 | D8: =+'REGISTRO TOTAL'!$C$30 -> 12 | F8: =+F7-D8-E8 -> 11211 | G8: =+'REGISTRO TOTAL'!$C$17 -> 160 | H8: =+G8*1000/F8 -> 14.271697 | I8: =+I7+H8 -> 28.528135 | O8: =+O7+1 -> 2 | P8: =+'REGISTRO TOTAL'!$C$81 -> 15 | R8: =+R7-P8-Q8 -> 11086 | S8: =+'REGISTRO TOTAL'!$C$68 -> 200 | T8: =+S8*1000/R8 -> 18.040772 | U8: =+U7+T8 -> 34.255528
A9: =+A8+1 -> 45783 | C9: =+C8+1 -> 3 | D9: =+'REGISTRO TOTAL'!$D$30 -> 20 | F9: =+F8-D9-E9 -> 11191 | G9: =+'REGISTRO TOTAL'!$D$17 -> 200 | H9: =+G9*1000/F9 -> 17.871504 | I9: =+I8+H9 -> 46.399639 | O9: =+O8+1 -> 3 | P9: =+'REGISTRO TOTAL'!$D$81 -> 14 | R9: =+R8-P9-Q9 -> 11072 | S9: =+'REGISTRO TOTAL'!$D$68 -> 220 | T9: =+S9*1000/R9 -> 19.869942 | U9: =+U8+T9 -> 54.12547
A10: =+A9+1 -> 45784 | C10: =+C9+1 -> 4 | D10: =+'REGISTRO TOTAL'!$E$30 -> 42 | F10: =+F9-D10-E10 -> 11149 | G10: =+'REGISTRO TOTAL'!$E$17 -> 260 | H10: =+G10*1000/F10 -> 23.320477 | I10: =+I9+H10 -> 69.720116 | O10: =+O9+1 -> 4 | P10: =+'REGISTRO TOTAL'!$E$81 -> 37 | R10: =+R9-P10-Q10 -> 11035 | S10: =+'REGISTRO TOTAL'!$E$68 -> 260 | T10: =+S10*1000/R10 -> 23.561396 | U10: =+U9+T10 -> 77.686865
A11: =+A10+1 -> 45785 | C11: =+C10+1 -> 5 | D11: =+'REGISTRO TOTAL'!$F$30 -> 47 | F11: =+F10-D11-E11 -> 11102 | G11: =+'REGISTRO TOTAL'!$F$17 -> 280 | H11: =+G11*1000/F11 -> 25.220681 | I11: =+I10+H11 -> 94.940797 | O11: =+O10+1 -> 5 | P11: =+'REGISTRO TOTAL'!$F$81 -> 27 | R11: =+R10-P11-Q11 -> 11008 | S11: =+'REGISTRO TOTAL'!$F$68 -> 280 | T11: =+S11*1000/R11 -> 25.436047 | U11: =+U10+T11 -> 103.12291
A12: =+A11+1 -> 45786 | C12: =+C11+1 -> 6 | D12: =+'REGISTRO TOTAL'!$G$30 -> 36 | F12: =+F11-D12-E12 -> 11066 | G12: =+'REGISTRO TOTAL'!$G$17 -> 320 | H12: =+G12*1000/F12 -> 28.917405 | I12: =+I11+H12 -> 123.8582 | O12: =+O11+1 -> 6 | P12: =+'REGISTRO TOTAL'!$G$81 -> 17 | R12: =+R11-P12-Q12 -> 10991 | S12: =+'REGISTRO TOTAL'!$G$68 -> 280 | T12: =+S12*1000/R12 -> 25.475389 | U12: =+U11+T12 -> 128.5983
A13: =+A12+1 -> 45787 | C13: =+C12+1 -> 7 | D13: =+'REGISTRO TOTAL'!$H$30 -> 42 | F13: =+F12-D13-E13 -> 11024 | G13: =+'REGISTRO TOTAL'!$H$17 -> 400 | H13: =+G13*1000/F13 -> 36.28447 | I13: =+I12+H13 -> 160.14267 | J13: =+'REGISTRO TOTAL'!U17 -> 194 | K13: =+J13-J6 -> 150 | L13: =+(J13-$J$6)/C13 -> 21.428571 | M13: =+I13/J13 -> 0.82547769 | N13: 160-190 | O13: =+O12+1 -> 7 | P13: =+'REGISTRO TOTAL'!$H$81 -> 25 | R13: =+R12-P13-Q13 -> 10966 | S13: =+'REGISTRO TOTAL'!$H$68 -> 320 | T13: =+S13*1000/R13 -> 29.181105 | U13: =+U12+T13 -> 157.77941 | V13: =+'REGISTRO TOTAL'!U68 -> 95 | W13: =+V13-V6 -> 51 | X13: =+(V13-$J$6)/O13 -> 7.2857143 | Y13: =+U13/V13 -> 1.6608359 | Z13: 160-185
A14: =+A13+1 -> 45788 | B14: Semana 2 | C14: =+C13+1 -> 8 | D14: =+'REGISTRO TOTAL'!$B$31 -> 7 | F14: =+F13-D14-E14 -> 11017 | G14: =+'REGISTRO TOTAL'!$B$18 -> 400 | H14: =+G14*1000/F14 -> 36.307525 | I14: =+I13+H14 -> 196.4502 | O14: =+O13+1 -> 8 | P14: =+'REGISTRO TOTAL'!$B$82 -> 9 | R14: =+R13-P14-Q14 -> 10957 | S14: =+'REGISTRO TOTAL'!$B$69 -> 360 | T14: =+S14*1000/R14 -> 32.855709 | U14: =+U13+T14 -> 190.63511
A15: =+A14+1 -> 45789 | C15: =+C14+1 -> 9 | D15: =+'REGISTRO TOTAL'!$C$31 -> 10 | F15: =+F14-D15-E15 -> 11007 | G15: =+'REGISTRO TOTAL'!$C$18 -> 400 | H15: =+G15*1000/F15 -> 36.340511 | I15: =+I14+H15 -> 232.79071 | O15: =+O14+1 -> 9 | P15: =+'REGISTRO TOTAL'!$C$82 -> 13 | R15: =+R14-P15-Q15 -> 10944 | S15: =+'REGISTRO TOTAL'!$C$69 -> 420 | T15: =+S15*1000/R15 -> 38.377193 | U15: =+U14+T15 -> 229.01231
A16: =+A15+1 -> 45790 | C16: =+C15+1 -> 10 | D16: =+'REGISTRO TOTAL'!$D$31 -> 13 | F16: =+F15-D16-E16 -> 10994 | G16: =+'REGISTRO TOTAL'!$D$18 -> 480 | H16: =+G16*1000/F16 -> 43.660178 | I16: =+I15+H16 -> 276.45089 | O16: =+O15+1 -> 10 | P16: =+'REGISTRO TOTAL'!$D$82 -> 11 | R16: =+R15-P16-Q16 -> 10933 | S16: =+'REGISTRO TOTAL'!$D$69 -> 440 | T16: =+S16*1000/R16 -> 40.245129 | U16: =+U15+T16 -> 269.25744
A17: =+A16+1 -> 45791 | C17: =+C16+1 -> 11 | D17: =+'REGISTRO TOTAL'!$E$31 -> 12 | F17: =+F16-D17-E17 -> 10982 | G17: =+'REGISTRO TOTAL'!$E$18 -> 560 | H17: =+G17*1000/F17 -> 50.992533 | I17: =+I16+H17 -> 327.44342 | O17: =+O16+1 -> 11 | P17: =+'REGISTRO TOTAL'!$E$82 -> 13 | R17: =+R16-P17-Q17 -> 10920 | S17: =+'REGISTRO TOTAL'!$E$69 -> 520 | T17: =+S17*1000/R17 -> 47.619048 | U17: =+U16+T17 -> 316.87648
A18: =+A17+1 -> 45792 | C18: =+C17+1 -> 12 | D18: =+'REGISTRO TOTAL'!$F$31 -> 12 | F18: =+F17-D18-E18 -> 10970 | G18: =+'REGISTRO TOTAL'!$F$18 -> 600 | H18: =+G18*1000/F18 -> 54.694622 | I18: =+I17+H18 -> 382.13804 | O18: =+O17+1 -> 12 | P18: =+'REGISTRO TOTAL'!$F$82 -> 12 | R18: =+R17-P18-Q18 -> 10908 | S18: =+'REGISTRO TOTAL'!$F$69 -> 640 | T18: =+S18*1000/R18 -> 58.672534 | U18: =+U17+T18 -> 375.54902
A19: =+A18+1 -> 45793 | C19: =+C18+1 -> 13 | D19: =+'REGISTRO TOTAL'!$G$31 -> 14 | F19: =+F18-D19-E19 -> 10956 | G19: =+'REGISTRO TOTAL'!$G$18 -> 660 | H19: =+G19*1000/F19 -> 60.240964 | I19: =+I18+H19 -> 442.379 | O19: =+O18+1 -> 13 | P19: =+'REGISTRO TOTAL'!$G$82 -> 12 | R19: =+R18-P19-Q19 -> 10896 | S19: =+'REGISTRO TOTAL'!$G$69 -> 640 | T19: =+S19*1000/R19 -> 58.737151 | U19: =+U18+T19 -> 434.28617
A20: =+A19+1 -> 45794 | C20: =+C19+1 -> 14 | D20: =+'REGISTRO TOTAL'!$H$31 -> 21 | F20: =+F19-D20-E20 -> 10935 | G20: =+'REGISTRO TOTAL'!$H$18 -> 720 | H20: =+G20*1000/F20 -> 65.843621 | I20: =+I19+H20 -> 508.22263 | J20: =+'REGISTRO TOTAL'!U18 -> 455 | K20: =+J20-J13 -> 261 | L20: =+(J20-$J$6)/C20 -> 29.357143 | M20: =+I20/J20 -> 1.1169728 | N20: 380-390 | O20: =+O19+1 -> 14 | P20: =+'REGISTRO TOTAL'!$H$82 -> 18 | R20: =+R19-P20-Q20 -> 10878 | S20: =+'REGISTRO TOTAL'!$H$69 -> 720 | T20: =+S20*1000/R20 -> 66.188638 | U20: =+U19+T20 -> 500.47481 | V20: =+'REGISTRO TOTAL'!U69 -> 320 | W20: =+V20-V13 -> 225 | X20: =+(V20-$J$6)/O20 -> 19.714286 | Y20: =+U20/V20 -> 1.5639838 | Z20: 375-380
A21: =+A20+1 -> 45795 | B21: Semana 3 | C21: =+C20+1 -> 15 | D21: =+'REGISTRO TOTAL'!$B$32 -> 8 | F21: =+F20-D21-E21 -> 10927 | G21: =+'REGISTRO TOTAL'!$B$19 -> 720 | H21: =+G21*1000/F21 -> 65.891828 | I21: =+I20+H21 -> 574.11445 | O21: =+O20+1 -> 15 | P21: =+'REGISTRO TOTAL'!$B$83 -> 5 | R21: =+R20-P21-Q21 -> 10873 | S21: =+'REGISTRO TOTAL'!$B$70 -> 760 | T21: =+S21*1000/R21 -> 69.897912 | U21: =+U20+T21 -> 570.37272
A22: =+A21+1 -> 45796 | C22: =+C21+1 -> 16 | D22: =+'REGISTRO TOTAL'!$C$32 -> 9 | F22: =+F21-D22-E22 -> 10918 | G22: =+'REGISTRO TOTAL'!$C$19 -> 760 | H22: =+G22*1000/F22 -> 69.609819 | I22: =+I21+H22 -> 643.72427 | O22: =+O21+1 -> 16 | P22: =+'REGISTRO TOTAL'!$C$83 -> 5 | R22: =+R21-P22-Q22 -> 10868 | S22: =+'REGISTRO TOTAL'!$C$70 -> 800 | T22: =+S22*1000/R22 -> 73.6106 | U22: =+U21+T22 -> 643.98332
A23: =+A22+1 -> 45797 | C23: =+C22+1 -> 17 | D23: =+'REGISTRO TOTAL'!$D$32 -> 9 | F23: =+F22-D23-E23 -> 10909 | G23: =+'REGISTRO TOTAL'!$D$19 -> 840 | H23: =+G23*1000/F23 -> 77.000642 | I23: =+I22+H23 -> 720.72491 | O23: =+O22+1 -> 17 | P23: =+'REGISTRO TOTAL'!$D$83 -> 9 | R23: =+R22-P23-Q23 -> 10859 | S23: =+'REGISTRO TOTAL'!$D$70 -> 880 | T23: =+S23*1000/R23 -> 81.03877 | U23: =+U22+T23 -> 725.02209
A24: =+A23+1 -> 45798 | C24: =+C23+1 -> 18 | D24: =+'REGISTRO TOTAL'!$E$32 -> 9 | F24: =+F23-D24-E24 -> 10900 | G24: =+'REGISTRO TOTAL'!$E$19 -> 880 | H24: =+G24*1000/F24 -> 80.733945 | I24: =+I23+H24 -> 801.45886 | O24: =+O23+1 -> 18 | P24: =+'REGISTRO TOTAL'!$E$83 -> 7 | R24: =+R23-P24-Q24 -> 10852 | S24: =+'REGISTRO TOTAL'!$E$70 -> 880 | T24: =+S24*1000/R24 -> 81.091043 | U24: =+U23+T24 -> 806.11313
A25: =+A24+1 -> 45799 | C25: =+C24+1 -> 19 | D25: =+'REGISTRO TOTAL'!$F$32 -> 8 | F25: =+F24-D25-E25 -> 10892 | G25: =+'REGISTRO TOTAL'!$F$19 -> 960 | H25: =+G25*1000/F25 -> 88.138083 | I25: =+I24+H25 -> 889.59694 | O25: =+O24+1 -> 19 | P25: =+'REGISTRO TOTAL'!$F$83 -> 5 | R25: =+R24-P25-Q25 -> 10847 | S25: =+'REGISTRO TOTAL'!$F$70 -> 920 | T25: =+S25*1000/R25 -> 84.816078 | U25: =+U24+T25 -> 890.92921
A26: =+A25+1 -> 45800 | C26: =+C25+1 -> 20 | D26: =+'REGISTRO TOTAL'!$G$32 -> 9 | F26: =+F25-D26-E26 -> 10883 | G26: =+'REGISTRO TOTAL'!$G$19 -> 1040 | H26: =+G26*1000/F26 -> 95.561886 | I26: =+I25+H26 -> 985.15883 | O26: =+O25+1 -> 20 | P26: =+'REGISTRO TOTAL'!$G$83 -> 6 | R26: =+R25-P26-Q26 -> 10841 | S26: =+'REGISTRO TOTAL'!$G$70 -> 1000 | T26: =+S26*1000/R26 -> 92.242413 | U26: =+U25+T26 -> 983.17162
A27: =+A26+1 -> 45801 | C27: =+C26+1 -> 21 | D27: =+'REGISTRO TOTAL'!$H$32 -> 10 | F27: =+F26-D27-E27 -> 10873 | G27: =+'REGISTRO TOTAL'!$H$19 -> 1080 | H27: =+G27*1000/F27 -> 99.328612 | I27: =+I26+H27 -> 1084.4874 | J27: =+'REGISTRO TOTAL'!U19 -> 880 | K27: =+J27-J20 -> 425 | L27: =+(J27-$J$6)/C27 -> 39.809524 | M27: =+I27/J27 -> 1.2323721 | N27: 730-780 | O27: =+O26+1 -> 21 | P27: =+'REGISTRO TOTAL'!$H$83 -> 7 | R27: =+R26-P27-Q27 -> 10834 | S27: =+'REGISTRO TOTAL'!$H$70 -> 1000 | T27: =+S27*1000/R27 -> 92.302012 | U27: =+U26+T27 -> 1075.4736 | V27: =+'REGISTRO TOTAL'!U70 -> 652.5 | W27: =+V27-V20 -> 332.5 | X27: =+(V27-$J$6)/O27 -> 28.97619 | Y27: =+U27/V27 -> 1.6482355 | Z27: 680-760
A28: =+A27+1 -> 45802 | B28: Semana 4 | C28: =+C27+1 -> 22 | D28: =+'REGISTRO TOTAL'!$B$33 -> 5 | F28: =+F27-D28-E28 -> 10868 | G28: =+'REGISTRO TOTAL'!$B$20 -> 1160 | H28: =+G28*1000/F28 -> 106.73537 | I28: =+I27+H28 -> 1191.2228 | O28: =+O27+1 -> 22 | P28: =+'REGISTRO TOTAL'!$B$84 -> 6 | R28: =+R27-P28-Q28 -> 10828 | S28: =+'REGISTRO TOTAL'!$B$71 -> 1000 | T28: =+S28*1000/R28 -> 92.353158 | U28: =+U27+T28 -> 1167.8268
A29: =+A28+1 -> 45803 | C29: =+C28+1 -> 23 | D29: =+'REGISTRO TOTAL'!$C$33 -> 5 | F29: =+F28-D29-E29 -> 10863 | G29: =+'REGISTRO TOTAL'!$C$20 -> 1200 | H29: =+G29*1000/F29 -> 110.46672 | I29: =+I28+H29 -> 1301.6895 | O29: =+O28+1 -> 23 | P29: =+'REGISTRO TOTAL'!$C$84 -> 8 | R29: =+R28-P29-Q29 -> 10820 | S29: =+'REGISTRO TOTAL'!$C$71 -> 1080 | T29: =+S29*1000/R29 -> 99.815157 | U29: =+U28+T29 -> 1267.642
A30: =+A29+1 -> 45804 | C30: =+C29+1 -> 24 | D30: =+'REGISTRO TOTAL'!$D$33 -> 9 | F30: =+F29-D30-E30 -> 10854 | G30: =+'REGISTRO TOTAL'!$D$20 -> 1280 | H30: =+G30*1000/F30 -> 117.92887 | I30: =+I29+H30 -> 1419.6184 | O30: =+O29+1 -> 24 | P30: =+'REGISTRO TOTAL'!$D$84 -> 8 | R30: =+R29-P30-Q30 -> 10812 | S30: =+'REGISTRO TOTAL'!$D$71 -> 1160 | T30: =+S30*1000/R30 -> 107.2882 | U30: =+U29+T30 -> 1374.9301
A31: =+A30+1 -> 45805 | C31: =+C30+1 -> 25 | D31: =+'REGISTRO TOTAL'!$E$33 -> 5 | F31: =+F30-D31-E31 -> 10849 | G31: =+'REGISTRO TOTAL'!$E$20 -> 1360 | H31: =+G31*1000/F31 -> 125.35718 | I31: =+I30+H31 -> 1544.9756 | O31: =+O30+1 -> 25 | P31: =+'REGISTRO TOTAL'!$E$84 -> 10 | R31: =+R30-P31-Q31 -> 10802 | S31: =+'REGISTRO TOTAL'!$E$71 -> 1320 | T31: =+S31*1000/R31 -> 122.19959 | U31: =+U30+T31 -> 1497.1297
A32: =+A31+1 -> 45806 | C32: =+C31+1 -> 26 | D32: =+'REGISTRO TOTAL'!$F$33 -> 9 | F32: =+F31-D32-E32 -> 10840 | G32: =+'REGISTRO TOTAL'!$F$20 -> 1440 | H32: =+G32*1000/F32 -> 132.84133 | I32: =+I31+H32 -> 1677.8169 | O32: =+O31+1 -> 26 | P32: =+'REGISTRO TOTAL'!$F$84 -> 10 | R32: =+R31-P32-Q32 -> 10792 | S32: =+'REGISTRO TOTAL'!$F$71 -> 1400 | T32: =+S32*1000/R32 -> 129.72572 | U32: =+U31+T32 -> 1626.8555
A33: =+A32+1 -> 45807 | C33: =+C32+1 -> 27 | D33: =+'REGISTRO TOTAL'!$G$33 -> 7 | F33: =+F32-D33-E33 -> 10833 | G33: =+'REGISTRO TOTAL'!$G$20 -> 1520 | H33: =+G33*1000/F33 -> 140.31201 | I33: =+I32+H33 -> 1818.1289 | O33: =+O32+1 -> 27 | P33: =+'REGISTRO TOTAL'!$G$84 -> 10 | R33: =+R32-P33-Q33 -> 10782 | S33: =+'REGISTRO TOTAL'!$G$71 -> 1440 | T33: =+S33*1000/R33 -> 133.55593 | U33: =+U32+T33 -> 1760.4114
A34: =+A33+1 -> 45808 | C34: =+C33+1 -> 28 | D34: =+'REGISTRO TOTAL'!$H$33 -> 9 | F34: =+F33-D34-E34 -> 10824 | G34: =+'REGISTRO TOTAL'!$H$20 -> 1520 | H34: =+G34*1000/F34 -> 140.42868 | I34: =+I33+H34 -> 1958.5576 | J34: =+'REGISTRO TOTAL'!U20 -> 1450 | K34: =+J34-J27 -> 570 | L34: =+(J34-$J$6)/C34 -> 50.214286 | M34: =+I34/J34 -> 1.3507294 | N34: 1210-1350 | O34: =+O33+1 -> 28 | P34: =+'REGISTRO TOTAL'!$H$84 -> 10 | R34: =+R33-P34-Q34 -> 10772 | S34: =+'REGISTRO TOTAL'!$H$71 -> 1520 | T34: =+S34*1000/R34 -> 141.10657 | U34: =+U33+T34 -> 1901.518 | V34: =+'REGISTRO TOTAL'!U71 -> 1132.5 | W34: =+V34-V27 -> 480 | X34: =+(V34-$J$6)/O34 -> 38.875 | Y34: =+U34/V34 -> 1.6790446 | Z34: 1150-1320
A35: =+A34+1 -> 45809 | B35: Semana 5 | C35: =+C34+1 -> 29 | D35: =+'REGISTRO TOTAL'!$B$34 -> 13 | F35: =+F34-D35-E35 -> 10811 | G35: =+'REGISTRO TOTAL'!$B$21 -> 1560 | H35: =+G35*1000/F35 -> 144.29747 | I35: =+I34+H35 -> 2102.8551 | O35: =+O34+1 -> 29 | P35: =+'REGISTRO TOTAL'!$B$85 -> 5 | R35: =+R34-P35-Q35 -> 10767 | S35: =+'REGISTRO TOTAL'!$B$72 -> 1480 | T35: =+S35*1000/R35 -> 137.45704 | U35: =+U34+T35 -> 2038.975
A36: =+A35+1 -> 45810 | C36: =+C35+1 -> 30 | D36: =+'REGISTRO TOTAL'!$C$34 -> 11 | F36: =+F35-D36-E36 -> 10800 | G36: =+'REGISTRO TOTAL'!$C$21 -> 1560 | H36: =+G36*1000/F36 -> 144.44444 | I36: =+I35+H36 -> 2247.2995 | O36: =+O35+1 -> 30 | P36: =+'REGISTRO TOTAL'!$C$85 -> 7 | R36: =+R35-P36-Q36 -> 10760 | S36: =+'REGISTRO TOTAL'!$C$72 -> 1480 | T36: =+S36*1000/R36 -> 137.54647 | U36: =+U35+T36 -> 2176.5215
A37: =+A36+1 -> 45811 | C37: =+C36+1 -> 31 | D37: =+'REGISTRO TOTAL'!$D$34 -> 14 | F37: =+F36-D37-E37 -> 10786 | G37: =+'REGISTRO TOTAL'!$D$21 -> 1640 | H37: =+G37*1000/F37 -> 152.04895 | I37: =+I36+H37 -> 2399.3485 | O37: =+O36+1 -> 31 | P37: =+'REGISTRO TOTAL'!$D$85 -> 3 | R37: =+R36-P37-Q37 -> 10757 | S37: =+'REGISTRO TOTAL'!$D$72 -> 1520 | T37: =+S37*1000/R37 -> 141.30334 | U37: =+U36+T37 -> 2317.8248
A38: =+A37+1 -> 45812 | C38: =+C37+1 -> 32 | D38: =+'REGISTRO TOTAL'!$E$34 -> 13 | F38: =+F37-D38-E38 -> 10773 | G38: =+'REGISTRO TOTAL'!$E$21 -> 1680 | H38: =+G38*1000/F38 -> 155.94542 | I38: =+I37+H38 -> 2555.2939 | O38: =+O37+1 -> 32 | P38: =+'REGISTRO TOTAL'!$E$85 -> 7 | R38: =+R37-P38-Q38 -> 10750 | S38: =+'REGISTRO TOTAL'!$E$72 -> 1560 | T38: =+S38*1000/R38 -> 145.11628 | U38: =+U37+T38 -> 2462.9411
A39: =+A38+1 -> 45813 | C39: =+C38+1 -> 33 | D39: =+'REGISTRO TOTAL'!$F$34 -> 13 | F39: =+F38-D39-E39 -> 10760 | G39: =+'REGISTRO TOTAL'!$F$21 -> 1720 | H39: =+G39*1000/F39 -> 159.8513 | I39: =+I38+H39 -> 2715.1452 | O39: =+O38+1 -> 33 | P39: =+'REGISTRO TOTAL'!$F$85 -> 6 | R39: =+R38-P39-Q39 -> 10744 | S39: =+'REGISTRO TOTAL'!$F$72 -> 1600 | T39: =+S39*1000/R39 -> 148.92033 | U39: =+U38+T39 -> 2611.8614
A40: =+A39+1 -> 45814 | C40: =+C39+1 -> 34 | D40: =+'REGISTRO TOTAL'!$G$34 -> 17 | F40: =+F39-D40-E40 -> 10743 | G40: =+'REGISTRO TOTAL'!$G$21 -> 1760 | H40: =+G40*1000/F40 -> 163.82761 | I40: =+I39+H40 -> 2878.9728 | O40: =+O39+1 -> 34 | P40: =+'REGISTRO TOTAL'!$G$85 -> 11 | R40: =+R39-P40-Q40 -> 10733 | S40: =+'REGISTRO TOTAL'!$G$72 -> 1600 | T40: =+S40*1000/R40 -> 149.07295 | U40: =+U39+T40 -> 2760.9344
A41: =+A40+1 -> 45815 | C41: =+C40+1 -> 35 | D41: =+'REGISTRO TOTAL'!$H$34 -> 14 | F41: =+F40-D41-E41 -> 10729 | G41: =+'REGISTRO TOTAL'!$H$21 -> 1760 | H41: =+G41*1000/F41 -> 164.04138 | I41: =+I40+H41 -> 3043.0142 | J41: =+'REGISTRO TOTAL'!U21 -> 5045 | K41: =+J41-J34 -> 3595 | L41: =+(J41-$J$6)/C41 -> 142.88571 | M41: =+I41/J41 -> 0.60317427 | N41: 1880-1950 | O41: =+O40+1 -> 35 | P41: =+'REGISTRO TOTAL'!$H$85 -> 6 | R41: =+R40-P41-Q41 -> 10727 | S41: =+'REGISTRO TOTAL'!$H$72 -> 1600 | T41: =+S41*1000/R41 -> 149.15633 | U41: =+U40+T41 -> 2910.0907 | V41: =+'REGISTRO TOTAL'!U72 -> 1650 | W41: =+V41-V34 -> 517.5 | X41: =+(V41-$J$6)/O41 -> 45.885714 | Y41: =+U41/V41 -> 1.7636913 | Z41: 1750-1800
A42: =+A41+1 -> 45816 | B42: Semana 6 | C42: =+C41+1 -> 36 | D42: =+'REGISTRO TOTAL'!$B$35 -> 12 | F42: =+F41-D42-E42 -> 10717 | G42: =+'REGISTRO TOTAL'!$B$22 -> 1760 | H42: =+G42*1000/F42 -> 164.22506 | I42: =+I41+H42 -> 3207.2392 | K42: =+J42-J41 -> -5045 | L42: =+(J42-$J$6)/C42 -> -1.2222222 | M42: =+I42/J42 -> #DIV/0! | N42: Sube 100-90 gr dia | O42: =+O41+1 -> 36 | P42: =+'REGISTRO TOTAL'!$B$86 -> 7 | R42: =+R41-P42-Q42 -> 10720 | S42: =+'REGISTRO TOTAL'!$B$73 -> 1600 | T42: =+S42*1000/R42 -> 149.25373 | U42: =+U41+T42 -> 3059.3444 | W42: =+V42-V41 -> -1650 | X42: =+(V42-$J$6)/O42 -> -1.2222222 | Y42: =+U42/V42 -> #DIV/0! | Z42: Sube: 70gr- 80 x dia
A43: =+A42+1 -> 45817 | C43: =+C42+1 -> 37 | D43: =+'REGISTRO TOTAL'!$C$35 -> 10 | F43: =+F42-D43-E43 -> 10707 | G43: =+'REGISTRO TOTAL'!$C$22 -> 1760 | H43: =+G43*1000/F43 -> 164.37844 | I43: =+I42+H43 -> 3371.6177 | K43: =+J43-J42 -> 0 | L43: =+(J43-$J$6)/C43 -> -1.1891892 | M43: =+I43/J43 -> #DIV/0! | O43: =+O42+1 -> 37 | P43: =+'REGISTRO TOTAL'!$C$86 -> 7 | R43: =+R42-P43-Q43 -> 10713 | S43: =+'REGISTRO TOTAL'!$C$73 -> 1640 | T43: =+S43*1000/R43 -> 153.08504 | U43: =+U42+T43 -> 3212.4295 | W43: =+V43-V42 -> 0 | X43: =+(V43-$J$6)/O43 -> -1.1891892 | Y43: =+U43/V43 -> #DIV/0!
A44: =+A43+1 -> 45818 | C44: =+C43+1 -> 38 | D44: =+'REGISTRO TOTAL'!$D$35 -> 15 | F44: =+F43-D44-E44 -> 10692 | G44: =+'REGISTRO TOTAL'!$D$22 -> 1800 | H44: =+G44*1000/F44 -> 168.35017 | I44: =+I43+H44 -> 3539.9679 | K44: =+J44-J43 -> 0 | L44: =+(J44-$J$6)/C44 -> -1.1578947 | M44: =+I44/J44 -> #DIV/0! | O44: =+O43+1 -> 38 | P44: =+'REGISTRO TOTAL'!$D$86 -> 7 | R44: =+R43-P44-Q44 -> 10706 | S44: =+'REGISTRO TOTAL'!$D$73 -> 1640 | T44: =+S44*1000/R44 -> 153.18513 | U44: =+U43+T44 -> 3365.6146 | W44: =+V44-V43 -> 0 | X44: =+(V44-$J$6)/O44 -> -1.1578947 | Y44: =+U44/V44 -> #DIV/0!
A45: =+A44+1 -> 45819 | C45: =+C44+1 -> 39 | D45: =+'REGISTRO TOTAL'!$E$35 -> 14 | F45: =+F44-D45-E45 -> 10678 | G45: =+'REGISTRO TOTAL'!$E$22 -> 1800 | H45: =+G45*1000/F45 -> 168.57089 | I45: =+I44+H45 -> 3708.5387 | K45: =+J45-J44 -> 0 | L45: =+(J45-$J$6)/C45 -> -1.1282051 | M45: =+I45/J45 -> #DIV/0! | O45: =+O44+1 -> 39 | P45: =+'REGISTRO TOTAL'!$E$86 -> 6 | R45: =+R44-P45-Q45 -> 10700 | S45: =+'REGISTRO TOTAL'!$E$73 -> 1680 | T45: =+S45*1000/R45 -> 157.00935 | U45: =+U44+T45 -> 3522.624 | W45: =+V45-V44 -> 0 | X45: =+(V45-$J$6)/O45 -> -1.1282051 | Y45: =+U45/V45 -> #DIV/0!
A46: =+A45+1 -> 45820 | C46: =+C45+1 -> 40 | D46: =+'REGISTRO TOTAL'!$F$35 -> 12 | F46: =+F45-D46-E46 -> 10666 | G46: =+'REGISTRO TOTAL'!$F$22 -> 1840 | H46: =+G46*1000/F46 -> 172.51078 | I46: =+I45+H46 -> 3881.0495 | K46: =+J46-J45 -> 0 | L46: =+(J46-$J$6)/C46 -> -1.1 | M46: =+I46/J46 -> #DIV/0! | O46: =+O45+1 -> 40 | P46: =+'REGISTRO TOTAL'!$F$86 -> 6 | R46: =+R45-P46-Q46 -> 10694 | S46: =+'REGISTRO TOTAL'!$F$73 -> 1680 | T46: =+S46*1000/R46 -> 157.09744 | U46: =+U45+T46 -> 3679.7214 | W46: =+V46-V45 -> 0 | X46: =+(V46-$J$6)/O46 -> -1.1 | Y46: =+U46/V46 -> #DIV/0!
A47: =+A46+1 -> 45821 | C47: =+C46+1 -> 41 | D47: =+'REGISTRO TOTAL'!$G$35 -> 12 | F47: =+F46-D47-E47 -> 10654 | G47: =+'REGISTRO TOTAL'!$G$22 -> 1840 | H47: =+G47*1000/F47 -> 172.70509 | I47: =+I46+H47 -> 4053.7546 | K47: =+J47-J46 -> 0 | L47: =+(J47-$J$6)/C47 -> -1.0731707 | M47: =+I47/J47 -> #DIV/0! | O47: =+O46+1 -> 41 | P47: =+'REGISTRO TOTAL'!$G$86 -> 7 | R47: =+R46-P47-Q47 -> 10687 | S47: =+'REGISTRO TOTAL'!$G$73 -> 1680 | T47: =+S47*1000/R47 -> 157.20034 | U47: =+U46+T47 -> 3836.9217 | W47: =+V47-V46 -> 0 | X47: =+(V47-$J$6)/O47 -> -1.0731707 | Y47: =+U47/V47 -> #DIV/0!
A48: =+A47+1 -> 45822 | C48: =+C47+1 -> 42 | D48: =+'REGISTRO TOTAL'!$H$35 -> 15 | F48: =+F47-D48-E48 -> 10639 | G48: =+'REGISTRO TOTAL'!$H$22 -> 1800 | H48: =+G48*1000/F48 -> 169.18883 | I48: =+I47+H48 -> 4222.9435 | K48: =+J48-J47 -> 0 | L48: =+(J48-$J$6)/C48 -> -1.047619 | M48: =+I48/J48 -> #DIV/0! | O48: =+O47+1 -> 42 | P48: =+'REGISTRO TOTAL'!$H$86 -> 7 | R48: =+R47-P48-Q48 -> 10680 | S48: =+'REGISTRO TOTAL'!$H$73 -> 1680 | T48: =+S48*1000/R48 -> 157.30337 | U48: =+U47+T48 -> 3994.2251 | W48: =+V48-V47 -> 0 | X48: =+(V48-$J$6)/O48 -> -1.047619 | Y48: =+U48/V48 -> #DIV/0!
A49: =+A48+1 -> 45823 | B49: Semana 7 | C49: =+C48+1 -> 43 | D49: =+'REGISTRO TOTAL'!$B$36 -> 11 | F49: =+F48-D49-E49 -> 10628 | G49: =+'REGISTRO TOTAL'!$B$23 -> 1760 | H49: =+G49*1000/F49 -> 165.6003 | I49: =+I48+H49 -> 4388.5438 | K49: =+J49-J48 -> 0 | L49: =+(J49-$J$6)/C49 -> -1.0232558 | M49: =+I49/J49 -> #DIV/0! | O49: =+O48+1 -> 43 | P49: =+'REGISTRO TOTAL'!$B$87 -> 6 | R49: =+R48-P49-Q49 -> 10674 | S49: =+'REGISTRO TOTAL'!$B$74 -> 1680 | T49: =+S49*1000/R49 -> 157.39179 | U49: =+U48+T49 -> 4151.6169 | W49: =+V49-V48 -> 0 | X49: =+(V49-$J$6)/O49 -> -1.0232558 | Y49: =+U49/V49 -> #DIV/0!
A50: =+A49+1 -> 45824 | C50: =+C49+1 -> 44 | D50: =+'REGISTRO TOTAL'!$C$36 -> 13 | F50: =+F49-D50-E50 -> 10615 | G50: =+'REGISTRO TOTAL'!$C$23 -> 1760 | H50: =+G50*1000/F50 -> 165.80311 | I50: =+I49+H50 -> 4554.3469 | K50: =+J50-J49 -> 0 | L50: =+(J50-$J$6)/C50 -> -1 | M50: =+I50/J50 -> #DIV/0! | O50: =+O49+1 -> 44 | P50: =+'REGISTRO TOTAL'!$C$87 -> 7 | R50: =+R49-P50-Q50 -> 10667 | S50: =+'REGISTRO TOTAL'!$C$74 -> 1680 | T50: =+S50*1000/R50 -> 157.49508 | U50: =+U49+T50 -> 4309.112 | W50: =+V50-V49 -> 0 | X50: =+(V50-$J$6)/O50 -> -1 | Y50: =+U50/V50 -> #DIV/0!
A51: =+A50+1 -> 45825 | C51: =+C50+1 -> 45 | D51: =+'REGISTRO TOTAL'!$D$36 -> 13 | F51: =+F50-D51-E51 -> 10602 | G51: =+'REGISTRO TOTAL'!$D$23 -> 1720 | H51: =+G51*1000/F51 -> 162.23354 | I51: =+I50+H51 -> 4716.5804 | K51: =+J51-J50 -> 0 | L51: =+(J51-$J$6)/C51 -> -0.97777778 | M51: =+I51/J51 -> #DIV/0! | O51: =+O50+1 -> 45 | P51: =+'REGISTRO TOTAL'!$D$87 -> 7 | R51: =+R50-P51-Q51 -> 10660 | S51: =+'REGISTRO TOTAL'!$D$74 -> 1680 | T51: =+S51*1000/R51 -> 157.5985 | U51: =+U50+T51 -> 4466.7105 | W51: =+V51-V50 -> 0 | X51: =+(V51-$J$6)/O51 -> -0.97777778 | Y51: =+U51/V51 -> #DIV/0!
A52: =+A51+1 -> 45826 | C52: =+C51+1 -> 46 | D52: =+'REGISTRO TOTAL'!$E$36 -> 14 | E52: 2400 | F52: =+F51-D52-E52 -> 8188 | G52: =+'REGISTRO TOTAL'!$E$23 -> 1720 | H52: =+G52*1000/F52 -> 210.06351 | I52: =+I51+H52 -> 4926.6439 | K52: =+J52-J51 -> 0 | L52: =+(J52-$J$6)/C52 -> -0.95652174 | M52: =+I52/J52 -> #DIV/0! | O52: =+O51+1 -> 46 | P52: =+'REGISTRO TOTAL'!$E$87 -> 11 | R52: =+R51-P52-Q52 -> 10649 | S52: =+'REGISTRO TOTAL'!$E$74 -> 1680 | T52: =+S52*1000/R52 -> 157.76129 | U52: =+U51+T52 -> 4624.4718 | W52: =+V52-V51 -> 0 | X52: =+(V52-$J$6)/O52 -> -0.95652174 | Y52: =+U52/V52 -> #DIV/0!
A53: =+A52+1 -> 45827 | C53: =+C52+1 -> 47 | D53: =+'REGISTRO TOTAL'!$F$36 -> 10 | E53: 2000 | F53: =+F52-D53-E53 -> 6178 | G53: =+'REGISTRO TOTAL'!$F$23 -> 1400 | H53: =+G53*1000/F53 -> 226.61055 | I53: =+I52+H53 -> 5153.2545 | K53: =+J53-J52 -> 0 | L53: =+(J53-$J$6)/C53 -> -0.93617021 | M53: =+I53/J53 -> #DIV/0! | O53: =+O52+1 -> 47 | P53: =+'REGISTRO TOTAL'!$F$87 -> 10 | Q53: 1600 | R53: =+R52-P53-Q53 -> 9039 | S53: =+'REGISTRO TOTAL'!$F$74 -> 1680 | T53: =+S53*1000/R53 -> 185.86127 | U53: =+U52+T53 -> 4810.333 | W53: =+V53-V52 -> 0 | X53: =+(V53-$J$6)/O53 -> -0.93617021 | Y53: =+U53/V53 -> #DIV/0!
A54: =+A53+1 -> 45828 | C54: =+C53+1 -> 48 | D54: =+'REGISTRO TOTAL'!$G$36 -> 8 | E54: 6100 | F54: =+F53-D54-E54 -> 70 | G54: =+'REGISTRO TOTAL'!$G$23 -> 1120 | H54: =+G54*1000/F54 -> 16000 | I54: =+I53+H54 -> 21153.254 | K54: =+J54-J53 -> 0 | L54: =+(J54-$J$6)/C54 -> -0.91666667 | M54: =+I54/J54 -> #DIV/0! | O54: =+O53+1 -> 48 | P54: =+'REGISTRO TOTAL'!$G$87 -> 10 | Q54: 1500 | R54: =+R53-P54-Q54 -> 7529 | S54: =+'REGISTRO TOTAL'!$G$74 -> 1560 | T54: =+S54*1000/R54 -> 207.19883 | U54: =+U53+T54 -> 5017.5319 | W54: =+V54-V53 -> 0 | X54: =+(V54-$J$6)/O54 -> -0.91666667 | Y54: =+U54/V54 -> #DIV/0!
A55: =+A54+1 -> 45829 | C55: =+C54+1 -> 49 | D55: =+'REGISTRO TOTAL'!$H$36 -> 12 | F55: =+F54-D55-E55 -> 58 | G55: =+'REGISTRO TOTAL'!$H$23 -> 0 | H55: =+G55*1000/F55 -> 0 | I55: =+I54+H55 -> 21153.254 | K55: =+J55-J54 -> 0 | L55: =+(J55-$J$6)/C55 -> -0.89795918 | M55: =+I55/J55 -> #DIV/0! | O55: =+O54+1 -> 49 | P55: =+'REGISTRO TOTAL'!$H$87 -> 14 | R55: =+R54-P55-Q55 -> 7515 | S55: =+'REGISTRO TOTAL'!$H$74 -> 1360 | T55: =+S55*1000/R55 -> 180.97139 | U55: =+U54+T55 -> 5198.5033 | W55: =+V55-V54 -> 0 | X55: =+(V55-$J$6)/O55 -> -0.89795918 | Y55: =+U55/V55 -> #DIV/0!
A56: =+A55+1 -> 45830 | B56: Semana 8 | C56: =+C55+1 -> 50 | D56: =+'REGISTRO TOTAL'!$B$37 -> 0 | F56: =+F55-D56-E56 -> 58 | G56: =+'REGISTRO TOTAL'!$B$24 -> 0 | H56: =+G56*1000/F56 -> 0 | I56: =+I55+H56 -> 21153.254 | K56: =+J56-J55 -> 0 | L56: =+(J56-$J$6)/C56 -> -0.88 | M56: =+I56/J56 -> #DIV/0! | O56: =+O55+1 -> 50 | P56: =+'REGISTRO TOTAL'!$B$88 -> 0 | Q56: 2304 | R56: =+R55-P56-Q56 -> 5211 | S56: =+'REGISTRO TOTAL'!$B$75 -> 0 | T56: =+S56*1000/R56 -> 0 | U56: =+U55+T56 -> 5198.5033 | W56: =+V56-V55 -> 0 | X56: =+(V56-$J$6)/O56 -> -0.88 | Y56: =+U56/V56 -> #DIV/0!
A57: =+A56+1 -> 45831 | C57: =+C56+1 -> 51 | D57: =+'REGISTRO TOTAL'!$C$37 -> 0 | F57: =+F56-D57-E57 -> 58 | G57: =+'REGISTRO TOTAL'!$C$24 -> 0 | H57: =+G57*1000/F57 -> 0 | I57: =+I56+H57 -> 21153.254 | K57: =+J57-J56 -> 0 | L57: =+(J57-$J$6)/C57 -> -0.8627451 | M57: =+I57/J57 -> #DIV/0! | O57: =+O56+1 -> 51 | P57: =+'REGISTRO TOTAL'!$C$88 -> 0 | Q57: 5301 | R57: =+R56-P57-Q57 -> -90 | S57: =+'REGISTRO TOTAL'!$C$75 -> 0 | T57: =+S57*1000/R57 -> 0 | U57: =+U56+T57 -> 5198.5033 | W57: =+V57-V56 -> 0 | X57: =+(V57-$J$6)/O57 -> -0.8627451 | Y57: =+U57/V57 -> #DIV/0!
A58: =+A57+1 -> 45832 | C58: =+C57+1 -> 52 | D58: =+'REGISTRO TOTAL'!$D$37 -> 0 | F58: =+F57-D58-E58 -> 58 | G58: =+'REGISTRO TOTAL'!$D$24 -> 0 | H58: =+G58*1000/F58 -> 0 | I58: =+I57+H58 -> 21153.254 | K58: =+J58-J57 -> 0 | L58: =+(J58-$J$6)/C58 -> -0.84615385 | M58: =+I58/J58 -> #DIV/0! | O58: =+O57+1 -> 52 | P58: =+'REGISTRO TOTAL'!$D$88 -> 0 | R58: =+R57-P58-Q58 -> -90 | S58: =+'REGISTRO TOTAL'!$D$75 -> 0 | T58: =+S58*1000/R58 -> 0 | U58: =+U57+T58 -> 5198.5033 | W58: =+V58-V57 -> 0 | X58: =+(V58-$J$6)/O58 -> -0.84615385 | Y58: =+U58/V58 -> #DIV/0!
A59: =+A58+1 -> 45833 | C59: =+C58+1 -> 53 | D59: =+'REGISTRO TOTAL'!$E$37 -> 0 | F59: =+F58-D59-E59 -> 58 | G59: =+'REGISTRO TOTAL'!$E$24 -> 0 | H59: =+G59*1000/F59 -> 0 | I59: =+I58+H59 -> 21153.254 | K59: =+J59-J58 -> 0 | L59: =+(J59-$J$6)/C59 -> -0.83018868 | M59: =+I59/J59 -> #DIV/0! | O59: =+O58+1 -> 53 | P59: =+'REGISTRO TOTAL'!$E$88 -> 0 | R59: =+R58-P59-Q59 -> -90 | S59: =+'REGISTRO TOTAL'!$E$75 -> 0 | T59: =+S59*1000/R59 -> 0 | U59: =+U58+T59 -> 5198.5033 | W59: =+V59-V58 -> 0 | X59: =+(V59-$J$6)/O59 -> -0.83018868 | Y59: =+U59/V59 -> #DIV/0!
A60: =+A59+1 -> 45834 | C60: =+C59+1 -> 54 | D60: =+'REGISTRO TOTAL'!$F$37 -> 0 | F60: =+F59-D60-E60 -> 58 | G60: =+'REGISTRO TOTAL'!$F$24 -> 0 | H60: =+G60*1000/F60 -> 0 | I60: =+I59+H60 -> 21153.254 | K60: =+J60-J59 -> 0 | L60: =+(J60-$J$6)/C60 -> -0.81481481 | M60: =+I60/J60 -> #DIV/0! | O60: =+O59+1 -> 54 | P60: =+'REGISTRO TOTAL'!$F$88 -> 0 | R60: =+R59-P60-Q60 -> -90 | S60: =+'REGISTRO TOTAL'!$F$75 -> 0 | T60: =+S60*1000/R60 -> 0 | U60: =+U59+T60 -> 5198.5033 | W60: =+V60-V59 -> 0 | X60: =+(V60-$J$6)/O60 -> -0.81481481 | Y60: =+U60/V60 -> #DIV/0!
A61: =+A60+1 -> 45835 | C61: =+C60+1 -> 55 | D61: =+'REGISTRO TOTAL'!$G$37 -> 0 | F61: =+F60-D61-E61 -> 58 | G61: =+'REGISTRO TOTAL'!$G$24 -> 0 | H61: =+G61*1000/F61 -> 0 | I61: =+I60+H61 -> 21153.254 | K61: =+J61-J60 -> 0 | L61: =+(J61-$J$6)/C61 -> -0.8 | M61: =+I61/J61 -> #DIV/0! | O61: =+O60+1 -> 55 | P61: =+'REGISTRO TOTAL'!$G$88 -> 0 | R61: =+R60-P61-Q61 -> -90 | S61: =+'REGISTRO TOTAL'!$G$75 -> 0 | T61: =+S61*1000/R61 -> 0 | U61: =+U60+T61 -> 5198.5033 | W61: =+V61-V60 -> 0 | X61: =+(V61-$J$6)/O61 -> -0.8 | Y61: =+U61/V61 -> #DIV/0!
A62: =+A61+1 -> 45836 | C62: =+C61+1 -> 56 | D62: =+'REGISTRO TOTAL'!$H$37 -> 0 | F62: =+F61-D62-E62 -> 58 | G62: =+'REGISTRO TOTAL'!$H$24 -> 0 | H62: =+G62*1000/F62 -> 0 | I62: =+I61+H62 -> 21153.254 | K62: =+J62-J61 -> 0 | L62: =+(J62-$J$6)/C62 -> -0.78571429 | M62: =+I62/J62 -> #DIV/0! | O62: =+O61+1 -> 56 | P62: =+'REGISTRO TOTAL'!$H$88 -> 0 | R62: =+R61-P62-Q62 -> -90 | S62: =+'REGISTRO TOTAL'!$H$75 -> 0 | T62: =+S62*1000/R62 -> 0 | U62: =+U61+T62 -> 5198.5033 | W62: =+V62-V61 -> 0 | X62: =+(V62-$J$6)/O62 -> -0.78571429 | Y62: =+U62/V62 -> #DIV/0!
A63: =+A62+1 -> 45837 | B63: Semana 9 | C63: =+C62+1 -> 57 | D63: =+'REGISTRO TOTAL'!$B$38 -> 0 | F63: =+F62-D63-E63 -> 58 | G63: =+'REGISTRO TOTAL'!$B$25 -> 0 | H63: =+G63*1000/F63 -> 0 | I63: =+I62+H63 -> 21153.254 | K63: =+J63-J62 -> 0 | L63: =+(J63-$J$6)/C63 -> -0.77192982 | M63: =+I63/J63 -> #DIV/0! | O63: =+O62+1 -> 57 | P63: =+'REGISTRO TOTAL'!$B$89 -> 0 | R63: =+R62-P63-Q63 -> -90 | S63: =+'REGISTRO TOTAL'!$B$76 -> 0 | T63: =+S63*1000/R63 -> 0 | U63: =+U62+T63 -> 5198.5033 | W63: =+V63-V62 -> 0 | X63: =+(V63-$J$6)/O63 -> -0.77192982 | Y63: =+U63/V63 -> #DIV/0!
A64: =+A63+1 -> 45838 | C64: =+C63+1 -> 58 | D64: =+'REGISTRO TOTAL'!$C$38 -> 0 | F64: =+F63-D64-E64 -> 58 | G64: =+'REGISTRO TOTAL'!$C$25 -> 0 | H64: =+G64*1000/F64 -> 0 | I64: =+I63+H64 -> 21153.254 | K64: =+J64-J63 -> 0 | L64: =+(J64-$J$6)/C64 -> -0.75862069 | M64: =+I64/J64 -> #DIV/0! | O64: =+O63+1 -> 58 | P64: =+'REGISTRO TOTAL'!$C$89 -> 0 | R64: =+R63-P64-Q64 -> -90 | S64: =+'REGISTRO TOTAL'!$C$76 -> 0 | T64: =+S64*1000/R64 -> 0 | U64: =+U63+T64 -> 5198.5033 | W64: =+V64-V63 -> 0 | X64: =+(V64-$J$6)/O64 -> -0.75862069 | Y64: =+U64/V64 -> #DIV/0!
A65: =+A64+1 -> 45839 | C65: =+C64+1 -> 59 | D65: =+'REGISTRO TOTAL'!$D$38 -> 0 | F65: =+F64-D65-E65 -> 58 | G65: =+'REGISTRO TOTAL'!$D$25 -> 0 | H65: =+G65*1000/F65 -> 0 | I65: =+I64+H65 -> 21153.254 | K65: =+J65-J64 -> 0 | L65: =+(J65-$J$6)/C65 -> -0.74576271 | M65: =+I65/J65 -> #DIV/0! | O65: =+O64+1 -> 59 | P65: =+'REGISTRO TOTAL'!$D$89 -> 0 | R65: =+R64-P65-Q65 -> -90 | S65: =+'REGISTRO TOTAL'!$D$76 -> 0 | T65: =+S65*1000/R65 -> 0 | U65: =+U64+T65 -> 5198.5033 | W65: =+V65-V64 -> 0 | X65: =+(V65-$J$6)/O65 -> -0.74576271 | Y65: =+U65/V65 -> #DIV/0!
A66: =+A65+1 -> 45840 | C66: =+C65+1 -> 60 | D66: =+'REGISTRO TOTAL'!$E$38 -> 0 | F66: =+F65-D66-E66 -> 58 | G66: =+'REGISTRO TOTAL'!$E$25 -> 0 | H66: =+G66*1000/F66 -> 0 | I66: =+I65+H66 -> 21153.254 | K66: =+J66-J65 -> 0 | L66: =+(J66-$J$6)/C66 -> -0.73333333 | M66: =+I66/J66 -> #DIV/0! | O66: =+O65+1 -> 60 | P66: =+'REGISTRO TOTAL'!$E$89 -> 0 | R66: =+R65-P66-Q66 -> -90 | S66: =+'REGISTRO TOTAL'!$E$76 -> 0 | T66: =+S66*1000/R66 -> 0 | U66: =+U65+T66 -> 5198.5033 | W66: =+V66-V65 -> 0 | X66: =+(V66-$J$6)/O66 -> -0.73333333 | Y66: =+U66/V66 -> #DIV/0!
A67: =+A66+1 -> 45841 | C67: =+C66+1 -> 61 | D67: =+'REGISTRO TOTAL'!$F$38 -> 0 | F67: =+F66-D67-E67 -> 58 | G67: =+'REGISTRO TOTAL'!$F$25 -> 0 | H67: =+G67*1000/F67 -> 0 | I67: =+I66+H67 -> 21153.254 | K67: =+J67-J66 -> 0 | L67: =+(J67-$J$6)/C67 -> -0.72131148 | M67: =+I67/J67 -> #DIV/0! | O67: =+O66+1 -> 61 | P67: =+'REGISTRO TOTAL'!$F$89 -> 0 | R67: =+R66-P67-Q67 -> -90 | S67: =+'REGISTRO TOTAL'!$F$76 -> 0 | T67: =+S67*1000/R67 -> 0 | U67: =+U66+T67 -> 5198.5033 | W67: =+V67-V66 -> 0 | X67: =+(V67-$J$6)/O67 -> -0.72131148 | Y67: =+U67/V67 -> #DIV/0!
A68: =+A67+1 -> 45842 | C68: =+C67+1 -> 62 | D68: =+'REGISTRO TOTAL'!$G$38 -> 0 | F68: =+F67-D68-E68 -> 58 | G68: =+'REGISTRO TOTAL'!$G$25 -> 0 | H68: =+G68*1000/F68 -> 0 | I68: =+I67+H68 -> 21153.254 | K68: =+J68-J67 -> 0 | L68: =+(J68-$J$6)/C68 -> -0.70967742 | M68: =+I68/J68 -> #DIV/0! | O68: =+O67+1 -> 62 | P68: =+'REGISTRO TOTAL'!$G$89 -> 0 | R68: =+R67-P68-Q68 -> -90 | S68: =+'REGISTRO TOTAL'!$G$76 -> 0 | T68: =+S68*1000/R68 -> 0 | U68: =+U67+T68 -> 5198.5033 | W68: =+V68-V67 -> 0 | X68: =+(V68-$J$6)/O68 -> -0.70967742 | Y68: =+U68/V68 -> #DIV/0!
A69: =+A68+1 -> 45843 | C69: =+C68+1 -> 63 | D69: =+'REGISTRO TOTAL'!$H$38 -> 0 | F69: =+F68-D69-E69 -> 58 | G69: =+'REGISTRO TOTAL'!$H$25 -> 0 | H69: =+G69*1000/F69 -> 0 | I69: =+I68+H69 -> 21153.254 | K69: =+J69-J68 -> 0 | L69: =+(J69-$J$6)/C69 -> -0.6984127 | M69: =+I69/J69 -> #DIV/0! | O69: =+O68+1 -> 63 | P69: =+'REGISTRO TOTAL'!$H$89 -> 0 | R69: =+R68-P69-Q69 -> -90 | S69: =+'REGISTRO TOTAL'!$H$76 -> 0 | T69: =+S69*1000/R69 -> 0 | U69: =+U68+T69 -> 5198.5033 | W69: =+V69-V68 -> 0 | X69: =+(V69-$J$6)/O69 -> -0.6984127 | Y69: =+U69/V69 -> #DIV/0!

Sheet INVENTARIO
B1: BODEGA
B4: FECHA | C4: Nº FACTURA | D4: DETALLE | E4: ENTRADA | F4: VALOR | G4: CONSUMO | H4: INVENTARIO
B5: 45778 | C5: BODEGA MENESES RM-4387 | D5: PREINICIO P AVSL PREMEX | E5: 100 | F5: 9680000 | H5: =+E5-G5 -> 100
A6: 1 | B6: =+'REGISTRO TOTAL'!G8 -> 45780 | G6: =+'REGISTRO TOTAL'!B119/40 -> 8.5 | H6: =+H5+E6-G6 -> 91.5
A7: 2 | B7: =+B6+1 -> 45781 | G7: =+'REGISTRO TOTAL'!C119/40 -> 9 | H7: =+H6+E7-G7 -> 82.5
A8: 3 | B8: =+B7+1 -> 45782 | G8: =+'REGISTRO TOTAL'!D119/40 -> 10.5 | H8: =+H7+E8-G8 -> 72
A9: 4 | B9: =+B8+1 -> 45783 | G9: =+'REGISTRO TOTAL'!E119/40 -> 13 | H9: =+H8+E9-G9 -> 59
A10: 5 | B10: =+B9+1 -> 45784 | G10: =+'REGISTRO TOTAL'!F119/40 -> 14 | H10: =+H9+E10-G10 -> 45
A11: 6 | B11: =+B10+1 -> 45785 | G11: =+'REGISTRO TOTAL'!G119/40 -> 15 | H11: =+H10+E11-G11 -> 30
A12: 7 | B12: =+B11+1 -> 45786 | G12: =+'REGISTRO TOTAL'!H119/40 -> 18 | H12: =+H11+E12-G12 -> 12
A13: 8 | B13: =+B12+1 -> 45787 | C13: BODEGA MENESES RM-4401 | D13: INICIO P AVSL PREMEX | E13: 98 | F13: 9368800 | G13: =+'REGISTRO TOTAL'!B$120/40 -> 19 | H13: =+H12+E13-G13 -> 91
A14: 9 | B14: =+B13+1 -> 45788 | G14: =+'REGISTRO TOTAL'!C$120/40 -> 20.5 | H14: =+H13+E14-G14 -> 70.5
A15: 10 | B15: =+B14+1 -> 45789 | G15: =+'REGISTRO TOTAL'!D$120/40 -> 23 | H15: =+H14+E15-G15 -> 47.5
A16: 11 | B16: =+B15+1 -> 45790 | G16: =+'REGISTRO TOTAL'!E$120/40 -> 27 | H16: =+H15+E16-G16 -> 20.5
A17: 12 | B17: =+B16+1 -> 45791 | C17: BODEGA MENESES RM-4407 | D17: INICIO P AVSL PREMEX | E17: 75 | F17: 7170000 | G17: =+'REGISTRO TOTAL'!F$120/40 -> 31 | H17: =+H16+E17-G17 -> 64.5
A18: 13 | B18: =+B17+1 -> 45792 | G18: =+'REGISTRO TOTAL'!G$120/40 -> 32.5 | H18: =+H17+E18-G18 -> 32
A19: 14 | B19: =+B18+1 -> 45793 | G19: =+'REGISTRO TOTAL'!H$120/40 -> 36 | H19: =+H18+E19-G19 -> -4
A20: 15 | B20: =+B19+1 -> 45794 | C20: 5021444474 RM 4934 | D20: S-NUTREPOLLO CR 40 KG | E20: 85 | F20: 7989931.3 | G20: =+'REGISTRO TOTAL'!B$121/40 -> 37 | H20: =+H19+E20-G20 -> 44
A21: 16 | B21: =+B20+1 -> 45795 | G21: =+'REGISTRO TOTAL'!C$121/40 -> 39 | H21: =+H20+E21-G21 -> 5
A22: 17 | B22: =+B21+1 -> 45796 | G22: =+'REGISTRO TOTAL'!D$121/40 -> 43 | H22: =+H21+E22-G22 -> -38
A23: 18 | B23: =+B22+1 -> 45797 | C23: BODEGA MENESES RM-4417 | D23: INICIO P AVSL PREMEX | E23: 95 | F23: 9253000 | G23: =+'REGISTRO TOTAL'!E$121/40 -> 44 | H23: =+H22+E23-G23 -> 13
A24: 19 | B24: =+B23+1 -> 45798 | C24: BODEGA MENESES RM-4420 | D24: INICIO P AVSL PREMEX | E24: 50 | F24: 4870000 | G24: =+'REGISTRO TOTAL'!F$121/40 -> 47 | H24: =+H23+E24-G24 -> 16
A25: 20 | B25: =+B24+1 -> 45799 | C25: BODEGA MENESES RM-4422 | D25: INICIO P AVSL PREMEX | E25: 80 | F25: 7792000 | G25: =+'REGISTRO TOTAL'!G$121/40 -> 51 | H25: =+H24+E25-G25 -> 45
A26: 21 | B26: =+B25+1 -> 45800 | C26: BODEGA MENESES RM-4426 | D26: ENGORDE P AVSL PREMEX | E26: 160 | F26: 15264000 | G26: =+'REGISTRO TOTAL'!H$121/40 -> 52 | H26: =+H25+E26-G26 -> 153
B27: 45799 | C27: BODEGA MENESES RM-4427 | D27: ENGORDE P AVSL PREMEX | E27: 100 | F27: 9540000 | H27: =+H26+E27-G27 -> 253
A28: 22 | B28: =+B26+1 -> 45801 | C28: BODEGA MENESES RM-4430 | D28: ENGORDE P AVSL PREMEX | E28: 44 | F28: 4197600 | G28: =+'REGISTRO TOTAL'!B$122/40 -> 54 | H28: =+H27+E28-G28 -> 243
